Workbook

Sheet DASHBOARD
B2: 🏛 LOHAGARA PROVATI YOUTH ORGANIZATION
B3: Kamar Pukur Par, Uzir Hat, Lohagara, Chittagong · MANAGEMENT CONTROL DASHBOARD
B5: 📊 KEY PERFORMANCE INDICATORS
B6: 🏦 Net Fund (BDT) | K6: DPS Investment | L6: =B15 -> 2050000
B7: ='Central Fund Control'!B20 -> 5036580.2 | K7: FDR Investment | L7: =D15 -> 500000
B8: 👥 Total Members | D8: 📋 Total Shares | F8: 💰 Per Share/Month | H8: 📈 Expected Total | K8: Savings Balance | L8: =F15 -> 491280.17
B9: =COUNTA('Member Wise Deposit Summary'!$B$4:$B$80) -> 77 | D9: ='Member Wise Deposit Summary'!E81 -> 125 | F9: 1000 | H9: =125*1000*(COUNTIF('Month Wise Collection Summary'!C4:C10,">0")+COUNTIF('Month Wise Collection Summary'!C12:C23,">0")+COUNTIF('Month Wise Collection Summary'!C25:C36,">0")+COUNTIF('Month Wise Collection Summary'!C38:C49,">0")+COUNTIF('Month Wise Collection Summary'!C51:C62,">0")+COUNTIF('Month Wise Collection Summary'!C64:C75,">0")) -> 5125000 | K9: CNG Due | L9: =H15 -> 1239500
B10: ✅ Regular Collection | D10: ⏩ Advance Collection | F10: ⏳ Due Collection | H10: ⚠ Fine Collection | K10: Loan Due | L10: =H13 -> 758600
B11: ='Month Wise Collection Summary'!C77 -> 4493000 | D11: ='Month Wise Collection Summary'!D77 -> 216000 | F11: ='Month Wise Collection Summary'!E77 -> 375000 | H11: ='Month Wise Collection Summary'!F77 -> 23150
B12: 🎫 Entry Fee (BDT) | D12: 💸 Total Expenses | F12: 📊 Reconciliation | H12: 🏛 Loan Receivable
B13: ='Member Wise Deposit Summary'!F81 -> 12500 | D13: ='Month Wise Collection Summary'!H77 -> 83069.83 | F13: =IF(SUM((B11+D11+F11+H11+B13+B17))=SUM(D13+H13+B15+D15+F15+H15),"✔ BALANCED","⚠ WARNING — MISMATCH DETECTED") -> ✔ BALANCED | H13: ='Central Fund Control'!D9 -> 758600
B14: 🏧 DPS Investment | D14: 🏛 FDR Investment | F14: 💳 Savings Balance | H14: 🚗 CNG Receivable
B15: ='Central Fund Control'!D5 -> 2050000 | D15: ='Central Fund Control'!D6 -> 500000 | F15: ='Central Fund Control'!D7 -> 491280.17 | H15: ='Central Fund Control'!D8 -> 1239500
B16: Savings A/c Interest
B17: ='Central Fund Control'!B10 -> 2800
B19: 🗂 QUICK NAVIGATION — Click any button to jump to that sheet
B20: =HYPERLINK("#'Member Wise Deposit Summary'!A1","👥 Member Deposits") -> 👥 Member Deposits | D20: =HYPERLINK("#'Month Wise Collection Summary'!A1","📅 Monthly Collections") -> 📅 Monthly Collections | F20: =HYPERLINK("#'Month Wise Expenses'!A1","💸 Month Expenses") -> 💸 Month Expenses | H20: =HYPERLINK("#'Monthly Collection-2023'!A1","📋 Collection 2023") -> 📋 Collection 2023
B21: =HYPERLINK("#'Monthly Collection-2024)'!A1","📋 Collection 2024") -> 📋 Collection 2024 | D21: =HYPERLINK("#'Monthly Collection-2025'!A1","📋 Collection 2025") -> 📋 Collection 2025 | F21: =HYPERLINK("#'Monthly Collection-2026'!A1","📋 Collection 2026") -> 📋 Collection 2026 | H21: =HYPERLINK("#'Monthly Collection-2027'!A1","📋 Collection 2027") -> 📋 Collection 2027
B22: =HYPERLINK("#'Monthly Collection-2028'!A1","📋 Collection 2028") -> 📋 Collection 2028 | D22: =HYPERLINK("#'CNG 1 (Zohir Ahmed)'!A1","🚗 CNG 1 – Zohir") -> 🚗 CNG 1 – Zohir | F22: =HYPERLINK("#'CNG 2 (Abu Taher)'!A1","🚗 CNG 2 – Taher") -> 🚗 CNG 2 – Taher | H22: =HYPERLINK("#'CNG 3 (Zahedul Islam)'!A1","🚗 CNG 3 – Zahedul") -> 🚗 CNG 3 – Zahedul
B23: =HYPERLINK("#'CNG 4 (Sajal Barua)'!A1","🚗 CNG 4 – Sajal") -> 🚗 CNG 4 – Sajal | D23: =HYPERLINK("#'CNG 5 (Nurul Abser)'!A1","🚗 CNG 5 – Nurul") -> 🚗 CNG 5 – Nurul | F23: =HYPERLINK("#'CNG 6 (Abdul Malek)'!A1","🚗 CNG 6 – Malek") -> 🚗 CNG 6 – Malek | H23: =HYPERLINK("#'Auto Rikshwa (Kamal Uddin)'!A1","🚗 Auto – Kamal") -> 🚗 Auto – Kamal
B24: =HYPERLINK("#'CNG 7 (Md. Yousof)'!A1","🚗 CNG 7 – Yousof") -> 🚗 CNG 7 – Yousof | D24: =HYPERLINK("#'CNG 8 (Md. Alamgir'!A1","🚗 CNG 8 – Alamgir") -> 🚗 CNG 8 – Alamgir | F24: =HYPERLINK("#'CNG Summary'!A1","📈 CNG Summary") -> 📈 CNG Summary | H24: =HYPERLINK("#'Month Wise CNG Instlmnt Summary'!A1","📉 Month Wise CNG Installment Summary") -> 📉 Month Wise CNG Installment Summary
B25: =HYPERLINK("#'Loan Collection Summary'!A1","💼 Loan Summary") -> 💼 Loan Summary | D25: =HYPERLINK("#'Central Fund Control'!A1","🏦 Fund Control") -> 🏦 Fund Control | F25: =HYPERLINK("#'Investment Register'!A1","💹 Investments") -> 💹 Investments | H25: =HYPERLINK("#'Profit & Loss'!A1","📉 P&L Statement") -> 📉 P&L Statement
B26: =HYPERLINK("#'Share Maturity'!A1","🏁 Share Maturity") -> 🏁 Share Maturity | D26: =HYPERLINK("#'Member Final Receivable'!A1","👤 Final Receivable") -> 👤 Final Receivable
B27: Lohagara Provati Youth Organization · Dashboard v2.0 · Values auto-calculated from source sheets

Sheet Member Wise Deposit Summary
A1: =HYPERLINK("#DASHBOARD!A1","⬅ Dashboard") -> ⬅ Dashboard
B2: Lohagara Provati Youth Organization Kamar Pukur Par, Uzir Hat, Lohagara, Chittagong.
B3: Member ID | C3: Name | D3: Mobile Number | E3: Number of Shares | F3: Entry Fee (Per Share Tk.100/=) | G3: Till Date Total Deposit | H3: Total Fine | I3: Status
B4: ='Monthly Collection-2023'!B4 -> 1 | C4: ='Monthly Collection-2023'!C4 -> Monjurul Islam | D4: 1814824030 | E4: ='Monthly Collection-2023'!E4 -> 3 | F4: =E4*100 -> 300 | G4: ='Monthly Collection-2023'!AH4+'Monthly Collection-2024)'!BB4+'Monthly Collection-2025'!BB4+'Monthly Collection-2026'!BB4+'Monthly Collection-2027'!BB4+'Monthly Collection-2028'!BB4 -> 123000 | H4: ='Monthly Collection-2023'!AI4+'Monthly Collection-2024)'!BC4+'Monthly Collection-2025'!BC4+'Monthly Collection-2026'!BC4+'Monthly Collection-2027'!BC4+'Monthly Collection-2028'!BC4 -> 300 | I4: =IF(G4>(E4*1000*41),"Advanced",IF(G4<(E4*1000*41),"Due","Regular")) -> Regular
B5: ='Monthly Collection-2023'!B5 -> 2 | C5: ='Monthly Collection-2023'!C5 -> Saiful Islam | D5: 1816724075 | E5: ='Monthly Collection-2023'!E5 -> 2 | F5: =E5*100 -> 200 | G5: ='Monthly Collection-2023'!AH5+'Monthly Collection-2024)'!BB5+'Monthly Collection-2025'!BB5+'Monthly Collection-2026'!BB5+'Monthly Collection-2027'!BB5+'Monthly Collection-2028'!BB5 -> 82000 | H5: ='Monthly Collection-2023'!AI5+'Monthly Collection-2024)'!BC5+'Monthly Collection-2025'!BC5+'Monthly Collection-2026'!BC5+'Monthly Collection-2027'!BC5+'Monthly Collection-2028'!BC5 -> 0 | I5: =IF(G5>(E5*1000*41),"Advanced",IF(G5<(E5*1000*41),"Due","Regular")) -> Regular
B6: ='Monthly Collection-2023'!B6 -> 3 | C6: ='Monthly Collection-2023'!C6 -> Mohammad Tawhidul Islam | D6: 1846506898 | E6: ='Monthly Collection-2023'!E6 -> 2 | F6: =E6*100 -> 200 | G6: ='Monthly Collection-2023'!AH6+'Monthly Collection-2024)'!BB6+'Monthly Collection-2025'!BB6+'Monthly Collection-2026'!BB6+'Monthly Collection-2027'!BB6+'Monthly Collection-2028'!BB6 -> 82000 | H6: ='Monthly Collection-2023'!AI6+'Monthly Collection-2024)'!BC6+'Monthly Collection-2025'!BC6+'Monthly Collection-2026'!BC6+'Monthly Collection-2027'!BC6+'Monthly Collection-2028'!BC6 -> 100 | I6: =IF(G6>(E6*1000*41),"Advanced",IF(G6<(E6*1000*41),"Due","Regular")) -> Regular
B7: ='Monthly Collection-2023'!B7 -> 4 | C7: ='Monthly Collection-2023'!C7 -> Amanat Khan | D7: 966551311461 | E7: ='Monthly Collection-2023'!E7 -> 5 | F7: =E7*100 -> 500 | G7: ='Monthly Collection-2023'!AH7+'Monthly Collection-2024)'!BB7+'Monthly Collection-2025'!BB7+'Monthly Collection-2026'!BB7+'Monthly Collection-2027'!BB7+'Monthly Collection-2028'!BB7 -> 205000 | H7: ='Monthly Collection-2023'!AI7+'Monthly Collection-2024)'!BC7+'Monthly Collection-2025'!BC7+'Monthly Collection-2026'!BC7+'Monthly Collection-2027'!BC7+'Monthly Collection-2028'!BC7 -> 0 | I7: =IF(G7>(E7*1000*41),"Advanced",IF(G7<(E7*1000*41),"Due","Regular")) -> Regular
B8: ='Monthly Collection-2023'!B8 -> 5 | C8: ='Monthly Collection-2023'!C8 -> Nurunnabi Hosen Tanzid | D8: 1838848678 | E8: ='Monthly Collection-2023'!E8 -> 2 | F8: =E8*100 -> 200 | G8: ='Monthly Collection-2023'!AH8+'Monthly Collection-2024)'!BB8+'Monthly Collection-2025'!BB8+'Monthly Collection-2026'!BB8+'Monthly Collection-2027'!BB8+'Monthly Collection-2028'!BB8 -> 82000 | H8: ='Monthly Collection-2023'!AI8+'Monthly Collection-2024)'!BC8+'Monthly Collection-2025'!BC8+'Monthly Collection-2026'!BC8+'Monthly Collection-2027'!BC8+'Monthly Collection-2028'!BC8 -> 300 | I8: =IF(G8>(E8*1000*41),"Advanced",IF(G8<(E8*1000*41),"Due","Regular")) -> Regular
B9: ='Monthly Collection-2023'!B9 -> 6 | C9: ='Monthly Collection-2023'!C9 -> Jashim Uddin | D9: 966538760537 | E9: ='Monthly Collection-2023'!E9 -> 2 | F9: =E9*100 -> 200 | G9: ='Monthly Collection-2023'!AH9+'Monthly Collection-2024)'!BB9+'Monthly Collection-2025'!BB9+'Monthly Collection-2026'!BB9+'Monthly Collection-2027'!BB9+'Monthly Collection-2028'!BB9 -> 82000 | H9: ='Monthly Collection-2023'!AI9+'Monthly Collection-2024)'!BC9+'Monthly Collection-2025'!BC9+'Monthly Collection-2026'!BC9+'Monthly Collection-2027'!BC9+'Monthly Collection-2028'!BC9 -> 0 | I9: =IF(G9>(E9*1000*41),"Advanced",IF(G9<(E9*1000*41),"Due","Regular")) -> Regular
B10: ='Monthly Collection-2023'!B10 -> 7 | C10: ='Monthly Collection-2023'!C10 -> Shibu Sankar Karmaker | D10: 1885946523 | E10: ='Monthly Collection-2023'!E10 -> 2 | F10: =E10*100 -> 200 | G10: ='Monthly Collection-2023'!AH10+'Monthly Collection-2024)'!BB10+'Monthly Collection-2025'!BB10+'Monthly Collection-2026'!BB10+'Monthly Collection-2027'!BB10+'Monthly Collection-2028'!BB10 -> 82000 | H10: ='Monthly Collection-2023'!AI10+'Monthly Collection-2024)'!BC10+'Monthly Collection-2025'!BC10+'Monthly Collection-2026'!BC10+'Monthly Collection-2027'!BC10+'Monthly Collection-2028'!BC10 -> 0 | I10: =IF(G10>(E10*1000*41),"Advanced",IF(G10<(E10*1000*41),"Due","Regular")) -> Regular
B11: ='Monthly Collection-2023'!B11 -> 8 | C11: ='Monthly Collection-2023'!C11 -> Monsur | D11: 1608632799 | E11: ='Monthly Collection-2023'!E11 -> 2 | F11: =E11*100 -> 200 | G11: ='Monthly Collection-2023'!AH11+'Monthly Collection-2024)'!BB11+'Monthly Collection-2025'!BB11+'Monthly Collection-2026'!BB11+'Monthly Collection-2027'!BB11+'Monthly Collection-2028'!BB11 -> 82000 | H11: ='Monthly Collection-2023'!AI11+'Monthly Collection-2024)'!BC11+'Monthly Collection-2025'!BC11+'Monthly Collection-2026'!BC11+'Monthly Collection-2027'!BC11+'Monthly Collection-2028'!BC11 -> 0 | I11: =IF(G11>(E11*1000*41),"Advanced",IF(G11<(E11*1000*41),"Due","Regular")) -> Regular
B12: ='Monthly Collection-2023'!B12 -> 9 | C12: ='Monthly Collection-2023'!C12 -> Monjur Alam | D12: 1811938007 | E12: ='Monthly Collection-2023'!E12 -> 2 | F12: =E12*100 -> 200 | G12: ='Monthly Collection-2023'!AH12+'Monthly Collection-2024)'!BB12+'Monthly Collection-2025'!BB12+'Monthly Collection-2026'!BB12+'Monthly Collection-2027'!BB12+'Monthly Collection-2028'!BB12 -> 82000 | H12: ='Monthly Collection-2023'!AI12+'Monthly Collection-2024)'!BC12+'Monthly Collection-2025'!BC12+'Monthly Collection-2026'!BC12+'Monthly Collection-2027'!BC12+'Monthly Collection-2028'!BC12 -> 100 | I12: =IF(G12>(E12*1000*41),"Advanced",IF(G12<(E12*1000*41),"Due","Regular")) -> Regular
B13: ='Monthly Collection-2023'!B13 -> 10 | C13: ='Monthly Collection-2023'!C13 -> Rupal Kanti Karmaker | D13: 1812934934 | E13: ='Monthly Collection-2023'!E13 -> 1 | F13: =E13*100 -> 100 | G13: ='Monthly Collection-2023'!AH13+'Monthly Collection-2024)'!BB13+'Monthly Collection-2025'!BB13+'Monthly Collection-2026'!BB13+'Monthly Collection-2027'!BB13+'Monthly Collection-2028'!BB13 -> 40000 | H13: ='Monthly Collection-2023'!AI13+'Monthly Collection-2024)'!BC13+'Monthly Collection-2025'!BC13+'Monthly Collection-2026'!BC13+'Monthly Collection-2027'!BC13+'Monthly Collection-2028'!BC13 -> 100 | I13: =IF(G13>(E13*1000*41),"Advanced",IF(G13<(E13*1000*41),"Due","Regular")) -> Due
B14: ='Monthly Collection-2023'!B14 -> 11 | C14: ='Monthly Collection-2023'!C14 -> Yousof | D14: 1858217297 | E14: ='Monthly Collection-2023'!E14 -> 3 | F14: =E14*100 -> 300 | G14: ='Monthly Collection-2023'!AH14+'Monthly Collection-2024)'!BB14+'Monthly Collection-2025'!BB14+'Monthly Collection-2026'!BB14+'Monthly Collection-2027'!BB14+'Monthly Collection-2028'!BB14 -> 123000 | H14: ='Monthly Collection-2023'!AI14+'Monthly Collection-2024)'!BC14+'Monthly Collection-2025'!BC14+'Monthly Collection-2026'!BC14+'Monthly Collection-2027'!BC14+'Monthly Collection-2028'!BC14 -> 0 | I14: =IF(G14>(E14*1000*41),"Advanced",IF(G14<(E14*1000*41),"Due","Regular")) -> Regular
B15: ='Monthly Collection-2023'!B15 -> 12 | C15: ='Monthly Collection-2023'!C15 -> Arjun Kanti Karmaker | D15: 01813143128 | E15: ='Monthly Collection-2023'!E15 -> 1 | F15: =E15*100 -> 100 | G15: ='Monthly Collection-2023'!AH15+'Monthly Collection-2024)'!BB15+'Monthly Collection-2025'!BB15+'Monthly Collection-2026'!BB15+'Monthly Collection-2027'!BB15+'Monthly Collection-2028'!BB15 -> 41000 | H15: ='Monthly Collection-2023'!AI15+'Monthly Collection-2024)'!BC15+'Monthly Collection-2025'!BC15+'Monthly Collection-2026'!BC15+'Monthly Collection-2027'!BC15+'Monthly Collection-2028'!BC15 -> 0 | I15: =IF(G15>(E15*1000*41),"Advanced",IF(G15<(E15*1000*41),"Due","Regular")) -> Regular
B16: ='Monthly Collection-2023'!B16 -> 13 | C16: ='Monthly Collection-2023'!C16 -> Abdul Jabber | D16: 1814941801 | E16: ='Monthly Collection-2023'!E16 -> 2 | F16: =E16*100 -> 200 | G16: ='Monthly Collection-2023'!AH16+'Monthly Collection-2024)'!BB16+'Monthly Collection-2025'!BB16+'Monthly Collection-2026'!BB16+'Monthly Collection-2027'!BB16+'Monthly Collection-2028'!BB16 -> 82000 | H16: ='Monthly Collection-2023'!AI16+'Monthly Collection-2024)'!BC16+'Monthly Collection-2025'!BC16+'Monthly Collection-2026'!BC16+'Monthly Collection-2027'!BC16+'Monthly Collection-2028'!BC16 -> 0 | I16: =IF(G16>(E16*1000*41),"Advanced",IF(G16<(E16*1000*41),"Due","Regular")) -> Regular
B17: ='Monthly Collection-2023'!B17 -> 14 | C17: ='Monthly Collection-2023'!C17 -> Mohammad Helal Uddin | D17: 1819700976 | E17: ='Monthly Collection-2023'!E17 -> 3 | F17: =E17*100 -> 300 | G17: ='Monthly Collection-2023'!AH17+'Monthly Collection-2024)'!BB17+'Monthly Collection-2025'!BB17+'Monthly Collection-2026'!BB17+'Monthly Collection-2027'!BB17+'Monthly Collection-2028'!BB17 -> 123000 | H17: ='Monthly Collection-2023'!AI17+'Monthly Collection-2024)'!BC17+'Monthly Collection-2025'!BC17+'Monthly Collection-2026'!BC17+'Monthly Collection-2027'!BC17+'Monthly Collection-2028'!BC17 -> 0 | I17: =IF(G17>(E17*1000*41),"Advanced",IF(G17<(E17*1000*41),"Due","Regular")) -> Regular
B18: ='Monthly Collection-2023'!B18 -> 15 | C18: ='Monthly Collection-2023'!C18 -> Abul Kashem | D18: 1871777022 | E18: ='Monthly Collection-2023'!E18 -> 3 | F18: =E18*100 -> 300 | G18: ='Monthly Collection-2023'!AH18+'Monthly Collection-2024)'!BB18+'Monthly Collection-2025'!BB18+'Monthly Collection-2026'!BB18+'Monthly Collection-2027'!BB18+'Monthly Collection-2028'!BB18 -> 123000 | H18: ='Monthly Collection-2023'!AI18+'Monthly Collection-2024)'!BC18+'Monthly Collection-2025'!BC18+'Monthly Collection-2026'!BC18+'Monthly Collection-2027'!BC18+'Monthly Collection-2028'!BC18 -> 0 | I18: =IF(G18>(E18*1000*41),"Advanced",IF(G18<(E18*1000*41),"Due","Regular")) -> Regular
B19: ='Monthly Collection-2023'!B19 -> 16 | C19: ='Monthly Collection-2023'!C19 -> Uzzal Karmaker | D19: 1820016020 | E19: ='Monthly Collection-2023'!E19 -> 2 | F19: =E19*100 -> 200 | G19: ='Monthly Collection-2023'!AH19+'Monthly Collection-2024)'!BB19+'Monthly Collection-2025'!BB19+'Monthly Collection-2026'!BB19+'Monthly Collection-2027'!BB19+'Monthly Collection-2028'!BB19 -> 80000 | H19: ='Monthly Collection-2023'!AI19+'Monthly Collection-2024)'!BC19+'Monthly Collection-2025'!BC19+'Monthly Collection-2026'!BC19+'Monthly Collection-2027'!BC19+'Monthly Collection-2028'!BC19 -> 300 | I19: =IF(G19>(E19*1000*41),"Advanced",IF(G19<(E19*1000*41),"Due","Regular")) -> Due
B20: ='Monthly Collection-2023'!B20 -> 17 | C20: ='Monthly Collection-2023'!C20 -> Jahedul Islam | D20: 971562765681 | E20: ='Monthly Collection-2023'!E20 -> 2 | F20: =E20*100 -> 200 | G20: ='Monthly Collection-2023'!AH20+'Monthly Collection-2024)'!BB20+'Monthly Collection-2025'!BB20+'Monthly Collection-2026'!BB20+'Monthly Collection-2027'!BB20+'Monthly Collection-2028'!BB20 -> 82000 | H20: ='Monthly Collection-2023'!AI20+'Monthly Collection-2024)'!BC20+'Monthly Collection-2025'!BC20+'Monthly Collection-2026'!BC20+'Monthly Collection-2027'!BC20+'Monthly Collection-2028'!BC20 -> 0 | I20: =IF(G20>(E20*1000*41),"Advanced",IF(G20<(E20*1000*41),"Due","Regular")) -> Regular
B21: ='Monthly Collection-2023'!B21 -> 18 | C21: ='Monthly Collection-2023'!C21 -> Mohammad Alamgir | D21: 1822092650 | E21: ='Monthly Collection-2023'!E21 -> 2 | F21: =E21*100 -> 200 | G21: ='Monthly Collection-2023'!AH21+'Monthly Collection-2024)'!BB21+'Monthly Collection-2025'!BB21+'Monthly Collection-2026'!BB21+'Monthly Collection-2027'!BB21+'Monthly Collection-2028'!BB21 -> 86000 | H21: ='Monthly Collection-2023'!AI21+'Monthly Collection-2024)'!BC21+'Monthly Collection-2025'!BC21+'Monthly Collection-2026'!BC21+'Monthly Collection-2027'!BC21+'Monthly Collection-2028'!BC21 -> 100 | I21: =IF(G21>(E21*1000*41),"Advanced",IF(G21<(E21*1000*41),"Due","Regular")) -> Advanced
B22: ='Monthly Collection-2023'!B22 -> 19 | C22: ='Monthly Collection-2023'!C22 -> Kafil Uddin | D22: 966534770192 | E22: ='Monthly Collection-2023'!E22 -> 1 | F22: =E22*100 -> 100 | G22: ='Monthly Collection-2023'!AH22+'Monthly Collection-2024)'!BB22+'Monthly Collection-2025'!BB22+'Monthly Collection-2026'!BB22+'Monthly Collection-2027'!BB22+'Monthly Collection-2028'!BB22 -> 41000 | H22: ='Monthly Collection-2023'!AI22+'Monthly Collection-2024)'!BC22+'Monthly Collection-2025'!BC22+'Monthly Collection-2026'!BC22+'Monthly Collection-2027'!BC22+'Monthly Collection-2028'!BC22 -> 0 | I22: =IF(G22>(E22*1000*41),"Advanced",IF(G22<(E22*1000*41),"Due","Regular")) -> Regular
B23: ='Monthly Collection-2023'!B23 -> 20 | C23: ='Monthly Collection-2023'!C23 -> Mohammudul Hoque | D23: 1816821801 | E23: ='Monthly Collection-2023'!E23 -> 2 | F23: =E23*100 -> 200 | G23: ='Monthly Collection-2023'!AH23+'Monthly Collection-2024)'!BB23+'Monthly Collection-2025'!BB23+'Monthly Collection-2026'!BB23+'Monthly Collection-2027'!BB23+'Monthly Collection-2028'!BB23 -> 82000 | H23: ='Monthly Collection-2023'!AI23+'Monthly Collection-2024)'!BC23+'Monthly Collection-2025'!BC23+'Monthly Collection-2026'!BC23+'Monthly Collection-2027'!BC23+'Monthly Collection-2028'!BC23 -> 0 | I23: =IF(G23>(E23*1000*41),"Advanced",IF(G23<(E23*1000*41),"Due","Regular")) -> Regular
B24: ='Monthly Collection-2023'!B24 -> 21 | C24: ='Monthly Collection-2023'!C24 -> Nurul Amin | D24: 1820989105 | E24: ='Monthly Collection-2023'!E24 -> 1 | F24: =E24*100 -> 100 | G24: ='Monthly Collection-2023'!AH24+'Monthly Collection-2024)'!BB24+'Monthly Collection-2025'!BB24+'Monthly Collection-2026'!BB24+'Monthly Collection-2027'!BB24+'Monthly Collection-2028'!BB24 -> 41000 | H24: ='Monthly Collection-2023'!AI24+'Monthly Collection-2024)'!BC24+'Monthly Collection-2025'!BC24+'Monthly Collection-2026'!BC24+'Monthly Collection-2027'!BC24+'Monthly Collection-2028'!BC24 -> 50 | I24: =IF(G24>(E24*1000*41),"Advanced",IF(G24<(E24*1000*41),"Due","Regular")) -> Regular
B25: ='Monthly Collection-2023'!B25 -> 22 | C25: ='Monthly Collection-2023'!C25 -> Abul Kashem | D25: 1873812598 | E25: ='Monthly Collection-2023'!E25 -> 1 | F25: =E25*100 -> 100 | G25: ='Monthly Collection-2023'!AH25+'Monthly Collection-2024)'!BB25+'Monthly Collection-2025'!BB25+'Monthly Collection-2026'!BB25+'Monthly Collection-2027'!BB25+'Monthly Collection-2028'!BB25 -> 40000 | H25: ='Monthly Collection-2023'!AI25+'Monthly Collection-2024)'!BC25+'Monthly Collection-2025'!BC25+'Monthly Collection-2026'!BC25+'Monthly Collection-2027'!BC25+'Monthly Collection-2028'!BC25 -> 150 | I25: =IF(G25>(E25*1000*41),"Advanced",IF(G25<(E25*1000*41),"Due","Regular")) -> Due
B26: ='Monthly Collection-2023'!B26 -> 23 | C26: ='Monthly Collection-2023'!C26 -> Belal Uddin | D26: 1815073916 | E26: ='Monthly Collection-2023'!E26 -> 1 | F26: =E26*100 -> 100 | G26: ='Monthly Collection-2023'!AH26+'Monthly Collection-2024)'!BB26+'Monthly Collection-2025'!BB26+'Monthly Collection-2026'!BB26+'Monthly Collection-2027'!BB26+'Monthly Collection-2028'!BB26 -> 37000 | H26: ='Monthly Collection-2023'!AI26+'Monthly Collection-2024)'!BC26+'Monthly Collection-2025'!BC26+'Monthly Collection-2026'!BC26+'Monthly Collection-2027'!BC26+'Monthly Collection-2028'!BC26 -> 650 | I26: =IF(G26>(E26*1000*41),"Advanced",IF(G26<(E26*1000*41),"Due","Regular")) -> Due
B27: ='Monthly Collection-2023'!B27 -> 24 | C27: ='Monthly Collection-2023'!C27 -> Md. Helal Uddin | D27: 1860493163 | E27: ='Monthly Collection-2023'!E27 -> 1 | F27: =E27*100 -> 100 | G27: ='Monthly Collection-2023'!AH27+'Monthly Collection-2024)'!BB27+'Monthly Collection-2025'!BB27+'Monthly Collection-2026'!BB27+'Monthly Collection-2027'!BB27+'Monthly Collection-2028'!BB27 -> 36000 | H27: ='Monthly Collection-2023'!AI27+'Monthly Collection-2024)'!BC27+'Monthly Collection-2025'!BC27+'Monthly Collection-2026'!BC27+'Monthly Collection-2027'!BC27+'Monthly Collection-2028'!BC27 -> 1600 | I27: =IF(G27>(E27*1000*41),"Advanced",IF(G27<(E27*1000*41),"Due","Regular")) -> Due
... B30: ='Monthly Collection-2023'!B30 -> 27 | C30: ='Monthly Collection-2023'!C30 -> Riad Hossen | D30: 1882217274 | E30: ='Monthly Collection-2023'!E30 -> 1 | F30: =E30*100 -> 100 | G30: ='Monthly Collection-2023'!AH30+'Monthly Collection-2024)'!BB30+'Monthly Collection-2025'!BB30+'Monthly Collection-2026'!BB30+'Monthly Collection-2027'!BB30+'Monthly Collection-2028'!BB30 -> 41000 | H30: ='Monthly Collection-2023'!AI30+'Monthly Collection-2024)'!BC30+'Monthly Collection-2025'!BC30+'Monthly Collection-2026'!BC30+'Monthly Collection-2027'!BC30+'Monthly Collection-2028'!BC30 -> 100 | I30: =IF(G30>(E30*1000*41),"Advanced",IF(G30<(E30*1000*41),"Due","Regular")) -> Regular
B31: ='Monthly Collection-2023'!B31 -> 28 | C31: ='Monthly Collection-2023'!C31 -> Md. Sohel Islam | D31: 00971527120848 | E31: ='Monthly Collection-2023'!E31 -> 1 | F31: =E31*100 -> 100 | G31: ='Monthly Collection-2023'!AH31+'Monthly Collection-2024)'!BB31+'Monthly Collection-2025'!BB31+'Monthly Collection-2026'!BB31+'Monthly Collection-2027'!BB31+'Monthly Collection-2028'!BB31 -> 41000 | H31: ='Monthly Collection-2023'!AI31+'Monthly Collection-2024)'!BC31+'Monthly Collection-2025'!BC31+'Monthly Collection-2026'!BC31+'Monthly Collection-2027'!BC31+'Monthly Collection-2028'!BC31 -> 100 | I31: =IF(G31>(E31*1000*41),"Advanced",IF(G31<(E31*1000*41),"Due","Regular")) -> Regular
B32: ='Monthly Collection-2023'!B32 -> 29 | C32: ='Monthly Collection-2023'!C32 -> Idrish Alam | D32: 1883033042 | E32: ='Monthly Collection-2023'!E32 -> 1 | F32: =E32*100 -> 100 | G32: ='Monthly Collection-2023'!AH32+'Monthly Collection-2024)'!BB32+'Monthly Collection-2025'!BB32+'Monthly Collection-2026'!BB32+'Monthly Collection-2027'!BB32+'Monthly Collection-2028'!BB32 -> 41000 | H32: ='Monthly Collection-2023'!AI32+'Monthly Collection-2024)'!BC32+'Monthly Collection-2025'!BC32+'Monthly Collection-2026'!BC32+'Monthly Collection-2027'!BC32+'Monthly Collection-2028'!BC32 -> 100 | I32: =IF(G32>(E32*1000*41),"Advanced",IF(G32<(E32*1000*41),"Due","Regular")) -> Regular
B33: ='Monthly Collection-2023'!B33 -> 30 | C33: ='Monthly Collection-2023'!C33 -> Jahed | D33: 966562024068 | E33: ='Monthly Collection-2023'!E33 -> 2 | F33: =E33*100 -> 200 | G33: ='Monthly Collection-2023'!AH33+'Monthly Collection-2024)'!BB33+'Monthly Collection-2025'!BB33+'Monthly Collection-2026'!BB33+'Monthly Collection-2027'!BB33+'Monthly Collection-2028'!BB33 -> 82000 | H33: ='Monthly Collection-2023'!AI33+'Monthly Collection-2024)'!BC33+'Monthly Collection-2025'!BC33+'Monthly Collection-2026'!BC33+'Monthly Collection-2027'!BC33+'Monthly Collection-2028'!BC33 -> 300 | I33: =IF(G33>(E33*1000*41),"Advanced",IF(G33<(E33*1000*41),"Due","Regular")) -> Regular
B34: ='Monthly Collection-2023'!B34 -> 31 | C34: ='Monthly Collection-2023'!C34 -> Sahidul Islam | D34: 966549955548 | E34: ='Monthly Collection-2023'!E34 -> 2 | F34: =E34*100 -> 200 | G34: ='Monthly Collection-2023'!AH34+'Monthly Collection-2024)'!BB34+'Monthly Collection-2025'!BB34+'Monthly Collection-2026'!BB34+'Monthly Collection-2027'!BB34+'Monthly Collection-2028'!BB34 -> 82000 | H34: ='Monthly Collection-2023'!AI34+'Monthly Collection-2024)'!BC34+'Monthly Collection-2025'!BC34+'Monthly Collection-2026'!BC34+'Monthly Collection-2027'!BC34+'Monthly Collection-2028'!BC34 -> 100 | I34: =IF(G34>(E34*1000*41),"Advanced",IF(G34<(E34*1000*41),"Due","Regular")) -> Regular
B35: ='Monthly Collection-2023'!B35 -> 32 | C35: ='Monthly Collection-2023'!C35 -> Md. Sohel Uddin | D35: 1822020050 | E35: ='Monthly Collection-2023'!E35 -> 2 | F35: =E35*100 -> 200 | G35: ='Monthly Collection-2023'!AH35+'Monthly Collection-2024)'!BB35+'Monthly Collection-2025'!BB35+'Monthly Collection-2026'!BB35+'Monthly Collection-2027'!BB35+'Monthly Collection-2028'!BB35 -> 82000 | H35: ='Monthly Collection-2023'!AI35+'Monthly Collection-2024)'!BC35+'Monthly Collection-2025'!BC35+'Monthly Collection-2026'!BC35+'Monthly Collection-2027'!BC35+'Monthly Collection-2028'!BC35 -> 900 | I35: =IF(G35>(E35*1000*41),"Advanced",IF(G35<(E35*1000*41),"Due","Regular")) -> Regular
B36: ='Monthly Collection-2023'!B36 -> 33 | C36: ='Monthly Collection-2023'!C36 -> Mohammad Faruk | D36: 1831797810 | E36: ='Monthly Collection-2023'!E36 -> 1 | F36: =E36*100 -> 100 | G36: ='Monthly Collection-2023'!AH36+'Monthly Collection-2024)'!BB36+'Monthly Collection-2025'!BB36+'Monthly Collection-2026'!BB36+'Monthly Collection-2027'!BB36+'Monthly Collection-2028'!BB36 -> 39000 | H36: ='Monthly Collection-2023'!AI36+'Monthly Collection-2024)'!BC36+'Monthly Collection-2025'!BC36+'Monthly Collection-2026'!BC36+'Monthly Collection-2027'!BC36+'Monthly Collection-2028'!BC36 -> 650 | I36: =IF(G36>(E36*1000*41),"Advanced",IF(G36<(E36*1000*41),"Due","Regular")) -> Due
B37: ='Monthly Collection-2023'!B37 -> 34 | C37: ='Monthly Collection-2023'!C37 -> Didarul Islam | D37: 971562663270 | E37: ='Monthly Collection-2023'!E37 -> 1 | F37: =E37*100 -> 100 | G37: ='Monthly Collection-2023'!AH37+'Monthly Collection-2024)'!BB37+'Monthly Collection-2025'!BB37+'Monthly Collection-2026'!BB37+'Monthly Collection-2027'!BB37+'Monthly Collection-2028'!BB37 -> 41000 | H37: ='Monthly Collection-2023'!AI37+'Monthly Collection-2024)'!BC37+'Monthly Collection-2025'!BC37+'Monthly Collection-2026'!BC37+'Monthly Collection-2027'!BC37+'Monthly Collection-2028'!BC37 -> 0 | I37: =IF(G37>(E37*1000*41),"Advanced",IF(G37<(E37*1000*41),"Due","Regular")) -> Regular
B38: ='Monthly Collection-2023'!B38 -> 35 | C38: ='Monthly Collection-2023'!C38 -> Mohammad Fahim | D38: 1873808231 | E38: ='Monthly Collection-2023'!E38 -> 2 | F38: =E38*100 -> 200 | G38: ='Monthly Collection-2023'!AH38+'Monthly Collection-2024)'!BB38+'Monthly Collection-2025'!BB38+'Monthly Collection-2026'!BB38+'Monthly Collection-2027'!BB38+'Monthly Collection-2028'!BB38 -> 82000 | H38: ='Monthly Collection-2023'!AI38+'Monthly Collection-2024)'!BC38+'Monthly Collection-2025'!BC38+'Monthly Collection-2026'!BC38+'Monthly Collection-2027'!BC38+'Monthly Collection-2028'!BC38 -> 0 | I38: =IF(G38>(E38*1000*41),"Advanced",IF(G38<(E38*1000*41),"Due","Regular")) -> Regular
B39: ='Monthly Collection-2023'!B39 -> 36 | C39: ='Monthly Collection-2023'!C39 -> Delower Hossain | D39: 971561572487 | E39: ='Monthly Collection-2023'!E39 -> 1 | F39: =E39*100 -> 100 | G39: ='Monthly Collection-2023'!AH39+'Monthly Collection-2024)'!BB39+'Monthly Collection-2025'!BB39+'Monthly Collection-2026'!BB39+'Monthly Collection-2027'!BB39+'Monthly Collection-2028'!BB39 -> 41000 | H39: ='Monthly Collection-2023'!AI39+'Monthly Collection-2024)'!BC39+'Monthly Collection-2025'!BC39+'Monthly Collection-2026'!BC39+'Monthly Collection-2027'!BC39+'Monthly Collection-2028'!BC39 -> 0 | I39: =IF(G39>(E39*1000*41),"Advanced",IF(G39<(E39*1000*41),"Due","Regular")) -> Regular
B40: ='Monthly Collection-2023'!B40 -> 37 | C40: ='Monthly Collection-2023'!C40 -> Abdul Malek | D40: 1879352117 | E40: ='Monthly Collection-2023'!E40 -> 2 | F40: =E40*100 -> 200 | G40: ='Monthly Collection-2023'!AH40+'Monthly Collection-2024)'!BB40+'Monthly Collection-2025'!BB40+'Monthly Collection-2026'!BB40+'Monthly Collection-2027'!BB40+'Monthly Collection-2028'!BB40 -> 82000 | H40: ='Monthly Collection-2023'!AI40+'Monthly Collection-2024)'!BC40+'Monthly Collection-2025'!BC40+'Monthly Collection-2026'!BC40+'Monthly Collection-2027'!BC40+'Monthly Collection-2028'!BC40 -> 100 | I40: =IF(G40>(E40*1000*41),"Advanced",IF(G40<(E40*1000*41),"Due","Regular")) -> Regular
B41: ='Monthly Collection-2023'!B41 -> 38 | C41: ='Monthly Collection-2023'!C41 -> Khalil Uddin | D41: 00971569173725 | E41: ='Monthly Collection-2023'!E41 -> 2 | F41: =E41*100 -> 200 | G41: ='Monthly Collection-2023'!AH41+'Monthly Collection-2024)'!BB41+'Monthly Collection-2025'!BB41+'Monthly Collection-2026'!BB41+'Monthly Collection-2027'!BB41+'Monthly Collection-2028'!BB41 -> 82000 | H41: ='Monthly Collection-2023'!AI41+'Monthly Collection-2024)'!BC41+'Monthly Collection-2025'!BC41+'Monthly Collection-2026'!BC41+'Monthly Collection-2027'!BC41+'Monthly Collection-2028'!BC41 -> 0 | I41: =IF(G41>(E41*1000*41),"Advanced",IF(G41<(E41*1000*41),"Due","Regular")) -> Regular
B42: ='Monthly Collection-2023'!B42 -> 39 | C42: ='Monthly Collection-2023'!C42 -> Mohammad Abul Hashem | D42: 1873807617 | E42: ='Monthly Collection-2023'!E42 -> 2 | F42: =E42*100 -> 200 | G42: ='Monthly Collection-2023'!AH42+'Monthly Collection-2024)'!BB42+'Monthly Collection-2025'!BB42+'Monthly Collection-2026'!BB42+'Monthly Collection-2027'!BB42+'Monthly Collection-2028'!BB42 -> 76000 | H42: ='Monthly Collection-2023'!AI42+'Monthly Collection-2024)'!BC42+'Monthly Collection-2025'!BC42+'Monthly Collection-2026'!BC42+'Monthly Collection-2027'!BC42+'Monthly Collection-2028'!BC42 -> 1400 | I42: =IF(G42>(E42*1000*41),"Advanced",IF(G42<(E42*1000*41),"Due","Regular")) -> Due
B43: ='Monthly Collection-2023'!B43 -> 40 | C43: ='Monthly Collection-2023'!C43 -> Abdul Karim | D43: 971569774500 | E43: ='Monthly Collection-2023'!E43 -> 2 | F43: =E43*100 -> 200 | G43: ='Monthly Collection-2023'!AH43+'Monthly Collection-2024)'!BB43+'Monthly Collection-2025'!BB43+'Monthly Collection-2026'!BB43+'Monthly Collection-2027'!BB43+'Monthly Collection-2028'!BB43 -> 82000 | H43: ='Monthly Collection-2023'!AI43+'Monthly Collection-2024)'!BC43+'Monthly Collection-2025'!BC43+'Monthly Collection-2026'!BC43+'Monthly Collection-2027'!BC43+'Monthly Collection-2028'!BC43 -> 0 | I43: =IF(G43>(E43*1000*41),"Advanced",IF(G43<(E43*1000*41),"Due","Regular")) -> Regular
B44: ='Monthly Collection-2023'!B44 -> 41 | C44: ='Monthly Collection-2023'!C44 -> Mohammad Kaisar | D44: 1830621990 | E44: ='Monthly Collection-2023'!E44 -> 2 | F44: =E44*100 -> 200 | G44: ='Monthly Collection-2023'!AH44+'Monthly Collection-2024)'!BB44+'Monthly Collection-2025'!BB44+'Monthly Collection-2026'!BB44+'Monthly Collection-2027'!BB44+'Monthly Collection-2028'!BB44 -> 82000 | H44: ='Monthly Collection-2023'!AI44+'Monthly Collection-2024)'!BC44+'Monthly Collection-2025'!BC44+'Monthly Collection-2026'!BC44+'Monthly Collection-2027'!BC44+'Monthly Collection-2028'!BC44 -> 1200 | I44: =IF(G44>(E44*1000*41),"Advanced",IF(G44<(E44*1000*41),"Due","Regular")) -> Regular
B45: ='Monthly Collection-2023'!B45 -> 42 | C45: ='Monthly Collection-2023'!C45 -> Korshed Alam | D45: 0971501332588 | E45: ='Monthly Collection-2023'!E45 -> 6 | F45: =E45*100 -> 600 | G45: ='Monthly Collection-2023'!AH45+'Monthly Collection-2024)'!BB45+'Monthly Collection-2025'!BB45+'Monthly Collection-2026'!BB45+'Monthly Collection-2027'!BB45+'Monthly Collection-2028'!BB45 -> 246000 | H45: ='Monthly Collection-2023'!AI45+'Monthly Collection-2024)'!BC45+'Monthly Collection-2025'!BC45+'Monthly Collection-2026'!BC45+'Monthly Collection-2027'!BC45+'Monthly Collection-2028'!BC45 -> 0 | I45: =IF(G45>(E45*1000*41),"Advanced",IF(G45<(E45*1000*41),"Due","Regular")) -> Regular
B46: ='Monthly Collection-2023'!B46 -> 43 | C46: ='Monthly Collection-2023'!C46 -> Emon Hasan | D46: 971545640821 | E46: ='Monthly Collection-2023'!E46 -> 2 | F46: =E46*100 -> 200 | G46: ='Monthly Collection-2023'!AH46+'Monthly Collection-2024)'!BB46+'Monthly Collection-2025'!BB46+'Monthly Collection-2026'!BB46+'Monthly Collection-2027'!BB46+'Monthly Collection-2028'!BB46 -> 78000 | H46: ='Monthly Collection-2023'!AI46+'Monthly Collection-2024)'!BC46+'Monthly Collection-2025'!BC46+'Monthly Collection-2026'!BC46+'Monthly Collection-2027'!BC46+'Monthly Collection-2028'!BC46 -> 1000 | I46: =IF(G46>(E46*1000*41),"Advanced",IF(G46<(E46*1000*41),"Due","Regular")) -> Due
B47: ='Monthly Collection-2023'!B47 -> 44 | C47: ='Monthly Collection-2023'!C47 -> Tawhidul Islam | D47: 971562982931 | E47: ='Monthly Collection-2023'!E47 -> 2 | F47: =E47*100 -> 200 | G47: ='Monthly Collection-2023'!AH47+'Monthly Collection-2024)'!BB47+'Monthly Collection-2025'!BB47+'Monthly Collection-2026'!BB47+'Monthly Collection-2027'!BB47+'Monthly Collection-2028'!BB47 -> 80000 | H47: ='Monthly Collection-2023'!AI47+'Monthly Collection-2024)'!BC47+'Monthly Collection-2025'!BC47+'Monthly Collection-2026'!BC47+'Monthly Collection-2027'!BC47+'Monthly Collection-2028'!BC47 -> 1600 | I47: =IF(G47>(E47*1000*41),"Advanced",IF(G47<(E47*1000*41),"Due","Regular")) -> Due
B48: ='Monthly Collection-2023'!B48 -> 45 | C48: ='Monthly Collection-2023'!C48 -> Sahidul Islam | D48: 1840409753 | E48: ='Monthly Collection-2023'!E48 -> 1 | F48: =E48*100 -> 100 | G48: ='Monthly Collection-2023'!AH48+'Monthly Collection-2024)'!BB48+'Monthly Collection-2025'!BB48+'Monthly Collection-2026'!BB48+'Monthly Collection-2027'!BB48+'Monthly Collection-2028'!BB48 -> 39000 | H48: ='Monthly Collection-2023'!AI48+'Monthly Collection-2024)'!BC48+'Monthly Collection-2025'!BC48+'Monthly Collection-2026'!BC48+'Monthly Collection-2027'!BC48+'Monthly Collection-2028'!BC48 -> 850 | I48: =IF(G48>(E48*1000*41),"Advanced",IF(G48<(E48*1000*41),"Due","Regular")) -> Due
B49: ='Monthly Collection-2023'!B49 -> 46 | C49: ='Monthly Collection-2023'!C49 -> Amir Hossen | D49: 1871081769 | E49: ='Monthly Collection-2023'!E49 -> 1 | F49: =E49*100 -> 100 | G49: ='Monthly Collection-2023'!AH49+'Monthly Collection-2024)'!BB49+'Monthly Collection-2025'!BB49+'Monthly Collection-2026'!BB49+'Monthly Collection-2027'!BB49+'Monthly Collection-2028'!BB49 -> 40000 | H49: ='Monthly Collection-2023'!AI49+'Monthly Collection-2024)'!BC49+'Monthly Collection-2025'!BC49+'Monthly Collection-2026'!BC49+'Monthly Collection-2027'!BC49+'Monthly Collection-2028'!BC49 -> 1400 | I49: =IF(G49>(E49*1000*41),"Advanced",IF(G49<(E49*1000*41),"Due","Regular")) -> Due
B50: ='Monthly Collection-2023'!B50 -> 47 | C50: ='Monthly Collection-2023'!C50 -> Mohammad Abdullah Al Rafi | D50: 1882916447 | E50: ='Monthly Collection-2023'!E50 -> 1 | F50: =E50*100 -> 100 | G50: ='Monthly Collection-2023'!AH50+'Monthly Collection-2024)'!BB50+'Monthly Collection-2025'!BB50+'Monthly Collection-2026'!BB50+'Monthly Collection-2027'!BB50+'Monthly Collection-2028'!BB50 -> 40000 | H50: ='Monthly Collection-2023'!AI50+'Monthly Collection-2024)'!BC50+'Monthly Collection-2025'!BC50+'Monthly Collection-2026'!BC50+'Monthly Collection-2027'!BC50+'Monthly Collection-2028'!BC50 -> 50 | I50: =IF(G50>(E50*1000*41),"Advanced",IF(G50<(E50*1000*41),"Due","Regular")) -> Due
B51: ='Monthly Collection-2023'!B51 -> 48 | C51: ='Monthly Collection-2023'!C51 -> Nurul Huda Misbah | D51: 1814836702 | E51: ='Monthly Collection-2023'!E51 -> 2 | F51: =E51*100 -> 200 | G51: ='Monthly Collection-2023'!AH51+'Monthly Collection-2024)'!BB51+'Monthly Collection-2025'!BB51+'Monthly Collection-2026'!BB51+'Monthly Collection-2027'!BB51+'Monthly Collection-2028'!BB51 -> 82000 | H51: ='Monthly Collection-2023'!AI51+'Monthly Collection-2024)'!BC51+'Monthly Collection-2025'!BC51+'Monthly Collection-2026'!BC51+'Monthly Collection-2027'!BC51+'Monthly Collection-2028'!BC51 -> 0 | I51: =IF(G51>(E51*1000*41),"Advanced",IF(G51<(E51*1000*41),"Due","Regular")) -> Regular
B52: ='Monthly Collection-2023'!B52 -> 49 | C52: ='Monthly Collection-2023'!C52 -> Aminul Hoque | D52: 0097433390829 | E52: ='Monthly Collection-2023'!E52 -> 1 | F52: =E52*100 -> 100 | G52: ='Monthly Collection-2023'!AH52+'Monthly Collection-2024)'!BB52+'Monthly Collection-2025'!BB52+'Monthly Collection-2026'!BB52+'Monthly Collection-2027'!BB52+'Monthly Collection-2028'!BB52 -> 41000 | H52: ='Monthly Collection-2023'!AI52+'Monthly Collection-2024)'!BC52+'Monthly Collection-2025'!BC52+'Monthly Collection-2026'!BC52+'Monthly Collection-2027'!BC52+'Monthly Collection-2028'!BC52 -> 300 | I52: =IF(G52>(E52*1000*41),"Advanced",IF(G52<(E52*1000*41),"Due","Regular")) -> Regular
B53: ='Monthly Collection-2023'!B53 -> 50 | C53: ='Monthly Collection-2023'!C53 -> Shekh Ahmed Roki | D53: 1829921642 | E53: ='Monthly Collection-2023'!E53 -> 1 | F53: =E53*100 -> 100 | G53: ='Monthly Collection-2023'!AH53+'Monthly Collection-2024)'!BB53+'Monthly Collection-2025'!BB53+'Monthly Collection-2026'!BB53+'Monthly Collection-2027'!BB53+'Monthly Collection-2028'!BB53 -> 41000 | H53: ='Monthly Collection-2023'!AI53+'Monthly Collection-2024)'!BC53+'Monthly Collection-2025'!BC53+'Monthly Collection-2026'!BC53+'Monthly Collection-2027'!BC53+'Monthly Collection-2028'!BC53 -> 0 | I53: =IF(G53>(E53*1000*41),"Advanced",IF(G53<(E53*1000*41),"Due","Regular")) -> Regular
B54: ='Monthly Collection-2023'!B54 -> 51 | C54: ='Monthly Collection-2023'!C54 -> Md. Sahjahan | D54: 1889786926 | E54: ='Monthly Collection-2023'!E54 -> 3 | F54: =E54*100 -> 300 | G54: ='Monthly Collection-2023'!AH54+'Monthly Collection-2024)'!BB54+'Monthly Collection-2025'!BB54+'Monthly Collection-2026'!BB54+'Monthly Collection-2027'!BB54+'Monthly Collection-2028'!BB54 -> 123000 | H54: ='Monthly Collection-2023'!AI54+'Monthly Collection-2024)'!BC54+'Monthly Collection-2025'!BC54+'Monthly Collection-2026'!BC54+'Monthly Collection-2027'!BC54+'Monthly Collection-2028'!BC54 -> 0 | I54: =IF(G54>(E54*1000*41),"Advanced",IF(G54<(E54*1000*41),"Due","Regular")) -> Regular
B55: ='Monthly Collection-2023'!B55 -> 52 | C55: ='Monthly Collection-2023'!C55 -> Babul Hossen | D55: 1833903155 | E55: ='Monthly Collection-2023'!E55 -> 1 | F55: =E55*100 -> 100 | G55: ='Monthly Collection-2023'!AH55+'Monthly Collection-2024)'!BB55+'Monthly Collection-2025'!BB55+'Monthly Collection-2026'!BB55+'Monthly Collection-2027'!BB55+'Monthly Collection-2028'!BB55 -> 38000 | H55: ='Monthly Collection-2023'!AI55+'Monthly Collection-2024)'!BC55+'Monthly Collection-2025'!BC55+'Monthly Collection-2026'!BC55+'Monthly Collection-2027'!BC55+'Monthly Collection-2028'!BC55 -> 950 | I55: =IF(G55>(E55*1000*41),"Advanced",IF(G55<(E55*1000*41),"Due","Regular")) -> Due
B56: ='Monthly Collection-2023'!B56 -> 53 | C56: ='Monthly Collection-2023'!C56 -> Khair Ahmed | D56: 1897045177 | E56: ='Monthly Collection-2023'!E56 -> 1 | F56: =E56*100 -> 100 | G56: ='Monthly Collection-2023'!AH56+'Monthly Collection-2024)'!BB56+'Monthly Collection-2025'!BB56+'Monthly Collection-2026'!BB56+'Monthly Collection-2027'!BB56+'Monthly Collection-2028'!BB56 -> 41000 | H56: ='Monthly Collection-2023'!AI56+'Monthly Collection-2024)'!BC56+'Monthly Collection-2025'!BC56+'Monthly Collection-2026'!BC56+'Monthly Collection-2027'!BC56+'Monthly Collection-2028'!BC56 -> 50 | I56: =IF(G56>(E56*1000*41),"Advanced",IF(G56<(E56*1000*41),"Due","Regular")) -> Regular
B57: ='Monthly Collection-2023'!B57 -> 54 | C57: ='Monthly Collection-2023'!C57 -> Md. Lutfar Rahman | D57: 00966564847790 | E57: ='Monthly Collection-2023'!E57 -> 1 | F57: =E57*100 -> 100 | G57: ='Monthly Collection-2023'!AH57+'Monthly Collection-2024)'!BB57+'Monthly Collection-2025'!BB57+'Monthly Collection-2026'!BB57+'Monthly Collection-2027'!BB57+'Monthly Collection-2028'!BB57 -> 41000 | H57: ='Monthly Collection-2023'!AI57+'Monthly Collection-2024)'!BC57+'Monthly Collection-2025'!BC57+'Monthly Collection-2026'!BC57+'Monthly Collection-2027'!BC57+'Monthly Collection-2028'!BC57 -> 300 | I57: =IF(G57>(E57*1000*41),"Advanced",IF(G57<(E57*1000*41),"Due","Regular")) -> Regular
B58: ='Monthly Collection-2023'!B58 -> 55 | C58: ='Monthly Collection-2023'!C58 -> Abu Bakker | D58: 00971559969326 | E58: ='Monthly Collection-2023'!E58 -> 2 | F58: =E58*100 -> 200 | G58: ='Monthly Collection-2023'!AH58+'Monthly Collection-2024)'!BB58+'Monthly Collection-2025'!BB58+'Monthly Collection-2026'!BB58+'Monthly Collection-2027'!BB58+'Monthly Collection-2028'!BB58 -> 86000 | H58: ='Monthly Collection-2023'!AI58+'Monthly Collection-2024)'!BC58+'Monthly Collection-2025'!BC58+'Monthly Collection-2026'!BC58+'Monthly Collection-2027'!BC58+'Monthly Collection-2028'!BC58 -> 1950 | I58: =IF(G58>(E58*1000*41),"Advanced",IF(G58<(E58*1000*41),"Due","Regular")) -> Advanced
B59: ='Monthly Collection-2023'!B59 -> 56 | C59: ='Monthly Collection-2023'!C59 -> Abdullah Al Mumid | D59: 01585430658 | E59: ='Monthly Collection-2023'!E59 -> 1 | F59: =E59*100 -> 100 | G59: ='Monthly Collection-2023'!AH59+'Monthly Collection-2024)'!BB59+'Monthly Collection-2025'!BB59+'Monthly Collection-2026'!BB59+'Monthly Collection-2027'!BB59+'Monthly Collection-2028'!BB59 -> 41000 | H59: ='Monthly Collection-2023'!AI59+'Monthly Collection-2024)'!BC59+'Monthly Collection-2025'!BC59+'Monthly Collection-2026'!BC59+'Monthly Collection-2027'!BC59+'Monthly Collection-2028'!BC59 -> 700 | I59: =IF(G59>(E59*1000*41),"Advanced",IF(G59<(E59*1000*41),"Due","Regular")) -> Regular
B60: ='Monthly Collection-2023'!B60 -> 57 | C60: ='Monthly Collection-2023'!C60 -> Sujan Kanti Karmaker | D60: 01814785317 | E60: ='Monthly Collection-2023'!E60 -> 1 | F60: =E60*100 -> 100 | G60: ='Monthly Collection-2023'!AH60+'Monthly Collection-2024)'!BB60+'Monthly Collection-2025'!BB60+'Monthly Collection-2026'!BB60+'Monthly Collection-2027'!BB60+'Monthly Collection-2028'!BB60 -> 41000 | H60: ='Monthly Collection-2023'!AI60+'Monthly Collection-2024)'!BC60+'Monthly Collection-2025'!BC60+'Monthly Collection-2026'!BC60+'Monthly Collection-2027'!BC60+'Monthly Collection-2028'!BC60 -> 900 | I60: =IF(G60>(E60*1000*41),"Advanced",IF(G60<(E60*1000*41),"Due","Regular")) -> Regular
B61: ='Monthly Collection-2023'!B61 -> 58 | C61: ='Monthly Collection-2023'!C61 -> Prokash Kanti Nath | D61: 01728125764 | E61: ='Monthly Collection-2023'!E61 -> 1 | F61: =E61*100 -> 100 | G61: ='Monthly Collection-2023'!AH61+'Monthly Collection-2024)'!BB61+'Monthly Collection-2025'!BB61+'Monthly Collection-2026'!BB61+'Monthly Collection-2027'!BB61+'Monthly Collection-2028'!BB61 -> 41000 | H61: ='Monthly Collection-2023'!AI61+'Monthly Collection-2024)'!BC61+'Monthly Collection-2025'!BC61+'Monthly Collection-2026'!BC61+'Monthly Collection-2027'!BC61+'Monthly Collection-2028'!BC61 -> 0 | I61: =IF(G61>(E61*1000*41),"Advanced",IF(G61<(E61*1000*41),"Due","Regular")) -> Regular
B62: ='Monthly Collection-2023'!B62 -> 59 | C62: ='Monthly Collection-2023'!C62 -> Abdul Sabur | D62: 1817246488 | E62: ='Monthly Collection-2023'!E62 -> 1 | F62: =E62*100 -> 100 | G62: ='Monthly Collection-2023'!AH62+'Monthly Collection-2024)'!BB62+'Monthly Collection-2025'!BB62+'Monthly Collection-2026'!BB62+'Monthly Collection-2027'!BB62+'Monthly Collection-2028'!BB62 -> 41000 | H62: ='Monthly Collection-2023'!AI62+'Monthly Collection-2024)'!BC62+'Monthly Collection-2025'!BC62+'Monthly Collection-2026'!BC62+'Monthly Collection-2027'!BC62+'Monthly Collection-2028'!BC62 -> 0 | I62: =IF(G62>(E62*1000*41),"Advanced",IF(G62<(E62*1000*41),"Due","Regular")) -> Regular
B63: ='Monthly Collection-2023'!B63 -> 60 | C63: ='Monthly Collection-2023'!C63 -> Ridowanul Hoque | D63: 1866911987 | E63: ='Monthly Collection-2023'!E63 -> 2 | F63: =E63*100 -> 200 | G63: ='Monthly Collection-2023'!AH63+'Monthly Collection-2024)'!BB63+'Monthly Collection-2025'!BB63+'Monthly Collection-2026'!BB63+'Monthly Collection-2027'!BB63+'Monthly Collection-2028'!BB63 -> 82000 | H63: ='Monthly Collection-2023'!AI63+'Monthly Collection-2024)'!BC63+'Monthly Collection-2025'!BC63+'Monthly Collection-2026'!BC63+'Monthly Collection-2027'!BC63+'Monthly Collection-2028'!BC63 -> 100 | I63: =IF(G63>(E63*1000*41),"Advanced",IF(G63<(E63*1000*41),"Due","Regular")) -> Regular
B64: ='Monthly Collection-2023'!B64 -> 61 | C64: ='Monthly Collection-2023'!C64 -> Mohammad Toyab | D64: 1817504865 | E64: ='Monthly Collection-2023'!E64 -> 1 | F64: =E64*100 -> 100 | G64: ='Monthly Collection-2023'!AH64+'Monthly Collection-2024)'!BB64+'Monthly Collection-2025'!BB64+'Monthly Collection-2026'!BB64+'Monthly Collection-2027'!BB64+'Monthly Collection-2028'!BB64 -> 41000 | H64: ='Monthly Collection-2023'!AI64+'Monthly Collection-2024)'!BC64+'Monthly Collection-2025'!BC64+'Monthly Collection-2026'!BC64+'Monthly Collection-2027'!BC64+'Monthly Collection-2028'!BC64 -> 50 | I64: =IF(G64>(E64*1000*41),"Advanced",IF(G64<(E64*1000*41),"Due","Regular")) -> Regular
B65: ='Monthly Collection-2023'!B65 -> 62 | C65: ='Monthly Collection-2023'!C65 -> Nurul Amin | D65: 1885316318 | E65: ='Monthly Collection-2023'!E65 -> 1 | F65: =E65*100 -> 100 | G65: ='Monthly Collection-2023'!AH65+'Monthly Collection-2024)'!BB65+'Monthly Collection-2025'!BB65+'Monthly Collection-2026'!BB65+'Monthly Collection-2027'!BB65+'Monthly Collection-2028'!BB65 -> 37000 | H65: ='Monthly Collection-2023'!AI65+'Monthly Collection-2024)'!BC65+'Monthly Collection-2025'!BC65+'Monthly Collection-2026'!BC65+'Monthly Collection-2027'!BC65+'Monthly Collection-2028'!BC65 -> 1200 | I65: =IF(G65>(E65*1000*41),"Advanced",IF(G65<(E65*1000*41),"Due","Regular")) -> Due
B66: ='Monthly Collection-2023'!B66 -> 63 | C66: ='Monthly Collection-2023'!C66 -> Joy Sankar Karmaker | D66: 1827204517 | E66: ='Monthly Collection-2023'!E66 -> 1 | F66: =E66*100 -> 100 | G66: ='Monthly Collection-2023'!AH66+'Monthly Collection-2024)'!BB66+'Monthly Collection-2025'!BB66+'Monthly Collection-2026'!BB66+'Monthly Collection-2027'!BB66+'Monthly Collection-2028'!BB66 -> 39000 | H66: ='Monthly Collection-2023'!AI66+'Monthly Collection-2024)'!BC66+'Monthly Collection-2025'!BC66+'Monthly Collection-2026'!BC66+'Monthly Collection-2027'!BC66+'Monthly Collection-2028'!BC66 -> 50 | I66: =IF(G66>(E66*1000*41),"Advanced",IF(G66<(E66*1000*41),"Due","Regular")) -> Due
B67: ='Monthly Collection-2023'!B67 -> 64 | C67: ='Monthly Collection-2023'!C67 -> Mohammad Sahjahan | D67: 00971557893251 | E67: ='Monthly Collection-2023'!E67 -> 1 | F67: =E67*100 -> 100 | G67: ='Monthly Collection-2023'!AH67+'Monthly Collection-2024)'!BB67+'Monthly Collection-2025'!BB67+'Monthly Collection-2026'!BB67+'Monthly Collection-2027'!BB67+'Monthly Collection-2028'!BB67 -> 41000 | H67: ='Monthly Collection-2023'!AI67+'Monthly Collection-2024)'!BC67+'Monthly Collection-2025'!BC67+'Monthly Collection-2026'!BC67+'Monthly Collection-2027'!BC67+'Monthly Collection-2028'!BC67 -> 250 | I67: =IF(G67>(E67*1000*41),"Advanced",IF(G67<(E67*1000*41),"Due","Regular")) -> Regular
B68: ='Monthly Collection-2023'!B68 -> 65 | C68: ='Monthly Collection-2023'!C68 -> Akter Hossen | D68: 1861821214 | E68: ='Monthly Collection-2023'!E68 -> 1 | F68: =E68*100 -> 100 | G68: ='Monthly Collection-2023'!AH68+'Monthly Collection-2024)'!BB68+'Monthly Collection-2025'!BB68+'Monthly Collection-2026'!BB68+'Monthly Collection-2027'!BB68+'Monthly Collection-2028'!BB68 -> 41000 | H68: ='Monthly Collection-2023'!AI68+'Monthly Collection-2024)'!BC68+'Monthly Collection-2025'!BC68+'Monthly Collection-2026'!BC68+'Monthly Collection-2027'!BC68+'Monthly Collection-2028'!BC68 -> 250 | I68: =IF(G68>(E68*1000*41),"Advanced",IF(G68<(E68*1000*41),"Due","Regular")) -> Regular
B69: ='Monthly Collection-2023'!B69 -> 66 | C69: ='Monthly Collection-2023'!C69 -> Ehsanul Kabir | D69: 00971557512381 | E69: ='Monthly Collection-2023'!E69 -> 1 | F69: =E69*100 -> 100 | G69: ='Monthly Collection-2023'!AH69+'Monthly Collection-2024)'!BB69+'Monthly Collection-2025'!BB69+'Monthly Collection-2026'!BB69+'Monthly Collection-2027'!BB69+'Monthly Collection-2028'!BB69 -> 41000 | H69: ='Monthly Collection-2023'!AI69+'Monthly Collection-2024)'!BC69+'Monthly Collection-2025'!BC69+'Monthly Collection-2026'!BC69+'Monthly Collection-2027'!BC69+'Monthly Collection-2028'!BC69 -> 250 | I69: =IF(G69>(E69*1000*41),"Advanced",IF(G69<(E69*1000*41),"Due","Regular")) -> Regular
B70: ='Monthly Collection-2023'!B70 -> 67 | C70: ='Monthly Collection-2023'!C70 -> Mohammad Sayed Uddin Forhad | D70: 971585735180 | E70: ='Monthly Collection-2023'!E70 -> 1 | F70: =E70*100 -> 100 | G70: ='Monthly Collection-2023'!AH70+'Monthly Collection-2024)'!BB70+'Monthly Collection-2025'!BB70+'Monthly Collection-2026'!BB70+'Monthly Collection-2027'!BB70+'Monthly Collection-2028'!BB70 -> 39000 | H70: ='Monthly Collection-2023'!AI70+'Monthly Collection-2024)'!BC70+'Monthly Collection-2025'!BC70+'Monthly Collection-2026'!BC70+'Monthly Collection-2027'!BC70+'Monthly Collection-2028'!BC70 -> 250 | I70: =IF(G70>(E70*1000*41),"Advanced",IF(G70<(E70*1000*41),"Due","Regular")) -> Due
B71: ='Monthly Collection-2023'!B71 -> 68 | C71: ='Monthly Collection-2023'!C71 -> Mohammad Ziabul Hoque | D71: 971502927559 | E71: ='Monthly Collection-2023'!E71 -> 1 | F71: =E71*100 -> 100 | G71: ='Monthly Collection-2023'!AH71+'Monthly Collection-2024)'!BB71+'Monthly Collection-2025'!BB71+'Monthly Collection-2026'!BB71+'Monthly Collection-2027'!BB71+'Monthly Collection-2028'!BB71 -> 39000 | H71: ='Monthly Collection-2023'!AI71+'Monthly Collection-2024)'!BC71+'Monthly Collection-2025'!BC71+'Monthly Collection-2026'!BC71+'Monthly Collection-2027'!BC71+'Monthly Collection-2028'!BC71 -> 100 | I71: =IF(G71>(E71*1000*41),"Advanced",IF(G71<(E71*1000*41),"Due","Regular")) -> Due
B72: ='Monthly Collection-2023'!B72 -> 69 | C72: ='Monthly Collection-2023'!C72 -> Mohammad Yousof | D72: 971561607784 | E72: ='Monthly Collection-2023'!E72 -> 2 | F72: =E72*100 -> 200 | G72: ='Monthly Collection-2023'!AH72+'Monthly Collection-2024)'!BB72+'Monthly Collection-2025'!BB72+'Monthly Collection-2026'!BB72+'Monthly Collection-2027'!BB72+'Monthly Collection-2028'!BB72 -> 82000 | H72: ='Monthly Collection-2023'!AI72+'Monthly Collection-2024)'!BC72+'Monthly Collection-2025'!BC72+'Monthly Collection-2026'!BC72+'Monthly Collection-2027'!BC72+'Monthly Collection-2028'!BC72 -> 0 | I72: =IF(G72>(E72*1000*41),"Advanced",IF(G72<(E72*1000*41),"Due","Regular")) -> Regular
B73: ='Monthly Collection-2023'!B73 -> 70 | C73: ='Monthly Collection-2023'!C73 -> Mohammad Osman Goni | D73: 1814123764 | E73: ='Monthly Collection-2023'!E73 -> 1 | F73: =E73*100 -> 100 | G73: ='Monthly Collection-2023'!AH73+'Monthly Collection-2024)'!BB73+'Monthly Collection-2025'!BB73+'Monthly Collection-2026'!BB73+'Monthly Collection-2027'!BB73+'Monthly Collection-2028'!BB73 -> 41000 | H73: ='Monthly Collection-2023'!AI73+'Monthly Collection-2024)'!BC73+'Monthly Collection-2025'!BC73+'Monthly Collection-2026'!BC73+'Monthly Collection-2027'!BC73+'Monthly Collection-2028'!BC73 -> 50 | I73: =IF(G73>(E73*1000*41),"Advanced",IF(G73<(E73*1000*41),"Due","Regular")) -> Regular
B74: ='Monthly Collection-2023'!B74 -> 71 | C74: ='Monthly Collection-2023'!C74 -> Iqbal Hossen | D74: 00971503805124 | E74: ='Monthly Collection-2023'!E74 -> 1 | F74: =E74*100 -> 100 | G74: ='Monthly Collection-2023'!AH74+'Monthly Collection-2024)'!BB74+'Monthly Collection-2025'!BB74+'Monthly Collection-2026'!BB74+'Monthly Collection-2027'!BB74+'Monthly Collection-2028'!BB74 -> 41000 | H74: ='Monthly Collection-2023'!AI74+'Monthly Collection-2024)'!BC74+'Monthly Collection-2025'!BC74+'Monthly Collection-2026'!BC74+'Monthly Collection-2027'!BC74+'Monthly Collection-2028'!BC74 -> 100 | I74: =IF(G74>(E74*1000*41),"Advanced",IF(G74<(E74*1000*41),"Due","Regular")) -> Regular
B75: ='Monthly Collection-2023'!B75 -> 72 | C75: ='Monthly Collection-2023'!C75 -> Debasish Karmaker | D75: 1863367162 | E75: ='Monthly Collection-2023'!E75 -> 1 | F75: =E75*100 -> 100 | G75: ='Monthly Collection-2023'!AH75+'Monthly Collection-2024)'!BB75+'Monthly Collection-2025'!BB75+'Monthly Collection-2026'!BB75+'Monthly Collection-2027'!BB75+'Monthly Collection-2028'!BB75 -> 40000 | H75: ='Monthly Collection-2023'!AI75+'Monthly Collection-2024)'!BC75+'Monthly Collection-2025'!BC75+'Monthly Collection-2026'!BC75+'Monthly Collection-2027'!BC75+'Monthly Collection-2028'!BC75 -> 50 | I75: =IF(G75>(E75*1000*41),"Advanced",IF(G75<(E75*1000*41),"Due","Regular")) -> Due
B76: ='Monthly Collection-2023'!B76 -> 73 | C76: ='Monthly Collection-2023'!C76 -> Salim Uddin | D76: 00971545732130 | E76: ='Monthly Collection-2023'!E76 -> 1 | F76: =E76*100 -> 100 | G76: ='Monthly Collection-2023'!AH76+'Monthly Collection-2024)'!BB76+'Monthly Collection-2025'!BB76+'Monthly Collection-2026'!BB76+'Monthly Collection-2027'!BB76+'Monthly Collection-2028'!BB76 -> 41000 | H76: ='Monthly Collection-2023'!AI76+'Monthly Collection-2024)'!BC76+'Monthly Collection-2025'!BC76+'Monthly Collection-2026'!BC76+'Monthly Collection-2027'!BC76+'Monthly Collection-2028'!BC76 -> 400 | I76: =IF(G76>(E76*1000*41),"Advanced",IF(G76<(E76*1000*41),"Due","Regular")) -> Regular
B77: ='Monthly Collection-2023'!B77 -> 74 | C77: ='Monthly Collection-2023'!C77 -> Mujibur Rahman | D77: 00966504512844 | E77: ='Monthly Collection-2023'!E77 -> 1 | F77: =E77*100 -> 100 | G77: ='Monthly Collection-2023'!AH77+'Monthly Collection-2024)'!BB77+'Monthly Collection-2025'!BB77+'Monthly Collection-2026'!BB77+'Monthly Collection-2027'!BB77+'Monthly Collection-2028'!BB77 -> 40000 | H77: ='Monthly Collection-2023'!AI77+'Monthly Collection-2024)'!BC77+'Monthly Collection-2025'!BC77+'Monthly Collection-2026'!BC77+'Monthly Collection-2027'!BC77+'Monthly Collection-2028'!BC77 -> 0 | I77: =IF(G77>(E77*1000*41),"Advanced",IF(G77<(E77*1000*41),"Due","Regular")) -> Due
B78: ='Monthly Collection-2023'!B78 -> 75 | C78: ='Monthly Collection-2023'!C78 -> Md. Borhan Uddin | D78: 1608600387 | E78: ='Monthly Collection-2023'!E78 -> 1 | F78: =E78*100 -> 100 | G78: ='Monthly Collection-2023'!AH78+'Monthly Collection-2024)'!BB78+'Monthly Collection-2025'!BB78+'Monthly Collection-2026'!BB78+'Monthly Collection-2027'!BB78+'Monthly Collection-2028'!BB78 -> 41000 | H78: ='Monthly Collection-2023'!AI78+'Monthly Collection-2024)'!BC78+'Monthly Collection-2025'!BC78+'Monthly Collection-2026'!BC78+'Monthly Collection-2027'!BC78+'Monthly Collection-2028'!BC78 -> 0 | I78: =IF(G78>(E78*1000*41),"Advanced",IF(G78<(E78*1000*41),"Due","Regular")) -> Regular
B79: ='Monthly Collection-2023'!B79 -> 76 | C79: ='Monthly Collection-2023'!C79 -> Mokter Ahmed | D79: 00966554277305 | E79: ='Monthly Collection-2023'!E79 -> 1 | F79: =E79*100 -> 100 | G79: ='Monthly Collection-2023'!AH79+'Monthly Collection-2024)'!BB79+'Monthly Collection-2025'!BB79+'Monthly Collection-2026'!BB79+'Monthly Collection-2027'!BB79+'Monthly Collection-2028'!BB79 -> 41000 | H79: ='Monthly Collection-2023'!AI79+'Monthly Collection-2024)'!BC79+'Monthly Collection-2025'!BC79+'Monthly Collection-2026'!BC79+'Monthly Collection-2027'!BC79+'Monthly Collection-2028'!BC79 -> 50 | I79: =IF(G79>(E79*1000*41),"Advanced",IF(G79<(E79*1000*41),"Due","Regular")) -> Regular
B80: ='Monthly Collection-2023'!B80 -> 77 | C80: ='Monthly Collection-2023'!C80 -> Nepal Kanti Karmaker | D80: 1812676040 | E80: ='Monthly Collection-2023'!E80 -> 1 | F80: =E80*100 -> 100 | G80: ='Monthly Collection-2023'!AH80+'Monthly Collection-2024)'!BB80+'Monthly Collection-2025'!BB80+'Monthly Collection-2026'!BB80+'Monthly Collection-2027'!BB80+'Monthly Collection-2028'!BB80 -> 41000 | H80: ='Monthly Collection-2023'!AI80+'Monthly Collection-2024)'!BC80+'Monthly Collection-2025'!BC80+'Monthly Collection-2026'!BC80+'Monthly Collection-2027'!BC80+'Monthly Collection-2028'!BC80 -> 950 | I80: =IF(G80>(E80*1000*41),"Advanced",IF(G80<(E80*1000*41),"Due","Regular")) -> Regular
B81: Grand Total | E81: =SUM(E4:E80) -> 125 | F81: =SUM(F4:F80) -> 12500 | G81: =SUM(G4:G80) -> 5084000 | H81: =SUM(H4:H80) -> 23150

Sheet Month Wise Collection Summary
A1: =HYPERLINK("#DASHBOARD!A1","⬅ Dashboard") -> ⬅ Dashboard
B2: Lohagara Progoti Youth Organization Kamar Pukur Par, Uzir Hat, Lohagara, Chittagong.
B3: Month | C3: Regular Deposit | D3: Advance | E3: Due Collection | F3: Fine | G3: CNG & Other Installment Collection | H3: Expense | I3: Bank Deposit
B4: 45078 | C4: ='Monthly Collection-2023'!F81 -> 124000 | D4: ='Monthly Collection-2023'!G81 -> 0 | E4: ='Monthly Collection-2023'!H81 -> 0 | F4: ='Monthly Collection-2023'!I81 -> 0 | H4: ='Month Wise Expenses'!D9 -> 6400 | I4: =SUM(C4:G4)-H4 -> 117600
B5: 45108 | C5: ='Monthly Collection-2023'!J81 -> 124000 | D5: ='Monthly Collection-2023'!K81 -> 4000 | E5: ='Monthly Collection-2023'!L81 -> 0 | F5: ='Monthly Collection-2023'!M81 -> 0 | H5: ='Month Wise Expenses'!D10 -> 300 | I5: =SUM(C5:G5)-H5 -> 127700
B6: 45139 | C6: ='Monthly Collection-2023'!N81 -> 122000 | D6: ='Monthly Collection-2023'!O81 -> 0 | E6: ='Monthly Collection-2023'!P81 -> 0 | F6: ='Monthly Collection-2023'!Q81 -> 50 | H6: ='Month Wise Expenses'!D11 -> 0 | I6: =SUM(C6:G6)-H6 -> 122050
B7: 45170 | C7: ='Monthly Collection-2023'!R81 -> 118000 | D7: ='Monthly Collection-2023'!S81 -> 11000 | E7: ='Monthly Collection-2023'!T81 -> 1000 | F7: ='Monthly Collection-2023'!U81 -> 200 | H7: ='Month Wise Expenses'!D12 -> 0 | I7: =SUM(C7:G7)-H7 -> 130200
B8: 45200 | C8: ='Monthly Collection-2023'!V81 -> 109000 | D8: ='Monthly Collection-2023'!W81 -> 0 | E8: ='Monthly Collection-2023'!X81 -> 5000 | F8: ='Monthly Collection-2023'!Y81 -> 300 | H8: ='Month Wise Expenses'!D13 -> 0 | I8: =SUM(C8:G8)-H8 -> 114300
B9: 45231 | C9: ='Monthly Collection-2023'!Z81 -> 108000 | D9: ='Monthly Collection-2023'!AA81 -> 0 | E9: ='Monthly Collection-2023'!AB81 -> 7000 | F9: ='Monthly Collection-2023'!AC81 -> 350 | H9: ='Month Wise Expenses'!D14 -> 0 | I9: =SUM(C9:G9)-H9 -> 115350
B10: 45261 | C10: ='Monthly Collection-2023'!AD81 -> 108000 | D10: ='Monthly Collection-2023'!AE81 -> 11000 | E10: ='Monthly Collection-2023'!AF81 -> 10000 | F10: ='Monthly Collection-2023'!AG81 -> 500 | H10: ='Month Wise Expenses'!D15 -> 0 | I10: =SUM(C10:G10)-H10 -> 129500
B11: 2023 Total | C11: =SUM(C4:C10) -> 813000 | D11: =SUM(D4:D10) -> 26000 | E11: =SUM(E4:E10) -> 23000 | F11: =SUM(F4:F10) -> 1400 | G11: =SUM(G4:G10) -> 0 | H11: =SUM(H4:H10) -> 6700 | I11: =SUM(I4:I10) -> 856700
B12: 45292 | C12: ='Monthly Collection-2024)'!F81 -> 112000 | D12: ='Monthly Collection-2024)'!G81 -> 0 | E12: ='Monthly Collection-2024)'!H81 -> 11000 | F12: ='Monthly Collection-2024)'!I81 -> 550 | H12: ='Month Wise Expenses'!G4 -> 0 | I12: =SUM(C12:G12)-H12 -> 123550
B13: 45323 | C13: ='Monthly Collection-2024)'!J81 -> 116000 | D13: ='Monthly Collection-2024)'!K81 -> 0 | E13: ='Monthly Collection-2024)'!L81 -> 2000 | F13: ='Monthly Collection-2024)'!M81 -> 100 | H13: ='Month Wise Expenses'!G5 -> 0 | I13: =SUM(C13:G13)-H13 -> 118100
B14: 45352 | C14: ='Monthly Collection-2024)'!N81 -> 119000 | D14: ='Monthly Collection-2024)'!O81 -> 11000 | E14: ='Monthly Collection-2024)'!P81 -> 3000 | F14: ='Monthly Collection-2024)'!Q81 -> 200 | H14: ='Month Wise Expenses'!G6 -> 0 | I14: =SUM(C14:G14)-H14 -> 133200
B15: 45383 | C15: ='Monthly Collection-2024)'!R81 -> 108000 | D15: ='Monthly Collection-2024)'!S81 -> 0 | E15: ='Monthly Collection-2024)'!T81 -> 2000 | F15: ='Monthly Collection-2024)'!U81 -> 200 | H15: ='Month Wise Expenses'!G7 -> 0 | I15: =SUM(C15:G15)-H15 -> 110200
B16: 45413 | C16: ='Monthly Collection-2024)'!V81 -> 104000 | D16: ='Monthly Collection-2024)'!W81 -> 4000 | E16: ='Monthly Collection-2024)'!X81 -> 32000 | F16: ='Monthly Collection-2024)'!Y81 -> 3800 | H16: ='Month Wise Expenses'!G8 -> 0 | I16: =SUM(C16:G16)-H16 -> 143800
B17: 45444 | C17: ='Monthly Collection-2024)'!Z81 -> 115000 | D17: ='Monthly Collection-2024)'!AA81 -> 6000 | E17: ='Monthly Collection-2024)'!AB81 -> 12000 | F17: ='Monthly Collection-2024)'!AC81 -> 600 | H17: ='Month Wise Expenses'!G9 -> 0 | I17: =SUM(C17:G17)-H17 -> 133600
B18: 45474 | C18: ='Monthly Collection-2024)'!AD81 -> 114000 | D18: ='Monthly Collection-2024)'!AE81 -> 11000 | E18: ='Monthly Collection-2024)'!AF81 -> 8000 | F18: ='Monthly Collection-2024)'!AG81 -> 550 | H18: ='Month Wise Expenses'!G10 -> 0 | I18: =SUM(C18:G18)-H18 -> 133550
B19: 45505 | C19: ='Monthly Collection-2024)'!AH81 -> 108000 | D19: ='Monthly Collection-2024)'!AI81 -> 8000 | E19: ='Monthly Collection-2024)'!AJ81 -> 8000 | F19: ='Monthly Collection-2024)'!AK81 -> 1350 | H19: ='Month Wise Expenses'!G11 -> 0 | I19: =SUM(C19:G19)-H19 -> 125350
B20: 45536 | C20: ='Monthly Collection-2024)'!AL81 -> 108000 | D20: ='Monthly Collection-2024)'!AM81 -> 3000 | E20: ='Monthly Collection-2024)'!AN81 -> 7000 | F20: ='Monthly Collection-2024)'!AO81 -> 400 | H20: ='Month Wise Expenses'!G12 -> 1000 | I20: =SUM(C20:G20)-H20 -> 117400
B21: 45566 | C21: ='Monthly Collection-2024)'!AP81 -> 109000 | D21: ='Monthly Collection-2024)'!AQ81 -> 6000 | E21: ='Monthly Collection-2024)'!AR81 -> 5000 | F21: ='Monthly Collection-2024)'!AS81 -> 250 | H21: ='Month Wise Expenses'!G13 -> 1000 | I21: =SUM(C21:G21)-H21 -> 119250
B22: 45597 | C22: ='Monthly Collection-2024)'!AT81 -> 111000 | D22: ='Monthly Collection-2024)'!AU81 -> 2000 | E22: ='Monthly Collection-2024)'!AV81 -> 14000 | F22: ='Monthly Collection-2024)'!AW81 -> 700 | H22: ='Month Wise Expenses'!G14 -> 1300 | I22: =SUM(C22:G22)-H22 -> 126400
B23: 45627 | C23: ='Monthly Collection-2024)'!AX81 -> 105000 | D23: ='Monthly Collection-2024)'!AY81 -> 8000 | E23: ='Monthly Collection-2024)'!AZ81 -> 4000 | F23: ='Monthly Collection-2024)'!BA81 -> 200 | H23: ='Month Wise Expenses'!G15 -> 1000 | I23: =SUM(C23:G23)-H23 -> 116200
B24: 2024 Total | C24: =SUM(C12:C23) -> 1329000 | D24: =SUM(D12:D23) -> 59000 | E24: =SUM(E12:E23) -> 108000 | F24: =SUM(F12:F23) -> 8900 | G24: =SUM(G12:G23) -> 0 | H24: =SUM(H12:H23) -> 4300 | I24: =SUM(I12:I23) -> 1500600
B25: 45658 | C25: ='Monthly Collection-2025'!F81 -> 113000 | D25: ='Monthly Collection-2025'!G81 -> 14000 | E25: ='Monthly Collection-2025'!H81 -> 20000 | F25: ='Monthly Collection-2025'!I81 -> 1000 | G25: ='Month Wise CNG Instlmnt Summary'!C4 -> 30000 | H25: ='Month Wise Expenses'!J4 -> 1000 | I25: =SUM(C25:G25)-H25 -> 177000
B26: 45689 | C26: ='Monthly Collection-2025'!J81 -> 113000 | D26: ='Monthly Collection-2025'!K81 -> 2000 | E26: ='Monthly Collection-2025'!L81 -> 12000 | F26: ='Monthly Collection-2025'!M81 -> 750 | G26: ='Month Wise CNG Instlmnt Summary'!C5 -> 30000 | H26: ='Month Wise Expenses'!J5 -> 1250 | I26: =SUM(C26:G26)-H26 -> 156500
B27: 45717 | C27: ='Monthly Collection-2025'!N81 -> 108000 | D27: ='Monthly Collection-2025'!O81 -> 4000 | E27: ='Monthly Collection-2025'!P81 -> 3000 | F27: ='Monthly Collection-2025'!Q81 -> 150 | G27: ='Month Wise CNG Instlmnt Summary'!C6 -> 45000 | H27: ='Month Wise Expenses'!J6 -> 1400 | I27: =SUM(C27:G27)-H27 -> 158750
B28: 45748 | C28: ='Monthly Collection-2025'!R81 -> 104000 | D28: ='Monthly Collection-2025'!S81 -> 5000 | E28: ='Monthly Collection-2025'!T81 -> 10000 | F28: ='Monthly Collection-2025'!U81 -> 500 | G28: ='Month Wise CNG Instlmnt Summary'!C7 -> 45000 | H28: ='Month Wise Expenses'!J7 -> 1000 | I28: =SUM(C28:G28)-H28 -> 163500
B29: 45778 | C29: ='Monthly Collection-2025'!V81 -> 108000 | D29: ='Monthly Collection-2025'!W81 -> 8000 | E29: ='Monthly Collection-2025'!X81 -> 18000 | F29: ='Monthly Collection-2025'!Y81 -> 950 | G29: ='Month Wise CNG Instlmnt Summary'!C8 -> 55000 | H29: ='Month Wise Expenses'!J8 -> 1000 | I29: =SUM(C29:G29)-H29 -> 188950
B30: 45809 | C30: ='Monthly Collection-2025'!Z81 -> 107000 | D30: ='Monthly Collection-2025'!AA81 -> 5000 | E30: ='Monthly Collection-2025'!AB81 -> 7000 | F30: ='Monthly Collection-2025'!AC81 -> 350 | G30: ='Month Wise CNG Instlmnt Summary'!C9 -> 40000 | H30: ='Month Wise Expenses'!J9 -> 1000 | I30: =SUM(C30:G30)-H30 -> 158350
B31: 45839 | C31: ='Monthly Collection-2025'!AD81 -> 102000 | D31: ='Monthly Collection-2025'!AE81 -> 12000 | E31: ='Monthly Collection-2025'!AF81 -> 9000 | F31: ='Monthly Collection-2025'!AG81 -> 450 | G31: ='Month Wise CNG Instlmnt Summary'!C10 -> 55000 | H31: ='Month Wise Expenses'!J10 -> 1250 | I31: =SUM(C31:G31)-H31 -> 177200
B32: 45870 | C32: ='Monthly Collection-2025'!AH81 -> 108000 | D32: ='Monthly Collection-2025'!AI81 -> 2000 | E32: ='Monthly Collection-2025'!AJ81 -> 24000 | F32: ='Monthly Collection-2025'!AK81 -> 1250 | G32: ='Month Wise CNG Instlmnt Summary'!C11 -> 55000 | H32: ='Month Wise Expenses'!J11 -> 4000 | I32: =SUM(C32:G32)-H32 -> 186250
B33: 45901 | C33: ='Monthly Collection-2025'!AL81 -> 105000 | D33: ='Monthly Collection-2025'!AM81 -> 10000 | E33: ='Monthly Collection-2025'!AN81 -> 3000 | F33: ='Monthly Collection-2025'!AO81 -> 150 | G33: ='Month Wise CNG Instlmnt Summary'!C12+2700 -> 57700 | H33: ='Month Wise Expenses'!J12 -> 3250 | I33: =SUM(C33:G33)-H33 -> 172600
B34: 45931 | C34: ='Monthly Collection-2025'!AP81 -> 108000 | D34: ='Monthly Collection-2025'!AQ81 -> 3000 | E34: ='Monthly Collection-2025'!AR81 -> 11000 | F34: ='Monthly Collection-2025'!AS81 -> 900 | G34: ='Month Wise CNG Instlmnt Summary'!C13 -> 55000 | H34: ='Month Wise Expenses'!J13 -> 1250 | I34: =SUM(C34:G34)-H34 -> 176650
B35: 45962 | C35: ='Monthly Collection-2025'!AT81 -> 114000 | D35: ='Monthly Collection-2025'!AU81 -> 5000 | E35: ='Monthly Collection-2025'!AV81 -> 11000 | F35: ='Monthly Collection-2025'!AW81 -> 550 | G35: ='Month Wise CNG Instlmnt Summary'!C14+27000 -> 93000 | H35: ='Month Wise Expenses'!J14 -> 1000 | I35: =SUM(C35:G35)-H35 -> 222550
B36: 45992 | C36: ='Monthly Collection-2025'!AX81 -> 109000 | D36: ='Monthly Collection-2025'!AY81 -> 0 | E36: ='Monthly Collection-2025'!AZ81 -> 10000 | F36: ='Monthly Collection-2025'!BA81 -> 500 | G36: ='Month Wise CNG Instlmnt Summary'!C15 -> 72000 | H36: ='Month Wise Expenses'!J15 -> 1000 | I36: =SUM(C36:G36)-H36 -> 190500
B37: 2025 Total | C37: =SUM(C25:C36) -> 1299000 | D37: =SUM(D25:D36) -> 70000 | E37: =SUM(E25:E36) -> 138000 | F37: =SUM(F25:F36) -> 7500 | G37: =SUM(G25:G36) -> 632700 | H37: =SUM(H25:H36) -> 18400 | I37: =SUM(I25:I36) -> 2128800
B38: 46023 | C38: ='Monthly Collection-2026'!F81 -> 114000 | D38: ='Monthly Collection-2026'!G81 -> 8000 | E38: ='Monthly Collection-2026'!H81 -> 3000 | F38: ='Monthly Collection-2026'!I81 -> 150 | G38: ='Month Wise CNG Instlmnt Summary'!F4 -> 66000 | H38: ='Month Wise Expenses'!M4 -> 50697 | I38: =SUM(C38:G38)-H38 -> 140453
B39: 46054 | C39: ='Monthly Collection-2026'!J81 -> 105000 | D39: ='Monthly Collection-2026'!K81 -> 4000 | E39: ='Monthly Collection-2026'!L81 -> 10000 | F39: ='Monthly Collection-2026'!M81 -> 500 | G39: ='Month Wise CNG Instlmnt Summary'!F5 -> 73000 | H39: ='Month Wise Expenses'!M5 -> 1000 | I39: =SUM(C39:G39)-H39 -> 191500
B40: 46082 | C40: ='Monthly Collection-2026'!N81 -> 106000 | D40: ='Monthly Collection-2026'!O81 -> 12000 | E40: ='Monthly Collection-2026'!P81 -> 8000 | F40: ='Monthly Collection-2026'!Q81 -> 400 | G40: ='Month Wise CNG Instlmnt Summary'!F6 -> 55000 | H40: ='Month Wise Expenses'!M6 -> 1000 | I40: =SUM(C40:G40)-H40 -> 180400
B41: 46113 | C41: ='Monthly Collection-2026'!R81 -> 107000 | D41: ='Monthly Collection-2026'!S81 -> 13000 | E41: ='Monthly Collection-2026'!T81 -> 20000 | F41: ='Monthly Collection-2026'!U81 -> 1000 | G41: ='Month Wise CNG Instlmnt Summary'!F7 -> 118500 | H41: 100 | I41: =SUM(C41:G41)-H41 -> 259400
B42: 46143 | C42: ='Monthly Collection-2026'!V81 -> 101000 | D42: ='Monthly Collection-2026'!W81 -> 1000 | E42: ='Monthly Collection-2026'!X81 -> 5000 | F42: ='Monthly Collection-2026'!Y81 -> 300 | G42: ='Month Wise CNG Instlmnt Summary'!F8 -> 74000 | H42: ='Month Wise Expenses'!M8 -> 200 | I42: =SUM(C42:G42)-H42 -> 181100
B43: 46174 | C43: ='Monthly Collection-2026'!Z81 -> 107000 | D43: ='Monthly Collection-2026'!AA81 -> 5000 | E43: ='Monthly Collection-2026'!AB81 -> 13000 | F43: ='Monthly Collection-2026'!AC81 -> 650 | G43: ='Month Wise CNG Instlmnt Summary'!F9+59000 -> 127000 | H43: ='Month Wise Expenses'!M9 -> 100 | I43: =SUM(C43:G43)-H43 -> 252550
B44: 46204 | C44: ='Monthly Collection-2026'!AD81 -> 107000 | D44: ='Monthly Collection-2026'!AE81 -> 2000 | E44: ='Monthly Collection-2026'!AF81 -> 7000 | F44: ='Monthly Collection-2026'!AG81 -> 350 | G44: ='Month Wise CNG Instlmnt Summary'!F10 -> 81000 | H44: ='Month Wise Expenses'!M10 -> 0 | I44: =SUM(C44:G44)-H44 -> 197350
B45: 46235 | C45: ='Monthly Collection-2026'!AH81 -> 109000 | D45: ='Monthly Collection-2026'!AI81 -> 2000 | E45: ='Monthly Collection-2026'!AJ81 -> 21000 | F45: ='Monthly Collection-2026'!AK81 -> 1050 | G45: ='Month Wise CNG Instlmnt Summary'!F11 -> 74000 | H45: ='Month Wise Expenses'!M11 -> 100 | I45: =SUM(C45:G45)-H45 -> 206950
B46: 46266 | C46: ='Monthly Collection-2026'!AL81 -> 104000 | D46: ='Monthly Collection-2026'!AM81 -> 10000 | E46: ='Monthly Collection-2026'!AN81 -> 8000 | F46: ='Monthly Collection-2026'!AO81 -> 400 | G46: ='Month Wise CNG Instlmnt Summary'!F12 -> 88000 | H46: ='Month Wise Expenses'!M12 -> 200 | I46: =SUM(C46:G46)-H46 -> 210200
B47: 46296 | C47: ='Monthly Collection-2026'!AP81 -> 92000 | D47: ='Monthly Collection-2026'!AQ81 -> 4000 | E47: ='Monthly Collection-2026'!AR81 -> 11000 | F47: ='Monthly Collection-2026'!AS81 -> 550 | G47: ='Month Wise CNG Instlmnt Summary'!F13 -> 110000 | H47: ='Month Wise Expenses'!M13 -> 272.83 | I47: =SUM(C47:G47)-H47 -> 217277.17
B48: 46327 | C48: ='Monthly Collection-2026'!AT81 -> 0 | D48: ='Monthly Collection-2026'!AU81 -> 0 | E48: ='Monthly Collection-2026'!AV81 -> 0 | F48: ='Monthly Collection-2026'!AW81 -> 0 | G48: ='Month Wise CNG Instlmnt Summary'!F14 -> 0 | H48: ='Month Wise Expenses'!M14 -> 0 | I48: =SUM(C48:G48)-H48 -> 0
B49: 46357 | C49: ='Monthly Collection-2026'!AX81 -> 0 | D49: ='Monthly Collection-2026'!AY81 -> 0 | E49: ='Monthly Collection-2026'!AZ81 -> 0 | F49: ='Monthly Collection-2026'!BA81 -> 0 | G49: ='Month Wise CNG Instlmnt Summary'!F15 -> 0 | H49: ='Month Wise Expenses'!M15 -> 0 | I49: =SUM(C49:G49)-H49 -> 0
B50: 2026 Total | C50: =SUM(C38:C49) -> 1052000 | D50: =SUM(D38:D49) -> 61000 | E50: =SUM(E38:E49) -> 106000 | F50: =SUM(F38:F49) -> 5350 | G50: =SUM(G38:G49) -> 866500 | H50: =SUM(H38:H49) -> 53669.83 | I50: =SUM(I38:I49) -> 2037180.2
B51: 46388 | C51: ='Monthly Collection-2027'!F81 -> 0 | D51: ='Monthly Collection-2027'!G81 -> 0 | E51: ='Monthly Collection-2027'!H81 -> 0 | F51: ='Monthly Collection-2027'!I81 -> 0 | H51: ='Month Wise Expenses'!P4 -> 0 | I51: =SUM(C51:G51)-H51 -> 0
B52: 46419 | C52: ='Monthly Collection-2027'!J81 -> 0 | D52: ='Monthly Collection-2027'!K81 -> 0 | E52: ='Monthly Collection-2027'!L81 -> 0 | F52: ='Monthly Collection-2027'!M81 -> 0 | H52: ='Month Wise Expenses'!P5 -> 0 | I52: =SUM(C52:G52)-H52 -> 0
B53: 46447 | C53: ='Monthly Collection-2027'!N81 -> 0 | D53: ='Monthly Collection-2027'!O81 -> 0 | E53: ='Monthly Collection-2027'!P81 -> 0 | F53: ='Monthly Collection-2027'!Q81 -> 0 | H53: ='Month Wise Expenses'!P6 -> 0 | I53: =SUM(C53:G53)-H53 -> 0
B54: 46478 | C54: ='Monthly Collection-2027'!R81 -> 0 | D54: ='Monthly Collection-2027'!S81 -> 0 | E54: ='Monthly Collection-2027'!T81 -> 0 | F54: ='Monthly Collection-2027'!U81 -> 0 | H54: ='Month Wise Expenses'!P7 -> 0 | I54: =SUM(C54:G54)-H54 -> 0
B55: 46508 | C55: ='Monthly Collection-2027'!V81 -> 0 | D55: ='Monthly Collection-2027'!W81 -> 0 | E55: ='Monthly Collection-2027'!X81 -> 0 | F55: ='Monthly Collection-2027'!Y81 -> 0 | H55: ='Month Wise Expenses'!P8 -> 0 | I55: =SUM(C55:G55)-H55 -> 0
B56: 46539 | C56: ='Monthly Collection-2027'!Z81 -> 0 | D56: ='Monthly Collection-2027'!AA81 -> 0 | E56: ='Monthly Collection-2027'!AB81 -> 0 | F56: ='Monthly Collection-2027'!AC81 -> 0 | H56: ='Month Wise Expenses'!P9 -> 0 | I56: =SUM(C56:G56)-H56 -> 0
B57: 46569 | C57: ='Monthly Collection-2027'!AD81 -> 0 | D57: ='Monthly Collection-2027'!AE81 -> 0 | E57: ='Monthly Collection-2027'!AF81 -> 0 | F57: ='Monthly Collection-2027'!AG81 -> 0 | H57: ='Month Wise Expenses'!P10 -> 0 | I57: =SUM(C57:G57)-H57 -> 0
B58: 46600 | C58: ='Monthly Collection-2027'!AH81 -> 0 | D58: ='Monthly Collection-2027'!AI81 -> 0 | E58: ='Monthly Collection-2027'!AJ81 -> 0 | F58: ='Monthly Collection-2027'!AK81 -> 0 | H58: ='Month Wise Expenses'!P11 -> 0 | I58: =SUM(C58:G58)-H58 -> 0
B59: 46631 | C59: ='Monthly Collection-2027'!AL81 -> 0 | D59: ='Monthly Collection-2027'!AM81 -> 0 | E59: ='Monthly Collection-2027'!AN81 -> 0 | F59: ='Monthly Collection-2027'!AO81 -> 0 | H59: ='Month Wise Expenses'!P12 -> 0 | I59: =SUM(C59:G59)-H59 -> 0
B60: 46661 | C60: ='Monthly Collection-2027'!AP81 -> 0 | D60: ='Monthly Collection-2027'!AQ81 -> 0 | E60: ='Monthly Collection-2027'!AR81 -> 0 | F60: ='Monthly Collection-2027'!AS81 -> 0 | H60: ='Month Wise Expenses'!P13 -> 0 | I60: =SUM(C60:G60)-H60 -> 0
B61: 46692 | C61: ='Monthly Collection-2027'!AT81 -> 0 | D61: ='Monthly Collection-2027'!AU81 -> 0 | E61: ='Monthly Collection-2027'!AV81 -> 0 | F61: ='Monthly Collection-2027'!AW81 -> 0 | H61: ='Month Wise Expenses'!P14 -> 0 | I61: =SUM(C61:G61)-H61 -> 0
B62: 46722 | C62: ='Monthly Collection-2027'!AX81 -> 0 | D62: ='Monthly Collection-2027'!AY81 -> 0 | E62: ='Monthly Collection-2027'!AZ81 -> 0 | F62: ='Monthly Collection-2027'!BA81 -> 0 | H62: ='Month Wise Expenses'!P15 -> 0 | I62: =SUM(C62:G62)-H62 -> 0
B63: 2027 Total | C63: =SUM(C51:C62) -> 0 | D63: =SUM(D51:D62) -> 0 | E63: =SUM(E51:E62) -> 0 | F63: =SUM(F51:F62) -> 0 | G63: =SUM(G51:G62) -> 0 | H63: =SUM(H51:H62) -> 0 | I63: =SUM(I51:I62) -> 0
B64: 46753 | C64: ='Monthly Collection-2028'!F81 -> 0 | D64: ='Monthly Collection-2028'!G81 -> 0 | E64: ='Monthly Collection-2028'!H81 -> 0 | F64: ='Monthly Collection-2028'!I81 -> 0 | H64: ='Month Wise Expenses'!S4 -> 0 | I64: =SUM(C64:G64)-H64 -> 0
B65: 46784 | C65: ='Monthly Collection-2028'!J81 -> 0 | D65: ='Monthly Collection-2028'!K81 -> 0 | E65: ='Monthly Collection-2028'!L81 -> 0 | F65: ='Monthly Collection-2028'!M81 -> 0 | H65: ='Month Wise Expenses'!S5 -> 0 | I65: =SUM(C65:G65)-H65 -> 0
B66: 46813 | C66: ='Monthly Collection-2028'!N81 -> 0 | D66: ='Monthly Collection-2028'!O81 -> 0 | E66: ='Monthly Collection-2028'!P81 -> 0 | F66: ='Monthly Collection-2028'!Q81 -> 0 | H66: ='Month Wise Expenses'!S6 -> 0 | I66: =SUM(C66:G66)-H66 -> 0
B67: 46844 | C67: ='Monthly Collection-2028'!R81 -> 0 | D67: ='Monthly Collection-2028'!S81 -> 0 | E67: ='Monthly Collection-2028'!T81 -> 0 | F67: ='Monthly Collection-2028'!U81 -> 0 | H67: ='Month Wise Expenses'!S7 -> 0 | I67: =SUM(C67:G67)-H67 -> 0
B68: 46874 | C68: ='Monthly Collection-2028'!V81 -> 0 | D68: ='Monthly Collection-2028'!W81 -> 0 | E68: ='Monthly Collection-2028'!X81 -> 0 | F68: ='Monthly Collection-2028'!Y81 -> 0 | H68: ='Month Wise Expenses'!S8 -> 0 | I68: =SUM(C68:G68)-H68 -> 0
B69: 46905 | C69: ='Monthly Collection-2028'!Z81 -> 0 | D69: ='Monthly Collection-2028'!AA81 -> 0 | E69: ='Monthly Collection-2028'!AB81 -> 0 | F69: ='Monthly Collection-2028'!AC81 -> 0 | H69: ='Month Wise Expenses'!S9 -> 0 | I69: =SUM(C69:G69)-H69 -> 0
B70: 46935 | C70: ='Monthly Collection-2028'!AD81 -> 0 | D70: ='Monthly Collection-2028'!AE81 -> 0 | E70: ='Monthly Collection-2028'!AF81 -> 0 | F70: ='Monthly Collection-2028'!AG81 -> 0 | H70: ='Month Wise Expenses'!S10 -> 0 | I70: =SUM(C70:G70)-H70 -> 0
B71: 46966 | C71: ='Monthly Collection-2028'!AH81 -> 0 | D71: ='Monthly Collection-2028'!AI81 -> 0 | E71: ='Monthly Collection-2028'!AJ81 -> 0 | F71: ='Monthly Collection-2028'!AK81 -> 0 | H71: ='Month Wise Expenses'!S11 -> 0 | I71: =SUM(C71:G71)-H71 -> 0
B72: 46997 | C72: ='Monthly Collection-2028'!AL81 -> 0 | D72: ='Monthly Collection-2028'!AM81 -> 0 | E72: ='Monthly Collection-2028'!AN81 -> 0 | F72: ='Monthly Collection-2028'!AO81 -> 0 | H72: ='Month Wise Expenses'!S12 -> 0 | I72: =SUM(C72:G72)-H72 -> 0
B73: 47027 | C73: ='Monthly Collection-2028'!AP81 -> 0 | D73: ='Monthly Collection-2028'!AQ81 -> 0 | E73: ='Monthly Collection-2028'!AR81 -> 0 | F73: ='Monthly Collection-2028'!AS81 -> 0 | H73: ='Month Wise Expenses'!S13 -> 0 | I73: =SUM(C73:G73)-H73 -> 0
B74: 47058 | C74: ='Monthly Collection-2028'!AT81 -> 0 | D74: ='Monthly Collection-2028'!AU81 -> 0 | E74: ='Monthly Collection-2028'!AV81 -> 0 | F74: ='Monthly Collection-2028'!AW81 -> 0 | H74: ='Month Wise Expenses'!S14 -> 0 | I74: =SUM(C74:G74)-H74 -> 0
B75: 47088 | C75: ='Monthly Collection-2028'!AX81 -> 0 | D75: ='Monthly Collection-2028'!AY81 -> 0 | E75: ='Monthly Collection-2028'!AZ81 -> 0 | F75: ='Monthly Collection-2028'!BA81 -> 0 | H75: ='Month Wise Expenses'!S15 -> 0 | I75: =SUM(C75:G75)-H75 -> 0
B76: 2028 Total | C76: =SUM(C64:C75) -> 0 | D76: =SUM(D64:D75) -> 0 | E76: =SUM(E64:E75) -> 0 | F76: =SUM(F64:F75) -> 0 | G76: =SUM(G64:G75) -> 0 | H76: =SUM(H64:H75) -> 0 | I76: =SUM(I64:I75) -> 0
B77: Grand Total | C77: =C11+C24+C37+C50+C63+C76 -> 4493000 | D77: =D11+D24+D37+D50+D63+D76 -> 216000 | E77: =E11+E24+E37+E50+E63+E76 -> 375000 | F77: =F11+F24+F37+F50+F63+F76 -> 23150 | G77: =G11+G24+G37+G50+G63+G76 -> 1499200 | H77: =H11+H24+H37+H50+H63+H76 -> 83069.83 | I77: =I11+I24+I37+I50+I63+I76 -> 6523280.2

Sheet Month Wise Expenses
A1: =HYPERLINK("#DASHBOARD!A1","⬅ Dashboard") -> ⬅ Dashboard
B2: 2023 | E2: 2024 | H2: 2025 | K2: 2026 | N2: 2027 | Q2: 2028
B3: Month | C3: Description | D3: Expenses | E3: Month | F3: Description | G3: Expenses | H3: Month | I3: Description | J3: Expenses | K3: Month | L3: Description | M3: Expenses | N3: Month | O3: Description | P3: Expenses | Q3: Month | R3: Description | S3: Expenses
E4: January | F4: Expense | G4: 0 | H4: January | I4: Cashier Salary | J4: 1000 | K4: January | L4: Picnic Expense & Cashier Salary | M4: =1200+48570+927 -> 50697 | N4: January | Q4: January
E5: February | F5: Expense | G5: 0 | H5: February | I5: Cashier Salary & Other | J5: 1250 | K5: February | L5: Cashier Salary | M5: 1000 | N5: February | Q5: February
E6: March | F6: Expense | G6: 0 | H6: March | I6: Cashier Salary & Other | J6: 1400 | K6: March | L6: Cashier Salary | M6: 1000 | N6: March | Q6: March
E7: April | F7: Expense | G7: 0 | H7: April | I7: Cashier Salary | J7: 1000 | K7: April | L7: Print Cost | M7: 100 | N7: April | Q7: April
E8: May | F8: Expense | G8: 0 | H8: May | I8: Cashier Salary | J8: 1000 | K8: May | L8: Form Print & Snacks | M8: 200 | N8: May | Q8: May
B9: June | C9: Cash Memmo Book & Money Receipt Book Print | D9: 6400 | E9: June | F9: Expense | G9: 0 | H9: June | I9: Cashier Salary | J9: 1000 | K9: June | L9: Snacks | M9: 100 | N9: June
B10: July | C10: Snacks & Others | D10: 300 | E10: July | F10: Expense | G10: 0 | H10: July | I10: Cashier Salary & Other | J10: 1250 | K10: July | L10: Expense | M10: 0 | N10: July
B11: August | C11: Expense | D11: 0 | E11: August | F11: Expense | G11: 0 | H11: August | I11: Cashier Salary & Cabinet Purchase | J11: 4000 | K11: August | L11: Snacks | M11: 100 | N11: August
B12: September | C12: Expense | D12: 0 | E12: September | F12: Cashier Salary | G12: 1000 | H12: September | I12: Cashier Salary & Chair Purchase | J12: 3250 | K12: September | L12: Form Print & Snacks | M12: 200 | N12: September
B13: October | C13: Expense | D13: 0 | E13: October | F13: Cashier Salary | G13: 1000 | H13: October | I13: Cashier Salary & Other | J13: 1250 | K13: October | L13: Snacks & Bank SMS Charge | M13: =100+172.83 -> 272.83 | N13: October
B14: November | C14: Expense | D14: 0 | E14: November | F14: Cashier Salary & Other | G14: 1300 | H14: November | I14: Cashier Salary | J14: 1000 | K14: November | N14: November
B15: December | C15: Expense | D15: 0 | E15: December | F15: Cashier Salary | G15: 1000 | H15: December | I15: Cashier Salary | J15: 1000 | K15: December | N15: December
B16: Total | D16: =SUM(D4:D15) -> 6700 | G16: =SUM(G4:G15) -> 4300 | J16: =SUM(J4:J15) -> 18400 | M16: =SUM(M4:M15) -> 53669.83 | P16: =SUM(P4:P15) -> 0 | S16: =SUM(S4:S15) -> 0

Sheet Monthly Collection-2023
A1: =HYPERLINK("#DASHBOARD!A1","⬅ Dashboard") -> ⬅ Dashboard | AK1: AUTO HELPER (do not edit): Status R=Due, G=Advance-covered; Advance balance carried month to month. Use the [+] above to expand.
B2: Member ID. | C2: Name | D2: Mobile Number | E2: Number of Shares | F2: 45078 | J2: =EDATE($F2,1) -> 45108 | N2: =EDATE($F2,2) -> 45139 | R2: =EDATE($F2,3) -> 45170 | V2: =EDATE($F2,4) -> 45200 | Z2: =EDATE($F2,5) -> 45231 | AD2: =EDATE($F2,6) -> 45261 | AH2: Total Deposit | AI2: Total Fine | AL2: =F$2 -> 45078 | AN2: =J$2 -> 45108 | AP2: =N$2 -> 45139 | AR2: =R$2 -> 45170 | AT2: =V$2 -> 45200 | AV2: =Z$2 -> 45231 | AX2: =AD$2 -> 45261
F3: Regular Deposit | G3: Advance | H3: Due Collection | I3: Fine | J3: Regular Deposit | K3: Advance | L3: Due Collection | M3: Fine | N3: Regular Deposit | O3: Advance | P3: Due Collection | Q3: Fine | R3: Regular Deposit | S3: Advance | T3: Due Collection | U3: Fine | V3: Regular Deposit | W3: Advance | X3: Due Collection | Y3: Fine | Z3: Regular Deposit | AA3: Advance | AB3: Due Collection | AC3: Fine | AD3: Regular Deposit | AE3: Advance | AF3: Due Collection | AG3: Fine | AK3: Carry-in adv | AL3: Status | AM3: Adv balance | AN3: Status | AO3: Adv balance | AP3: Status | AQ3: Adv balance | AR3: Status | AS3: Adv balance | AT3: Status | AU3: Adv balance | AV3: Status | AW3: Adv balance | AX3: Status | AY3: Adv balance
B4: =ROW()-3 -> 1 | C4: Monjurul Islam | D4: ='Member Wise Deposit Summary'!D4 -> 1814824030 | E4: 3 | F4: =$E4*1000 -> 3000 | J4: =$E4*1000 -> 3000 | N4: =$E4*1000 -> 3000 | R4: =$E4*1000 -> 3000 | V4: =$E4*1000 -> 3000 | AD4: 3000 | AF4: 3000 | AG4: 150 | AH4: =F4+G4+H4+J4+K4+L4+N4+O4+P4+R4+S4+T4+V4+W4+X4+Z4+AA4+AB4+AD4+AE4+AF4 -> 21000 | AI4: =I4+M4+Q4+U4+Y4+AC4+AG4 -> 150 | AK4: 0 | AL4: =IF(N(F4)>=$E4*1000,"",IF(AND($E4>0,AK4>=$E4*1000),"G",IF(F$2<=TODAY(),"R",""))) | AM4: =AK4-IF(AL4="G",$E4*1000,0)+N(G4) -> 0 | AN4: =IF(N(J4)>=$E4*1000,"",IF(AND($E4>0,AM4>=$E4*1000),"G",IF(J$2<=TODAY(),"R",""))) | AO4: =AM4-IF(AN4="G",$E4*1000,0)+N(K4) -> 0 | AP4: =IF(N(N4)>=$E4*1000,"",IF(AND($E4>0,AO4>=$E4*1000),"G",IF(N$2<=TODAY(),"R",""))) | AQ4: =AO4-IF(AP4="G",$E4*1000,0)+N(O4) -> 0 | AR4: =IF(N(R4)>=$E4*1000,"",IF(AND($E4>0,AQ4>=$E4*1000),"G",IF(R$2<=TODAY(),"R",""))) | AS4: =AQ4-IF(AR4="G",$E4*1000,0)+N(S4) -> 0 | AT4: =IF(N(V4)>=$E4*1000,"",IF(AND($E4>0,AS4>=$E4*1000),"G",IF(V$2<=TODAY(),"R",""))) | AU4: =AS4-IF(AT4="G",$E4*1000,0)+N(W4) -> 0 | AV4: =IF(N(Z4)>=$E4*1000,"",IF(AND($E4>0,AU4>=$E4*1000),"G",IF(Z$2<=TODAY(),"R",""))) -> R | AW4: =AU4-IF(AV4="G",$E4*1000,0)+N(AA4) -> 0 | AX4: =IF(N(AD4)>=$E4*1000,"",IF(AND($E4>0,AW4>=$E4*1000),"G",IF(AD$2<=TODAY(),"R",""))) | AY4: =AW4-IF(AX4="G",$E4*1000,0)+N(AE4) -> 0
B5: =ROW()-3 -> 2 | C5: Saiful Islam | D5: ='Member Wise Deposit Summary'!D5 -> 1816724075 | E5: 2 | F5: =$E5*1000 -> 2000 | J5: =$E5*1000 -> 2000 | N5: =$E5*1000 -> 2000 | R5: =$E5*1000 -> 2000 | V5: =$E5*1000 -> 2000 | Z5: =$E5*1000 -> 2000 | AD5: =$E5*1000 -> 2000 | AH5: =F5+G5+H5+J5+K5+L5+N5+O5+P5+R5+S5+T5+V5+W5+X5+Z5+AA5+AB5+AD5+AE5+AF5 -> 14000 | AI5: =I5+M5+Q5+U5+Y5+AC5+AG5 -> 0 | AK5: 0 | AL5: =IF(N(F5)>=$E5*1000,"",IF(AND($E5>0,AK5>=$E5*1000),"G",IF(F$2<=TODAY(),"R",""))) | AM5: =AK5-IF(AL5="G",$E5*1000,0)+N(G5) -> 0 | AN5: =IF(N(J5)>=$E5*1000,"",IF(AND($E5>0,AM5>=$E5*1000),"G",IF(J$2<=TODAY(),"R",""))) | AO5: =AM5-IF(AN5="G",$E5*1000,0)+N(K5) -> 0 | AP5: =IF(N(N5)>=$E5*1000,"",IF(AND($E5>0,AO5>=$E5*1000),"G",IF(N$2<=TODAY(),"R",""))) | AQ5: =AO5-IF(AP5="G",$E5*1000,0)+N(O5) -> 0 | AR5: =IF(N(R5)>=$E5*1000,"",IF(AND($E5>0,AQ5>=$E5*1000),"G",IF(R$2<=TODAY(),"R",""))) | AS5: =AQ5-IF(AR5="G",$E5*1000,0)+N(S5) -> 0 | AT5: =IF(N(V5)>=$E5*1000,"",IF(AND($E5>0,AS5>=$E5*1000),"G",IF(V$2<=TODAY(),"R",""))) | AU5: =AS5-IF(AT5="G",$E5*1000,0)+N(W5) -> 0 | AV5: =IF(N(Z5)>=$E5*1000,"",IF(AND($E5>0,AU5>=$E5*1000),"G",IF(Z$2<=TODAY(),"R",""))) | AW5: =AU5-IF(AV5="G",$E5*1000,0)+N(AA5) -> 0 | AX5: =IF(N(AD5)>=$E5*1000,"",IF(AND($E5>0,AW5>=$E5*1000),"G",IF(AD$2<=TODAY(),"R",""))) | AY5: =AW5-IF(AX5="G",$E5*1000,0)+N(AE5) -> 0
B6: =ROW()-3 -> 3 | C6: Mohammad Tawhidul Islam | D6: ='Member Wise Deposit Summary'!D6 -> 1846506898 | E6: 2 | F6: =$E6*1000 -> 2000 | J6: =$E6*1000 -> 2000 | N6: =$E6*1000 -> 2000 | R6: =$E6*1000 -> 2000 | V6: =$E6*1000 -> 2000 | Z6: =$E6*1000 -> 2000 | AH6: =F6+G6+H6+J6+K6+L6+N6+O6+P6+R6+S6+T6+V6+W6+X6+Z6+AA6+AB6+AD6+AE6+AF6 -> 12000 | AI6: =I6+M6+Q6+U6+Y6+AC6+AG6 -> 0 | AK6: 0 | AL6: =IF(N(F6)>=$E6*1000,"",IF(AND($E6>0,AK6>=$E6*1000),"G",IF(F$2<=TODAY(),"R",""))) | AM6: =AK6-IF(AL6="G",$E6*1000,0)+N(G6) -> 0 | AN6: =IF(N(J6)>=$E6*1000,"",IF(AND($E6>0,AM6>=$E6*1000),"G",IF(J$2<=TODAY(),"R",""))) | AO6: =AM6-IF(AN6="G",$E6*1000,0)+N(K6) -> 0 | AP6: =IF(N(N6)>=$E6*1000,"",IF(AND($E6>0,AO6>=$E6*1000),"G",IF(N$2<=TODAY(),"R",""))) | AQ6: =AO6-IF(AP6="G",$E6*1000,0)+N(O6) -> 0 | AR6: =IF(N(R6)>=$E6*1000,"",IF(AND($E6>0,AQ6>=$E6*1000),"G",IF(R$2<=TODAY(),"R",""))) | AS6: =AQ6-IF(AR6="G",$E6*1000,0)+N(S6) -> 0 | AT6: =IF(N(V6)>=$E6*1000,"",IF(AND($E6>0,AS6>=$E6*1000),"G",IF(V$2<=TODAY(),"R",""))) | AU6: =AS6-IF(AT6="G",$E6*1000,0)+N(W6) -> 0 | AV6: =IF(N(Z6)>=$E6*1000,"",IF(AND($E6>0,AU6>=$E6*1000),"G",IF(Z$2<=TODAY(),"R",""))) | AW6: =AU6-IF(AV6="G",$E6*1000,0)+N(AA6) -> 0 | AX6: =IF(N(AD6)>=$E6*1000,"",IF(AND($E6>0,AW6>=$E6*1000),"G",IF(AD$2<=TODAY(),"R",""))) -> R | AY6: =AW6-IF(AX6="G",$E6*1000,0)+N(AE6) -> 0
B7: =ROW()-3 -> 4 | C7: Amanat Khan | D7: ='Member Wise Deposit Summary'!D7 -> 966551311461 | E7: 5 | F7: =$E7*1000 -> 5000 | J7: =$E7*1000 -> 5000 | N7: =$E7*1000 -> 5000 | R7: =$E7*1000 -> 5000 | V7: =$E7*1000 -> 5000 | Z7: =$E7*1000 -> 5000 | AD7: =$E7*1000 -> 5000 | AH7: =F7+G7+H7+J7+K7+L7+N7+O7+P7+R7+S7+T7+V7+W7+X7+Z7+AA7+AB7+AD7+AE7+AF7 -> 35000 | AI7: =I7+M7+Q7+U7+Y7+AC7+AG7 -> 0 | AK7: 0 | AL7: =IF(N(F7)>=$E7*1000,"",IF(AND($E7>0,AK7>=$E7*1000),"G",IF(F$2<=TODAY(),"R",""))) | AM7: =AK7-IF(AL7="G",$E7*1000,0)+N(G7) -> 0 | AN7: =IF(N(J7)>=$E7*1000,"",IF(AND($E7>0,AM7>=$E7*1000),"G",IF(J$2<=TODAY(),"R",""))) | AO7: =AM7-IF(AN7="G",$E7*1000,0)+N(K7) -> 0 | AP7: =IF(N(N7)>=$E7*1000,"",IF(AND($E7>0,AO7>=$E7*1000),"G",IF(N$2<=TODAY(),"R",""))) | AQ7: =AO7-IF(AP7="G",$E7*1000,0)+N(O7) -> 0 | AR7: =IF(N(R7)>=$E7*1000,"",IF(AND($E7>0,AQ7>=$E7*1000),"G",IF(R$2<=TODAY(),"R",""))) | AS7: =AQ7-IF(AR7="G",$E7*1000,0)+N(S7) -> 0 | AT7: =IF(N(V7)>=$E7*1000,"",IF(AND($E7>0,AS7>=$E7*1000),"G",IF(V$2<=TODAY(),"R",""))) | AU7: =AS7-IF(AT7="G",$E7*1000,0)+N(W7) -> 0 | AV7: =IF(N(Z7)>=$E7*1000,"",IF(AND($E7>0,AU7>=$E7*1000),"G",IF(Z$2<=TODAY(),"R",""))) | AW7: =AU7-IF(AV7="G",$E7*1000,0)+N(AA7) -> 0 | AX7: =IF(N(AD7)>=$E7*1000,"",IF(AND($E7>0,AW7>=$E7*1000),"G",IF(AD$2<=TODAY(),"R",""))) | AY7: =AW7-IF(AX7="G",$E7*1000,0)+N(AE7) -> 0
B8: =ROW()-3 -> 5 | C8: Nurunnabi Hosen Tanzid | D8: ='Member Wise Deposit Summary'!D8 -> 1838848678 | E8: 2 | F8: =$E8*1000 -> 2000 | J8: =$E8*1000 -> 2000 | N8: =$E8*1000 -> 2000 | R8: =$E8*1000 -> 2000 | V8: =$E8*1000 -> 2000 | Z8: =$E8*1000 -> 2000 | AD8: =$E8*1000 -> 2000 | AH8: =F8+G8+H8+J8+K8+L8+N8+O8+P8+R8+S8+T8+V8+W8+X8+Z8+AA8+AB8+AD8+AE8+AF8 -> 14000 | AI8: =I8+M8+Q8+U8+Y8+AC8+AG8 -> 0 | AK8: 0 | AL8: =IF(N(F8)>=$E8*1000,"",IF(AND($E8>0,AK8>=$E8*1000),"G",IF(F$2<=TODAY(),"R",""))) | AM8: =AK8-IF(AL8="G",$E8*1000,0)+N(G8) -> 0 | AN8: =IF(N(J8)>=$E8*1000,"",IF(AND($E8>0,AM8>=$E8*1000),"G",IF(J$2<=TODAY(),"R",""))) | AO8: =AM8-IF(AN8="G",$E8*1000,0)+N(K8) -> 0 | AP8: =IF(N(N8)>=$E8*1000,"",IF(AND($E8>0,AO8>=$E8*1000),"G",IF(N$2<=TODAY(),"R",""))) | AQ8: =AO8-IF(AP8="G",$E8*1000,0)+N(O8) -> 0 | AR8: =IF(N(R8)>=$E8*1000,"",IF(AND($E8>0,AQ8>=$E8*1000),"G",IF(R$2<=TODAY(),"R",""))) | AS8: =AQ8-IF(AR8="G",$E8*1000,0)+N(S8) -> 0 | AT8: =IF(N(V8)>=$E8*1000,"",IF(AND($E8>0,AS8>=$E8*1000),"G",IF(V$2<=TODAY(),"R",""))) | AU8: =AS8-IF(AT8="G",$E8*1000,0)+N(W8) -> 0 | AV8: =IF(N(Z8)>=$E8*1000,"",IF(AND($E8>0,AU8>=$E8*1000),"G",IF(Z$2<=TODAY(),"R",""))) | AW8: =AU8-IF(AV8="G",$E8*1000,0)+N(AA8) -> 0 | AX8: =IF(N(AD8)>=$E8*1000,"",IF(AND($E8>0,AW8>=$E8*1000),"G",IF(AD$2<=TODAY(),"R",""))) | AY8: =AW8-IF(AX8="G",$E8*1000,0)+N(AE8) -> 0
B9: =ROW()-3 -> 6 | C9: Jashim Uddin | D9: ='Member Wise Deposit Summary'!D9 -> 966538760537 | E9: 2 | F9: =$E9*1000 -> 2000 | J9: =$E9*1000 -> 2000 | N9: =$E9*1000 -> 2000 | R9: =$E9*1000 -> 2000 | S9: 8000 | AH9: =F9+G9+H9+J9+K9+L9+N9+O9+P9+R9+S9+T9+V9+W9+X9+Z9+AA9+AB9+AD9+AE9+AF9 -> 16000 | AI9: =I9+M9+Q9+U9+Y9+AC9+AG9 -> 0 | AK9: 0 | AL9: =IF(N(F9)>=$E9*1000,"",IF(AND($E9>0,AK9>=$E9*1000),"G",IF(F$2<=TODAY(),"R",""))) | AM9: =AK9-IF(AL9="G",$E9*1000,0)+N(G9) -> 0 | AN9: =IF(N(J9)>=$E9*1000,"",IF(AND($E9>0,AM9>=$E9*1000),"G",IF(J$2<=TODAY(),"R",""))) | AO9: =AM9-IF(AN9="G",$E9*1000,0)+N(K9) -> 0 | AP9: =IF(N(N9)>=$E9*1000,"",IF(AND($E9>0,AO9>=$E9*1000),"G",IF(N$2<=TODAY(),"R",""))) | AQ9: =AO9-IF(AP9="G",$E9*1000,0)+N(O9) -> 0 | AR9: =IF(N(R9)>=$E9*1000,"",IF(AND($E9>0,AQ9>=$E9*1000),"G",IF(R$2<=TODAY(),"R",""))) | AS9: =AQ9-IF(AR9="G",$E9*1000,0)+N(S9) -> 8000 | AT9: =IF(N(V9)>=$E9*1000,"",IF(AND($E9>0,AS9>=$E9*1000),"G",IF(V$2<=TODAY(),"R",""))) -> G | AU9: =AS9-IF(AT9="G",$E9*1000,0)+N(W9) -> 6000 | AV9: =IF(N(Z9)>=$E9*1000,"",IF(AND($E9>0,AU9>=$E9*1000),"G",IF(Z$2<=TODAY(),"R",""))) -> G | AW9: =AU9-IF(AV9="G",$E9*1000,0)+N(AA9) -> 4000 | AX9: =IF(N(AD9)>=$E9*1000,"",IF(AND($E9>0,AW9>=$E9*1000),"G",IF(AD$2<=TODAY(),"R",""))) -> G | AY9: =AW9-IF(AX9="G",$E9*1000,0)+N(AE9) -> 2000
B10: =ROW()-3 -> 7 | C10: Shibu Sankar Karmaker | D10: ='Member Wise Deposit Summary'!D10 -> 1885946523 | E10: 2 | F10: =$E10*1000 -> 2000 | J10: =$E10*1000 -> 2000 | N10: =$E10*1000 -> 2000 | R10: =$E10*1000 -> 2000 | V10: =$E10*1000 -> 2000 | Z10: =$E10*1000 -> 2000 | AD10: =$E10*1000 -> 2000 | AH10: =F10+G10+H10+J10+K10+L10+N10+O10+P10+R10+S10+T10+V10+W10+X10+Z10+AA10+AB10+AD10+AE10+AF10 -> 14000 | AI10: =I10+M10+Q10+U10+Y10+AC10+AG10 -> 0 | AK10: 0 | AL10: =IF(N(F10)>=$E10*1000,"",IF(AND($E10>0,AK10>=$E10*1000),"G",IF(F$2<=TODAY(),"R",""))) | AM10: =AK10-IF(AL10="G",$E10*1000,0)+N(G10) -> 0 | AN10: =IF(N(J10)>=$E10*1000,"",IF(AND($E10>0,AM10>=$E10*1000),"G",IF(J$2<=TODAY(),"R",""))) | AO10: =AM10-IF(AN10="G",$E10*1000,0)+N(K10) -> 0 | AP10: =IF(N(N10)>=$E10*1000,"",IF(AND($E10>0,AO10>=$E10*1000),"G",IF(N$2<=TODAY(),"R",""))) | AQ10: =AO10-IF(AP10="G",$E10*1000,0)+N(O10) -> 0 | AR10: =IF(N(R10)>=$E10*1000,"",IF(AND($E10>0,AQ10>=$E10*1000),"G",IF(R$2<=TODAY(),"R",""))) | AS10: =AQ10-IF(AR10="G",$E10*1000,0)+N(S10) -> 0 | AT10: =IF(N(V10)>=$E10*1000,"",IF(AND($E10>0,AS10>=$E10*1000),"G",IF(V$2<=TODAY(),"R",""))) | AU10: =AS10-IF(AT10="G",$E10*1000,0)+N(W10) -> 0 | AV10: =IF(N(Z10)>=$E10*1000,"",IF(AND($E10>0,AU10>=$E10*1000),"G",IF(Z$2<=TODAY(),"R",""))) | AW10: =AU10-IF(AV10="G",$E10*1000,0)+N(AA10) -> 0 | AX10: =IF(N(AD10)>=$E10*1000,"",IF(AND($E10>0,AW10>=$E10*1000),"G",IF(AD$2<=TODAY(),"R",""))) | AY10: =AW10-IF(AX10="G",$E10*1000,0)+N(AE10) -> 0
B11: =ROW()-3 -> 8 | C11: Monsur | D11: ='Member Wise Deposit Summary'!D11 -> 1608632799 | E11: 2 | F11: =$E11*1000 -> 2000 | J11: =$E11*1000 -> 2000 | N11: =$E11*1000 -> 2000 | R11: =$E11*1000 -> 2000 | V11: =$E11*1000 -> 2000 | Z11: =$E11*1000 -> 2000 | AD11: =$E11*1000 -> 2000 | AH11: =F11+G11+H11+J11+K11+L11+N11+O11+P11+R11+S11+T11+V11+W11+X11+Z11+AA11+AB11+AD11+AE11+AF11 -> 14000 | AI11: =I11+M11+Q11+U11+Y11+AC11+AG11 -> 0 | AK11: 0 | AL11: =IF(N(F11)>=$E11*1000,"",IF(AND($E11>0,AK11>=$E11*1000),"G",IF(F$2<=TODAY(),"R",""))) | AM11: =AK11-IF(AL11="G",$E11*1000,0)+N(G11) -> 0 | AN11: =IF(N(J11)>=$E11*1000,"",IF(AND($E11>0,AM11>=$E11*1000),"G",IF(J$2<=TODAY(),"R",""))) | AO11: =AM11-IF(AN11="G",$E11*1000,0)+N(K11) -> 0 | AP11: =IF(N(N11)>=$E11*1000,"",IF(AND($E11>0,AO11>=$E11*1000),"G",IF(N$2<=TODAY(),"R",""))) | AQ11: =AO11-IF(AP11="G",$E11*1000,0)+N(O11) -> 0 | AR11: =IF(N(R11)>=$E11*1000,"",IF(AND($E11>0,AQ11>=$E11*1000),"G",IF(R$2<=TODAY(),"R",""))) | AS11: =AQ11-IF(AR11="G",$E11*1000,0)+N(S11) -> 0 | AT11: =IF(N(V11)>=$E11*1000,"",IF(AND($E11>0,AS11>=$E11*1000),"G",IF(V$2<=TODAY(),"R",""))) | AU11: =AS11-IF(AT11="G",$E11*1000,0)+N(W11) -> 0 | AV11: =IF(N(Z11)>=$E11*1000,"",IF(AND($E11>0,AU11>=$E11*1000),"G",IF(Z$2<=TODAY(),"R",""))) | AW11: =AU11-IF(AV11="G",$E11*1000,0)+N(AA11) -> 0 | AX11: =IF(N(AD11)>=$E11*1000,"",IF(AND($E11>0,AW11>=$E11*1000),"G",IF(AD$2<=TODAY(),"R",""))) | AY11: =AW11-IF(AX11="G",$E11*1000,0)+N(AE11) -> 0
B12: =ROW()-3 -> 9 | C12: Monjur Alam | D12: ='Member Wise Deposit Summary'!D12 -> 1811938007 | E12: 2 | F12: =$E12*1000 -> 2000 | J12: =$E12*1000 -> 2000 | N12: =$E12*1000 -> 2000 | R12: =$E12*1000 -> 2000 | V12: =$E12*1000 -> 2000 | Z12: =$E12*1000 -> 2000 | AD12: =$E12*1000 -> 2000 | AH12: =F12+G12+H12+J12+K12+L12+N12+O12+P12+R12+S12+T12+V12+W12+X12+Z12+AA12+AB12+AD12+AE12+AF12 -> 14000 | AI12: =I12+M12+Q12+U12+Y12+AC12+AG12 -> 0 | AK12: 0 | AL12: =IF(N(F12)>=$E12*1000,"",IF(AND($E12>0,AK12>=$E12*1000),"G",IF(F$2<=TODAY(),"R",""))) | AM12: =AK12-IF(AL12="G",$E12*1000,0)+N(G12) -> 0 | AN12: =IF(N(J12)>=$E12*1000,"",IF(AND($E12>0,AM12>=$E12*1000),"G",IF(J$2<=TODAY(),"R",""))) | AO12: =AM12-IF(AN12="G",$E12*1000,0)+N(K12) -> 0 | AP12: =IF(N(N12)>=$E12*1000,"",IF(AND($E12>0,AO12>=$E12*1000),"G",IF(N$2<=TODAY(),"R",""))) | AQ12: =AO12-IF(AP12="G",$E12*1000,0)+N(O12) -> 0 | AR12: =IF(N(R12)>=$E12*1000,"",IF(AND($E12>0,AQ12>=$E12*1000),"G",IF(R$2<=TODAY(),"R",""))) | AS12: =AQ12-IF(AR12="G",$E12*1000,0)+N(S12) -> 0 | AT12: =IF(N(V12)>=$E12*1000,"",IF(AND($E12>0,AS12>=$E12*1000),"G",IF(V$2<=TODAY(),"R",""))) | AU12: =AS12-IF(AT12="G",$E12*1000,0)+N(W12) -> 0 | AV12: =IF(N(Z12)>=$E12*1000,"",IF(AND($E12>0,AU12>=$E12*1000),"G",IF(Z$2<=TODAY(),"R",""))) | AW12: =AU12-IF(AV12="G",$E12*1000,0)+N(AA12) -> 0 | AX12: =IF(N(AD12)>=$E12*1000,"",IF(AND($E12>0,AW12>=$E12*1000),"G",IF(AD$2<=TODAY(),"R",""))) | AY12: =AW12-IF(AX12="G",$E12*1000,0)+N(AE12) -> 0
B13: =ROW()-3 -> 10 | C13: Rupal Kanti Karmaker | D13: ='Member Wise Deposit Summary'!D13 -> 1812934934 | E13: 1 | F13: =$E13*1000 -> 1000 | J13: =$E13*1000 -> 1000 | N13: =$E13*1000 -> 1000 | R13: =$E13*1000 -> 1000 | V13: =$E13*1000 -> 1000 | Z13: =$E13*1000 -> 1000 | AD13: =$E13*1000 -> 1000 | AH13: =F13+G13+H13+J13+K13+L13+N13+O13+P13+R13+S13+T13+V13+W13+X13+Z13+AA13+AB13+AD13+AE13+AF13 -> 7000 | AI13: =I13+M13+Q13+U13+Y13+AC13+AG13 -> 0 | AK13: 0 | AL13: =IF(N(F13)>=$E13*1000,"",IF(AND($E13>0,AK13>=$E13*1000),"G",IF(F$2<=TODAY(),"R",""))) | AM13: =AK13-IF(AL13="G",$E13*1000,0)+N(G13) -> 0 | AN13: =IF(N(J13)>=$E13*1000,"",IF(AND($E13>0,AM13>=$E13*1000),"G",IF(J$2<=TODAY(),"R",""))) | AO13: =AM13-IF(AN13="G",$E13*1000,0)+N(K13) -> 0 | AP13: =IF(N(N13)>=$E13*1000,"",IF(AND($E13>0,AO13>=$E13*1000),"G",IF(N$2<=TODAY(),"R",""))) | AQ13: =AO13-IF(AP13="G",$E13*1000,0)+N(O13) -> 0 | AR13: =IF(N(R13)>=$E13*1000,"",IF(AND($E13>0,AQ13>=$E13*1000),"G",IF(R$2<=TODAY(),"R",""))) | AS13: =AQ13-IF(AR13="G",$E13*1000,0)+N(S13) -> 0 | AT13: =IF(N(V13)>=$E13*1000,"",IF(AND($E13>0,AS13>=$E13*1000),"G",IF(V$2<=TODAY(),"R",""))) | AU13: =AS13-IF(AT13="G",$E13*1000,0)+N(W13) -> 0 | AV13: =IF(N(Z13)>=$E13*1000,"",IF(AND($E13>0,AU13>=$E13*1000),"G",IF(Z$2<=TODAY(),"R",""))) | AW13: =AU13-IF(AV13="G",$E13*1000,0)+N(AA13) -> 0 | AX13: =IF(N(AD13)>=$E13*1000,"",IF(AND($E13>0,AW13>=$E13*1000),"G",IF(AD$2<=TODAY(),"R",""))) | AY13: =AW13-IF(AX13="G",$E13*1000,0)+N(AE13) -> 0
B14: =ROW()-3 -> 11 | C14: Yousof | D14: ='Member Wise Deposit Summary'!D14 -> 1858217297 | E14: 3 | F14: =$E14*1000 -> 3000 | J14: =$E14*1000 -> 3000 | N14: =$E14*1000 -> 3000 | R14: =$E14*1000 -> 3000 | V14: =$E14*1000 -> 3000 | Z14: =$E14*1000 -> 3000 | AD14: =$E14*1000 -> 3000 | AH14: =F14+G14+H14+J14+K14+L14+N14+O14+P14+R14+S14+T14+V14+W14+X14+Z14+AA14+AB14+AD14+AE14+AF14 -> 21000 | AI14: =I14+M14+Q14+U14+Y14+AC14+AG14 -> 0 | AK14: 0 | AL14: =IF(N(F14)>=$E14*1000,"",IF(AND($E14>0,AK14>=$E14*1000),"G",IF(F$2<=TODAY(),"R",""))) | AM14: =AK14-IF(AL14="G",$E14*1000,0)+N(G14) -> 0 | AN14: =IF(N(J14)>=$E14*1000,"",IF(AND($E14>0,AM14>=$E14*1000),"G",IF(J$2<=TODAY(),"R",""))) | AO14: =AM14-IF(AN14="G",$E14*1000,0)+N(K14) -> 0 | AP14: =IF(N(N14)>=$E14*1000,"",IF(AND($E14>0,AO14>=$E14*1000),"G",IF(N$2<=TODAY(),"R",""))) | AQ14: =AO14-IF(AP14="G",$E14*1000,0)+N(O14) -> 0 | AR14: =IF(N(R14)>=$E14*1000,"",IF(AND($E14>0,AQ14>=$E14*1000),"G",IF(R$2<=TODAY(),"R",""))) | AS14: =AQ14-IF(AR14="G",$E14*1000,0)+N(S14) -> 0 | AT14: =IF(N(V14)>=$E14*1000,"",IF(AND($E14>0,AS14>=$E14*1000),"G",IF(V$2<=TODAY(),"R",""))) | AU14: =AS14-IF(AT14="G",$E14*1000,0)+N(W14) -> 0 | AV14: =IF(N(Z14)>=$E14*1000,"",IF(AND($E14>0,AU14>=$E14*1000),"G",IF(Z$2<=TODAY(),"R",""))) | AW14: =AU14-IF(AV14="G",$E14*1000,0)+N(AA14) -> 0 | AX14: =IF(N(AD14)>=$E14*1000,"",IF(AND($E14>0,AW14>=$E14*1000),"G",IF(AD$2<=TODAY(),"R",""))) | AY14: =AW14-IF(AX14="G",$E14*1000,0)+N(AE14) -> 0
B15: =ROW()-3 -> 12 | C15: Arjun Kanti Karmaker | D15: ='Member Wise Deposit Summary'!D15 -> 01813143128 | E15: 1 | F15: =$E15*1000 -> 1000 | J15: =$E15*1000 -> 1000 | N15: =$E15*1000 -> 1000 | R15: =$E15*1000 -> 1000 | V15: =$E15*1000 -> 1000 | Z15: =$E15*1000 -> 1000 | AD15: =$E15*1000 -> 1000 | AH15: =F15+G15+H15+J15+K15+L15+N15+O15+P15+R15+S15+T15+V15+W15+X15+Z15+AA15+AB15+AD15+AE15+AF15 -> 7000 | AI15: =I15+M15+Q15+U15+Y15+AC15+AG15 -> 0 | AK15: 0 | AL15: =IF(N(F15)>=$E15*1000,"",IF(AND($E15>0,AK15>=$E15*1000),"G",IF(F$2<=TODAY(),"R",""))) | AM15: =AK15-IF(AL15="G",$E15*1000,0)+N(G15) -> 0 | AN15: =IF(N(J15)>=$E15*1000,"",IF(AND($E15>0,AM15>=$E15*1000),"G",IF(J$2<=TODAY(),"R",""))) | AO15: =AM15-IF(AN15="G",$E15*1000,0)+N(K15) -> 0 | AP15: =IF(N(N15)>=$E15*1000,"",IF(AND($E15>0,AO15>=$E15*1000),"G",IF(N$2<=TODAY(),"R",""))) | AQ15: =AO15-IF(AP15="G",$E15*1000,0)+N(O15) -> 0 | AR15: =IF(N(R15)>=$E15*1000,"",IF(AND($E15>0,AQ15>=$E15*1000),"G",IF(R$2<=TODAY(),"R",""))) | AS15: =AQ15-IF(AR15="G",$E15*1000,0)+N(S15) -> 0 | AT15: =IF(N(V15)>=$E15*1000,"",IF(AND($E15>0,AS15>=$E15*1000),"G",IF(V$2<=TODAY(),"R",""))) | AU15: =AS15-IF(AT15="G",$E15*1000,0)+N(W15) -> 0 | AV15: =IF(N(Z15)>=$E15*1000,"",IF(AND($E15>0,AU15>=$E15*1000),"G",IF(Z$2<=TODAY(),"R",""))) | AW15: =AU15-IF(AV15="G",$E15*1000,0)+N(AA15) -> 0 | AX15: =IF(N(AD15)>=$E15*1000,"",IF(AND($E15>0,AW15>=$E15*1000),"G",IF(AD$2<=TODAY(),"R",""))) | AY15: =AW15-IF(AX15="G",$E15*1000,0)+N(AE15) -> 0
B16: =ROW()-3 -> 13 | C16: Abdul Jabber | D16: ='Member Wise Deposit Summary'!D16 -> 1814941801 | E16: 2 | F16: =$E16*1000 -> 2000 | J16: =$E16*1000 -> 2000 | N16: =$E16*1000 -> 2000 | R16: =$E16*1000 -> 2000 | V16: =$E16*1000 -> 2000 | Z16: =$E16*1000 -> 2000 | AD16: =$E16*1000 -> 2000 | AH16: =F16+G16+H16+J16+K16+L16+N16+O16+P16+R16+S16+T16+V16+W16+X16+Z16+AA16+AB16+AD16+AE16+AF16 -> 14000 | AI16: =I16+M16+Q16+U16+Y16+AC16+AG16 -> 0 | AK16: 0 | AL16: =IF(N(F16)>=$E16*1000,"",IF(AND($E16>0,AK16>=$E16*1000),"G",IF(F$2<=TODAY(),"R",""))) | AM16: =AK16-IF(AL16="G",$E16*1000,0)+N(G16) -> 0 | AN16: =IF(N(J16)>=$E16*1000,"",IF(AND($E16>0,AM16>=$E16*1000),"G",IF(J$2<=TODAY(),"R",""))) | AO16: =AM16-IF(AN16="G",$E16*1000,0)+N(K16) -> 0 | AP16: =IF(N(N16)>=$E16*1000,"",IF(AND($E16>0,AO16>=$E16*1000),"G",IF(N$2<=TODAY(),"R",""))) | AQ16: =AO16-IF(AP16="G",$E16*1000,0)+N(O16) -> 0 | AR16: =IF(N(R16)>=$E16*1000,"",IF(AND($E16>0,AQ16>=$E16*1000),"G",IF(R$2<=TODAY(),"R",""))) | AS16: =AQ16-IF(AR16="G",$E16*1000,0)+N(S16) -> 0 | AT16: =IF(N(V16)>=$E16*1000,"",IF(AND($E16>0,AS16>=$E16*1000),"G",IF(V$2<=TODAY(),"R",""))) | AU16: =AS16-IF(AT16="G",$E16*1000,0)+N(W16) -> 0 | AV16: =IF(N(Z16)>=$E16*1000,"",IF(AND($E16>0,AU16>=$E16*1000),"G",IF(Z$2<=TODAY(),"R",""))) | AW16: =AU16-IF(AV16="G",$E16*1000,0)+N(AA16) -> 0 | AX16: =IF(N(AD16)>=$E16*1000,"",IF(AND($E16>0,AW16>=$E16*1000),"G",IF(AD$2<=TODAY(),"R",""))) | AY16: =AW16-IF(AX16="G",$E16*1000,0)+N(AE16) -> 0
B17: =ROW()-3 -> 14 | C17: Mohammad Helal Uddin | D17: ='Member Wise Deposit Summary'!D17 -> 1819700976 | E17: 3 | F17: =$E17*1000 -> 3000 | J17: =$E17*1000 -> 3000 | N17: =$E17*1000 -> 3000 | R17: =$E17*1000 -> 3000 | V17: =$E17*1000 -> 3000 | Z17: =$E17*1000 -> 3000 | AD17: =$E17*1000 -> 3000 | AH17: =F17+G17+H17+J17+K17+L17+N17+O17+P17+R17+S17+T17+V17+W17+X17+Z17+AA17+AB17+AD17+AE17+AF17 -> 21000 | AI17: =I17+M17+Q17+U17+Y17+AC17+AG17 -> 0 | AK17: 0 | AL17: =IF(N(F17)>=$E17*1000,"",IF(AND($E17>0,AK17>=$E17*1000),"G",IF(F$2<=TODAY(),"R",""))) | AM17: =AK17-IF(AL17="G",$E17*1000,0)+N(G17) -> 0 | AN17: =IF(N(J17)>=$E17*1000,"",IF(AND($E17>0,AM17>=$E17*1000),"G",IF(J$2<=TODAY(),"R",""))) | AO17: =AM17-IF(AN17="G",$E17*1000,0)+N(K17) -> 0 | AP17: =IF(N(N17)>=$E17*1000,"",IF(AND($E17>0,AO17>=$E17*1000),"G",IF(N$2<=TODAY(),"R",""))) | AQ17: =AO17-IF(AP17="G",$E17*1000,0)+N(O17) -> 0 | AR17: =IF(N(R17)>=$E17*1000,"",IF(AND($E17>0,AQ17>=$E17*1000),"G",IF(R$2<=TODAY(),"R",""))) | AS17: =AQ17-IF(AR17="G",$E17*1000,0)+N(S17) -> 0 | AT17: =IF(N(V17)>=$E17*1000,"",IF(AND($E17>0,AS17>=$E17*1000),"G",IF(V$2<=TODAY(),"R",""))) | AU17: =AS17-IF(AT17="G",$E17*1000,0)+N(W17) -> 0 | AV17: =IF(N(Z17)>=$E17*1000,"",IF(AND($E17>0,AU17>=$E17*1000),"G",IF(Z$2<=TODAY(),"R",""))) | AW17: =AU17-IF(AV17="G",$E17*1000,0)+N(AA17) -> 0 | AX17: =IF(N(AD17)>=$E17*1000,"",IF(AND($E17>0,AW17>=$E17*1000),"G",IF(AD$2<=TODAY(),"R",""))) | AY17: =AW17-IF(AX17="G",$E17*1000,0)+N(AE17) -> 0
B18: =ROW()-3 -> 15 | C18: Abul Kashem | D18: ='Member Wise Deposit Summary'!D18 -> 1871777022 | E18: 3 | F18: =$E18*1000 -> 3000 | J18: =$E18*1000 -> 3000 | N18: =$E18*1000 -> 3000 | R18: =$E18*1000 -> 3000 | V18: =$E18*1000 -> 3000 | Z18: =$E18*1000 -> 3000 | AD18: =$E18*1000 -> 3000 | AH18: =F18+G18+H18+J18+K18+L18+N18+O18+P18+R18+S18+T18+V18+W18+X18+Z18+AA18+AB18+AD18+AE18+AF18 -> 21000 | AI18: =I18+M18+Q18+U18+Y18+AC18+AG18 -> 0 | AK18: 0 | AL18: =IF(N(F18)>=$E18*1000,"",IF(AND($E18>0,AK18>=$E18*1000),"G",IF(F$2<=TODAY(),"R",""))) | AM18: =AK18-IF(AL18="G",$E18*1000,0)+N(G18) -> 0 | AN18: =IF(N(J18)>=$E18*1000,"",IF(AND($E18>0,AM18>=$E18*1000),"G",IF(J$2<=TODAY(),"R",""))) | AO18: =AM18-IF(AN18="G",$E18*1000,0)+N(K18) -> 0 | AP18: =IF(N(N18)>=$E18*1000,"",IF(AND($E18>0,AO18>=$E18*1000),"G",IF(N$2<=TODAY(),"R",""))) | AQ18: =AO18-IF(AP18="G",$E18*1000,0)+N(O18) -> 0 | AR18: =IF(N(R18)>=$E18*1000,"",IF(AND($E18>0,AQ18>=$E18*1000),"G",IF(R$2<=TODAY(),"R",""))) | AS18: =AQ18-IF(AR18="G",$E18*1000,0)+N(S18) -> 0 | AT18: =IF(N(V18)>=$E18*1000,"",IF(AND($E18>0,AS18>=$E18*1000),"G",IF(V$2<=TODAY(),"R",""))) | AU18: =AS18-IF(AT18="G",$E18*1000,0)+N(W18) -> 0 | AV18: =IF(N(Z18)>=$E18*1000,"",IF(AND($E18>0,AU18>=$E18*1000),"G",IF(Z$2<=TODAY(),"R",""))) | AW18: =AU18-IF(AV18="G",$E18*1000,0)+N(AA18) -> 0 | AX18: =IF(N(AD18)>=$E18*1000,"",IF(AND($E18>0,AW18>=$E18*1000),"G",IF(AD$2<=TODAY(),"R",""))) | AY18: =AW18-IF(AX18="G",$E18*1000,0)+N(AE18) -> 0
B19: =ROW()-3 -> 16 | C19: Uzzal Karmaker | D19: ='Member Wise Deposit Summary'!D19 -> 1820016020 | E19: 2 | F19: =$E19*1000 -> 2000 | J19: =$E19*1000 -> 2000 | N19: =$E19*1000 -> 2000 | V19: =$E19*1000 -> 2000 | X19: 2000 | Y19: 100 | Z19: =$E19*1000 -> 2000 | AD19: =$E19*1000 -> 2000 | AE19: 2000 | AH19: =F19+G19+H19+J19+K19+L19+N19+O19+P19+R19+S19+T19+V19+W19+X19+Z19+AA19+AB19+AD19+AE19+AF19 -> 16000 | AI19: =I19+M19+Q19+U19+Y19+AC19+AG19 -> 100 | AK19: 0 | AL19: =IF(N(F19)>=$E19*1000,"",IF(AND($E19>0,AK19>=$E19*1000),"G",IF(F$2<=TODAY(),"R",""))) | AM19: =AK19-IF(AL19="G",$E19*1000,0)+N(G19) -> 0 | AN19: =IF(N(J19)>=$E19*1000,"",IF(AND($E19>0,AM19>=$E19*1000),"G",IF(J$2<=TODAY(),"R",""))) | AO19: =AM19-IF(AN19="G",$E19*1000,0)+N(K19) -> 0 | AP19: =IF(N(N19)>=$E19*1000,"",IF(AND($E19>0,AO19>=$E19*1000),"G",IF(N$2<=TODAY(),"R",""))) | AQ19: =AO19-IF(AP19="G",$E19*1000,0)+N(O19) -> 0 | AR19: =IF(N(R19)>=$E19*1000,"",IF(AND($E19>0,AQ19>=$E19*1000),"G",IF(R$2<=TODAY(),"R",""))) -> R | AS19: =AQ19-IF(AR19="G",$E19*1000,0)+N(S19) -> 0 | AT19: =IF(N(V19)>=$E19*1000,"",IF(AND($E19>0,AS19>=$E19*1000),"G",IF(V$2<=TODAY(),"R",""))) | AU19: =AS19-IF(AT19="G",$E19*1000,0)+N(W19) -> 0 | AV19: =IF(N(Z19)>=$E19*1000,"",IF(AND($E19>0,AU19>=$E19*1000),"G",IF(Z$2<=TODAY(),"R",""))) | AW19: =AU19-IF(AV19="G",$E19*1000,0)+N(AA19) -> 0 | AX19: =IF(N(AD19)>=$E19*1000,"",IF(AND($E19>0,AW19>=$E19*1000),"G",IF(AD$2<=TODAY(),"R",""))) | AY19: =AW19-IF(AX19="G",$E19*1000,0)+N(AE19) -> 2000
B20: =ROW()-3 -> 17 | C20: Jahedul Islam | D20: ='Member Wise Deposit Summary'!D20 -> 971562765681 | E20: 2 | F20: =$E20*1000 -> 2000 | J20: =$E20*1000 -> 2000 | N20: =$E20*1000 -> 2000 | R20: =$E20*1000 -> 2000 | V20: =$E20*1000 -> 2000 | Z20: =$E20*1000 -> 2000 | AD20: =$E20*1000 -> 2000 | AH20: =F20+G20+H20+J20+K20+L20+N20+O20+P20+R20+S20+T20+V20+W20+X20+Z20+AA20+AB20+AD20+AE20+AF20 -> 14000 | AI20: =I20+M20+Q20+U20+Y20+AC20+AG20 -> 0 | AK20: 0 | AL20: =IF(N(F20)>=$E20*1000,"",IF(AND($E20>0,AK20>=$E20*1000),"G",IF(F$2<=TODAY(),"R",""))) | AM20: =AK20-IF(AL20="G",$E20*1000,0)+N(G20) -> 0 | AN20: =IF(N(J20)>=$E20*1000,"",IF(AND($E20>0,AM20>=$E20*1000),"G",IF(J$2<=TODAY(),"R",""))) | AO20: =AM20-IF(AN20="G",$E20*1000,0)+N(K20) -> 0 | AP20: =IF(N(N20)>=$E20*1000,"",IF(AND($E20>0,AO20>=$E20*1000),"G",IF(N$2<=TODAY(),"R",""))) | AQ20: =AO20-IF(AP20="G",$E20*1000,0)+N(O20) -> 0 | AR20: =IF(N(R20)>=$E20*1000,"",IF(AND($E20>0,AQ20>=$E20*1000),"G",IF(R$2<=TODAY(),"R",""))) | AS20: =AQ20-IF(AR20="G",$E20*1000,0)+N(S20) -> 0 | AT20: =IF(N(V20)>=$E20*1000,"",IF(AND($E20>0,AS20>=$E20*1000),"G",IF(V$2<=TODAY(),"R",""))) | AU20: =AS20-IF(AT20="G",$E20*1000,0)+N(W20) -> 0 | AV20: =IF(N(Z20)>=$E20*1000,"",IF(AND($E20>0,AU20>=$E20*1000),"G",IF(Z$2<=TODAY(),"R",""))) | AW20: =AU20-IF(AV20="G",$E20*1000,0)+N(AA20) -> 0 | AX20: =IF(N(AD20)>=$E20*1000,"",IF(AND($E20>0,AW20>=$E20*1000),"G",IF(AD$2<=TODAY(),"R",""))) | AY20: =AW20-IF(AX20="G",$E20*1000,0)+N(AE20) -> 0
B21: =ROW()-3 -> 18 | C21: Mohammad Alamgir | D21: ='Member Wise Deposit Summary'!D21 -> 1822092650 | E21: 2 | F21: =$E21*1000 -> 2000 | J21: =$E21*1000 -> 2000 | N21: =$E21*1000 -> 2000 | R21: =$E21*1000 -> 2000 | V21: =$E21*1000 -> 2000 | Z21: =$E21*1000 -> 2000 | AD21: =$E21*1000 -> 2000 | AH21: =F21+G21+H21+J21+K21+L21+N21+O21+P21+R21+S21+T21+V21+W21+X21+Z21+AA21+AB21+AD21+AE21+AF21 -> 14000 | AI21: =I21+M21+Q21+U21+Y21+AC21+AG21 -> 0 | AK21: 0 | AL21: =IF(N(F21)>=$E21*1000,"",IF(AND($E21>0,AK21>=$E21*1000),"G",IF(F$2<=TODAY(),"R",""))) | AM21: =AK21-IF(AL21="G",$E21*1000,0)+N(G21) -> 0 | AN21: =IF(N(J21)>=$E21*1000,"",IF(AND($E21>0,AM21>=$E21*1000),"G",IF(J$2<=TODAY(),"R",""))) | AO21: =AM21-IF(AN21="G",$E21*1000,0)+N(K21) -> 0 | AP21: =IF(N(N21)>=$E21*1000,"",IF(AND($E21>0,AO21>=$E21*1000),"G",IF(N$2<=TODAY(),"R",""))) | AQ21: =AO21-IF(AP21="G",$E21*1000,0)+N(O21) -> 0 | AR21: =IF(N(R21)>=$E21*1000,"",IF(AND($E21>0,AQ21>=$E21*1000),"G",IF(R$2<=TODAY(),"R",""))) | AS21: =AQ21-IF(AR21="G",$E21*1000,0)+N(S21) -> 0 | AT21: =IF(N(V21)>=$E21*1000,"",IF(AND($E21>0,AS21>=$E21*1000),"G",IF(V$2<=TODAY(),"R",""))) | AU21: =AS21-IF(AT21="G",$E21*1000,0)+N(W21) -> 0 | AV21: =IF(N(Z21)>=$E21*1000,"",IF(AND($E21>0,AU21>=$E21*1000),"G",IF(Z$2<=TODAY(),"R",""))) | AW21: =AU21-IF(AV21="G",$E21*1000,0)+N(AA21) -> 0 | AX21: =IF(N(AD21)>=$E21*1000,"",IF(AND($E21>0,AW21>=$E21*1000),"G",IF(AD$2<=TODAY(),"R",""))) | AY21: =AW21-IF(AX21="G",$E21*1000,0)+N(AE21) -> 0
B22: =ROW()-3 -> 19 | C22: Kafil Uddin | D22: ='Member Wise Deposit Summary'!D22 -> 966534770192 | E22: 1 | F22: =$E22*1000 -> 1000 | J22: =$E22*1000 -> 1000 | N22: =$E22*1000 -> 1000 | R22: =$E22*1000 -> 1000 | V22: =$E22*1000 -> 1000 | Z22: =$E22*1000 -> 1000 | AD22: =$E22*1000 -> 1000 | AH22: =F22+G22+H22+J22+K22+L22+N22+O22+P22+R22+S22+T22+V22+W22+X22+Z22+AA22+AB22+AD22+AE22+AF22 -> 7000 | AI22: =I22+M22+Q22+U22+Y22+AC22+AG22 -> 0 | AK22: 0 | AL22: =IF(N(F22)>=$E22*1000,"",IF(AND($E22>0,AK22>=$E22*1000),"G",IF(F$2<=TODAY(),"R",""))) | AM22: =AK22-IF(AL22="G",$E22*1000,0)+N(G22) -> 0 | AN22: =IF(N(J22)>=$E22*1000,"",IF(AND($E22>0,AM22>=$E22*1000),"G",IF(J$2<=TODAY(),"R",""))) | AO22: =AM22-IF(AN22="G",$E22*1000,0)+N(K22) -> 0 | AP22: =IF(N(N22)>=$E22*1000,"",IF(AND($E22>0,AO22>=$E22*1000),"G",IF(N$2<=TODAY(),"R",""))) | AQ22: =AO22-IF(AP22="G",$E22*1000,0)+N(O22) -> 0 | AR22: =IF(N(R22)>=$E22*1000,"",IF(AND($E22>0,AQ22>=$E22*1000),"G",IF(R$2<=TODAY(),"R",""))) | AS22: =AQ22-IF(AR22="G",$E22*1000,0)+N(S22) -> 0 | AT22: =IF(N(V22)>=$E22*1000,"",IF(AND($E22>0,AS22>=$E22*1000),"G",IF(V$2<=TODAY(),"R",""))) | AU22: =AS22-IF(AT22="G",$E22*1000,0)+N(W22) -> 0 | AV22: =IF(N(Z22)>=$E22*1000,"",IF(AND($E22>0,AU22>=$E22*1000),"G",IF(Z$2<=TODAY(),"R",""))) | AW22: =AU22-IF(AV22="G",$E22*1000,0)+N(AA22) -> 0 | AX22: =IF(N(AD22)>=$E22*1000,"",IF(AND($E22>0,AW22>=$E22*1000),"G",IF(AD$2<=TODAY(),"R",""))) | AY22: =AW22-IF(AX22="G",$E22*1000,0)+N(AE22) -> 0
B23: =ROW()-3 -> 20 | C23: Mohammudul Hoque | D23: ='Member Wise Deposit Summary'!D23 -> 1816821801 | E23: 2 | F23: =$E23*1000 -> 2000 | J23: =$E23*1000 -> 2000 | N23: =$E23*1000 -> 2000 | R23: =$E23*1000 -> 2000 | V23: =$E23*1000 -> 2000 | Z23: =$E23*1000 -> 2000 | AD23: =$E23*1000 -> 2000 | AH23: =F23+G23+H23+J23+K23+L23+N23+O23+P23+R23+S23+T23+V23+W23+X23+Z23+AA23+AB23+AD23+AE23+AF23 -> 14000 | AI23: =I23+M23+Q23+U23+Y23+AC23+AG23 -> 0 | AK23: 0 | AL23: =IF(N(F23)>=$E23*1000,"",IF(AND($E23>0,AK23>=$E23*1000),"G",IF(F$2<=TODAY(),"R",""))) | AM23: =AK23-IF(AL23="G",$E23*1000,0)+N(G23) -> 0 | AN23: =IF(N(J23)>=$E23*1000,"",IF(AND($E23>0,AM23>=$E23*1000),"G",IF(J$2<=TODAY(),"R",""))) | AO23: =AM23-IF(AN23="G",$E23*1000,0)+N(K23) -> 0 | AP23: =IF(N(N23)>=$E23*1000,"",IF(AND($E23>0,AO23>=$E23*1000),"G",IF(N$2<=TODAY(),"R",""))) | AQ23: =AO23-IF(AP23="G",$E23*1000,0)+N(O23) -> 0 | AR23: =IF(N(R23)>=$E23*1000,"",IF(AND($E23>0,AQ23>=$E23*1000),"G",IF(R$2<=TODAY(),"R",""))) | AS23: =AQ23-IF(AR23="G",$E23*1000,0)+N(S23) -> 0 | AT23: =IF(N(V23)>=$E23*1000,"",IF(AND($E23>0,AS23>=$E23*1000),"G",IF(V$2<=TODAY(),"R",""))) | AU23: =AS23-IF(AT23="G",$E23*1000,0)+N(W23) -> 0 | AV23: =IF(N(Z23)>=$E23*1000,"",IF(AND($E23>0,AU23>=$E23*1000),"G",IF(Z$2<=TODAY(),"R",""))) | AW23: =AU23-IF(AV23="G",$E23*1000,0)+N(AA23) -> 0 | AX23: =IF(N(AD23)>=$E23*1000,"",IF(AND($E23>0,AW23>=$E23*1000),"G",IF(AD$2<=TODAY(),"R",""))) | AY23: =AW23-IF(AX23="G",$E23*1000,0)+N(AE23) -> 0
B24: =ROW()-3 -> 21 | C24: Nurul Amin | D24: ='Member Wise Deposit Summary'!D24 -> 1820989105 | E24: 1 | F24: =$E24*1000 -> 1000 | J24: =$E24*1000 -> 1000 | N24: =$E24*1000 -> 1000 | R24: =$E24*1000 -> 1000 | V24: =$E24*1000 -> 1000 | Z24: =$E24*1000 -> 1000 | AD24: =$E24*1000 -> 1000 | AH24: =F24+G24+H24+J24+K24+L24+N24+O24+P24+R24+S24+T24+V24+W24+X24+Z24+AA24+AB24+AD24+AE24+AF24 -> 7000 | AI24: =I24+M24+Q24+U24+Y24+AC24+AG24 -> 0 | AK24: 0 | AL24: =IF(N(F24)>=$E24*1000,"",IF(AND($E24>0,AK24>=$E24*1000),"G",IF(F$2<=TODAY(),"R",""))) | AM24: =AK24-IF(AL24="G",$E24*1000,0)+N(G24) -> 0 | AN24: =IF(N(J24)>=$E24*1000,"",IF(AND($E24>0,AM24>=$E24*1000),"G",IF(J$2<=TODAY(),"R",""))) | AO24: =AM24-IF(AN24="G",$E24*1000,0)+N(K24) -> 0 | AP24: =IF(N(N24)>=$E24*1000,"",IF(AND($E24>0,AO24>=$E24*1000),"G",IF(N$2<=TODAY(),"R",""))) | AQ24: =AO24-IF(AP24="G",$E24*1000,0)+N(O24) -> 0 | AR24: =IF(N(R24)>=$E24*1000,"",IF(AND($E24>0,AQ24>=$E24*1000),"G",IF(R$2<=TODAY(),"R",""))) | AS24: =AQ24-IF(AR24="G",$E24*1000,0)+N(S24) -> 0 | AT24: =IF(N(V24)>=$E24*1000,"",IF(AND($E24>0,AS24>=$E24*1000),"G",IF(V$2<=TODAY(),"R",""))) | AU24: =AS24-IF(AT24="G",$E24*1000,0)+N(W24) -> 0 | AV24: =IF(N(Z24)>=$E24*1000,"",IF(AND($E24>0,AU24>=$E24*1000),"G",IF(Z$2<=TODAY(),"R",""))) | AW24: =AU24-IF(AV24="G",$E24*1000,0)+N(AA24) -> 0 | AX24: =IF(N(AD24)>=$E24*1000,"",IF(AND($E24>0,AW24>=$E24*1000),"G",IF(AD$2<=TODAY(),"R",""))) | AY24: =AW24-IF(AX24="G",$E24*1000,0)+N(AE24) -> 0
B25: =ROW()-3 -> 22 | C25: Abul Kashem | D25: ='Member Wise Deposit Summary'!D25 -> 1873812598 | E25: 1 | F25: =$E25*1000 -> 1000 | J25: =$E25*1000 -> 1000 | N25: =$E25*1000 -> 1000 | R25: =$E25*1000 -> 1000 | V25: =$E25*1000 -> 1000 | Z25: =$E25*1000 -> 1000 | AD25: =$E25*1000 -> 1000 | AH25: =F25+G25+H25+J25+K25+L25+N25+O25+P25+R25+S25+T25+V25+W25+X25+Z25+AA25+AB25+AD25+AE25+AF25 -> 7000 | AI25: =I25+M25+Q25+U25+Y25+AC25+AG25 -> 0 | AK25: 0 | AL25: =IF(N(F25)>=$E25*1000,"",IF(AND($E25>0,AK25>=$E25*1000),"G",IF(F$2<=TODAY(),"R",""))) | AM25: =AK25-IF(AL25="G",$E25*1000,0)+N(G25) -> 0 | AN25: =IF(N(J25)>=$E25*1000,"",IF(AND($E25>0,AM25>=$E25*1000),"G",IF(J$2<=TODAY(),"R",""))) | AO25: =AM25-IF(AN25="G",$E25*1000,0)+N(K25) -> 0 | AP25: =IF(N(N25)>=$E25*1000,"",IF(AND($E25>0,AO25>=$E25*1000),"G",IF(N$2<=TODAY(),"R",""))) | AQ25: =AO25-IF(AP25="G",$E25*1000,0)+N(O25) -> 0 | AR25: =IF(N(R25)>=$E25*1000,"",IF(AND($E25>0,AQ25>=$E25*1000),"G",IF(R$2<=TODAY(),"R",""))) | AS25: =AQ25-IF(AR25="G",$E25*1000,0)+N(S25) -> 0 | AT25: =IF(N(V25)>=$E25*1000,"",IF(AND($E25>0,AS25>=$E25*1000),"G",IF(V$2<=TODAY(),"R",""))) | AU25: =AS25-IF(AT25="G",$E25*1000,0)+N(W25) -> 0 | AV25: =IF(N(Z25)>=$E25*1000,"",IF(AND($E25>0,AU25>=$E25*1000),"G",IF(Z$2<=TODAY(),"R",""))) | AW25: =AU25-IF(AV25="G",$E25*1000,0)+N(AA25) -> 0 | AX25: =IF(N(AD25)>=$E25*1000,"",IF(AND($E25>0,AW25>=$E25*1000),"G",IF(AD$2<=TODAY(),"R",""))) | AY25: =AW25-IF(AX25="G",$E25*1000,0)+N(AE25) -> 0
B26: =ROW()-3 -> 23 | C26: Belal Uddin | D26: ='Member Wise Deposit Summary'!D26 -> 1815073916 | E26: 1 | F26: =$E26*1000 -> 1000 | J26: =$E26*1000 -> 1000 | N26: =$E26*1000 -> 1000 | R26: =$E26*1000 -> 1000 | AB26: 1000 | AC26: 50 | AD26: =$E26*1000 -> 1000 | AF26: 1000 | AG26: 50 | AH26: =F26+G26+H26+J26+K26+L26+N26+O26+P26+R26+S26+T26+V26+W26+X26+Z26+AA26+AB26+AD26+AE26+AF26 -> 7000 | AI26: =I26+M26+Q26+U26+Y26+AC26+AG26 -> 100 | AK26: 0 | AL26: =IF(N(F26)>=$E26*1000,"",IF(AND($E26>0,AK26>=$E26*1000),"G",IF(F$2<=TODAY(),"R",""))) | AM26: =AK26-IF(AL26="G",$E26*1000,0)+N(G26) -> 0 | AN26: =IF(N(J26)>=$E26*1000,"",IF(AND($E26>0,AM26>=$E26*1000),"G",IF(J$2<=TODAY(),"R",""))) | AO26: =AM26-IF(AN26="G",$E26*1000,0)+N(K26) -> 0 | AP26: =IF(N(N26)>=$E26*1000,"",IF(AND($E26>0,AO26>=$E26*1000),"G",IF(N$2<=TODAY(),"R",""))) | AQ26: =AO26-IF(AP26="G",$E26*1000,0)+N(O26) -> 0 | AR26: =IF(N(R26)>=$E26*1000,"",IF(AND($E26>0,AQ26>=$E26*1000),"G",IF(R$2<=TODAY(),"R",""))) | AS26: =AQ26-IF(AR26="G",$E26*1000,0)+N(S26) -> 0 | AT26: =IF(N(V26)>=$E26*1000,"",IF(AND($E26>0,AS26>=$E26*1000),"G",IF(V$2<=TODAY(),"R",""))) -> R | AU26: =AS26-IF(AT26="G",$E26*1000,0)+N(W26) -> 0 | AV26: =IF(N(Z26)>=$E26*1000,"",IF(AND($E26>0,AU26>=$E26*1000),"G",IF(Z$2<=TODAY(),"R",""))) -> R | AW26: =AU26-IF(AV26="G",$E26*1000,0)+N(AA26) -> 0 | AX26: =IF(N(AD26)>=$E26*1000,"",IF(AND($E26>0,AW26>=$E26*1000),"G",IF(AD$2<=TODAY(),"R",""))) | AY26: =AW26-IF(AX26="G",$E26*1000,0)+N(AE26) -> 0
B27: =ROW()-3 -> 24 | C27: Md. Helal Uddin | D27: ='Member Wise Deposit Summary'!D27 -> 1860493163 | E27: 1 | F27: =$E27*1000 -> 1000 | J27: =$E27*1000 -> 1000 | N27: =$E27*1000 -> 1000 | R27: =$E27*1000 -> 1000 | V27: =$E27*1000 -> 1000 | Z27: =$E27*1000 -> 1000 | AH27: =F27+G27+H27+J27+K27+L27+N27+O27+P27+R27+S27+T27+V27+W27+X27+Z27+AA27+AB27+AD27+AE27+AF27 -> 6000 | AI27: =I27+M27+Q27+U27+Y27+AC27+AG27 -> 0 | AK27: 0 | AL27: =IF(N(F27)>=$E27*1000,"",IF(AND($E27>0,AK27>=$E27*1000),"G",IF(F$2<=TODAY(),"R",""))) | AM27: =AK27-IF(AL27="G",$E27*1000,0)+N(G27) -> 0 | AN27: =IF(N(J27)>=$E27*1000,"",IF(AND($E27>0,AM27>=$E27*1000),"G",IF(J$2<=TODAY(),"R",""))) | AO27: =AM27-IF(AN27="G",$E27*1000,0)+N(K27) -> 0 | AP27: =IF(N(N27)>=$E27*1000,"",IF(AND($E27>0,AO27>=$E27*1000),"G",IF(N$2<=TODAY(),"R",""))) | AQ27: =AO27-IF(AP27="G",$E27*1000,0)+N(O27) -> 0 | AR27: =IF(N(R27)>=$E27*1000,"",IF(AND($E27>0,AQ27>=$E27*1000),"G",IF(R$2<=TODAY(),"R",""))) | AS27: =AQ27-IF(AR27="G",$E27*1000,0)+N(S27) -> 0 | AT27: =IF(N(V27)>=$E27*1000,"",IF(AND($E27>0,AS27>=$E27*1000),"G",IF(V$2<=TODAY(),"R",""))) | AU27: =AS27-IF(AT27="G",$E27*1000,0)+N(W27) -> 0 | AV27: =IF(N(Z27)>=$E27*1000,"",IF(AND($E27>0,AU27>=$E27*1000),"G",IF(Z$2<=TODAY(),"R",""))) | AW27: =AU27-IF(AV27="G",$E27*1000,0)+N(AA27) -> 0 | AX27: =IF(N(AD27)>=$E27*1000,"",IF(AND($E27>0,AW27>=$E27*1000),"G",IF(AD$2<=TODAY(),"R",""))) -> R | AY27: =AW27-IF(AX27="G",$E27*1000,0)+N(AE27) -> 0
B28: =ROW()-3 -> 25 | C28: Md.Hamid | D28: ='Member Wise Deposit Summary'!D28 -> 1870876309 | E28: 1 | F28: =$E28*1000 -> 1000 | J28: =$E28*1000 -> 1000 | N28: =$E28*1000 -> 1000 | R28: =$E28*1000 -> 1000 | V28: =$E28*1000 -> 1000 | Z28: =$E28*1000 -> 1000 | AD28: =$E28*1000 -> 1000 | AH28: =F28+G28+H28+J28+K28+L28+N28+O28+P28+R28+S28+T28+V28+W28+X28+Z28+AA28+AB28+AD28+AE28+AF28 -> 7000 | AI28: =I28+M28+Q28+U28+Y28+AC28+AG28 -> 0 | AK28: 0 | AL28: =IF(N(F28)>=$E28*1000,"",IF(AND($E28>0,AK28>=$E28*1000),"G",IF(F$2<=TODAY(),"R",""))) | AM28: =AK28-IF(AL28="G",$E28*1000,0)+N(G28) -> 0 | AN28: =IF(N(J28)>=$E28*1000,"",IF(AND($E28>0,AM28>=$E28*1000),"G",IF(J$2<=TODAY(),"R",""))) | AO28: =AM28-IF(AN28="G",$E28*1000,0)+N(K28) -> 0 | AP28: =IF(N(N28)>=$E28*1000,"",IF(AND($E28>0,AO28>=$E28*1000),"G",IF(N$2<=TODAY(),"R",""))) | AQ28: =AO28-IF(AP28="G",$E28*1000,0)+N(O28) -> 0 | AR28: =IF(N(R28)>=$E28*1000,"",IF(AND($E28>0,AQ28>=$E28*1000),"G",IF(R$2<=TODAY(),"R",""))) | AS28: =AQ28-IF(AR28="G",$E28*1000,0)+N(S28) -> 0 | AT28: =IF(N(V28)>=$E28*1000,"",IF(AND($E28>0,AS28>=$E28*1000),"G",IF(V$2<=TODAY(),"R",""))) | AU28: =AS28-IF(AT28="G",$E28*1000,0)+N(W28) -> 0 | AV28: =IF(N(Z28)>=$E28*1000,"",IF(AND($E28>0,AU28>=$E28*1000),"G",IF(Z$2<=TODAY(),"R",""))) | AW28: =AU28-IF(AV28="G",$E28*1000,0)+N(AA28) -> 0 | AX28: =IF(N(AD28)>=$E28*1000,"",IF(AND($E28>0,AW28>=$E28*1000),"G",IF(AD$2<=TODAY(),"R",""))) | AY28: =AW28-IF(AX28="G",$E28*1000,0)+N(AE28) -> 0
B29: =ROW()-3 -> 26 | C29: Samsul Alam | D29: ='Member Wise Deposit Summary'!D29 -> 1865394799 | E29: 3 | F29: =$E29*1000 -> 3000 | J29: =$E29*1000 -> 3000 | N29: =$E29*1000 -> 3000 | R29: =$E29*1000 -> 3000 | V29: =$E29*1000 -> 3000 | Z29: =$E29*1000 -> 3000 | AD29: =$E29*1000 -> 3000 | AH29: =F29+G29+H29+J29+K29+L29+N29+O29+P29+R29+S29+T29+V29+W29+X29+Z29+AA29+AB29+AD29+AE29+AF29 -> 21000 | AI29: =I29+M29+Q29+U29+Y29+AC29+AG29 -> 0 | AK29: 0 | AL29: =IF(N(F29)>=$E29*1000,"",IF(AND($E29>0,AK29>=$E29*1000),"G",IF(F$2<=TODAY(),"R",""))) | AM29: =AK29-IF(AL29="G",$E29*1000,0)+N(G29) -> 0 | AN29: =IF(N(J29)>=$E29*1000,"",IF(AND($E29>0,AM29>=$E29*1000),"G",IF(J$2<=TODAY(),"R",""))) | AO29: =AM29-IF(AN29="G",$E29*1000,0)+N(K29) -> 0 | AP29: =IF(N(N29)>=$E29*1000,"",IF(AND($E29>0,AO29>=$E29*1000),"G",IF(N$2<=TODAY(),"R",""))) | AQ29: =AO29-IF(AP29="G",$E29*1000,0)+N(O29) -> 0 | AR29: =IF(N(R29)>=$E29*1000,"",IF(AND($E29>0,AQ29>=$E29*1000),"G",IF(R$2<=TODAY(),"R",""))) | AS29: =AQ29-IF(AR29="G",$E29*1000,0)+N(S29) -> 0 | AT29: =IF(N(V29)>=$E29*1000,"",IF(AND($E29>0,AS29>=$E29*1000),"G",IF(V$2<=TODAY(),"R",""))) | AU29: =AS29-IF(AT29="G",$E29*1000,0)+N(W29) -> 0 | AV29: =IF(N(Z29)>=$E29*1000,"",IF(AND($E29>0,AU29>=$E29*1000),"G",IF(Z$2<=TODAY(),"R",""))) | AW29: =AU29-IF(AV29="G",$E29*1000,0)+N(AA29) -> 0 | AX29: =IF(N(AD29)>=$E29*1000,"",IF(AND($E29>0,AW29>=$E29*1000),"G",IF(AD$2<=TODAY(),"R",""))) | AY29: =AW29-IF(AX29="G",$E29*1000,0)+N(AE29) -> 0
B30: =ROW()-3 -> 27 | C30: Riad Hossen | D30: ='Member Wise Deposit Summary'!D30 -> 1882217274 | E30: 1 | F30: =$E30*1000 -> 1000 | J30: =$E30*1000 -> 1000 | N30: =$E30*1000 -> 1000 | R30: =$E30*1000 -> 1000 | U30: 50 | V30: =$E30*1000 -> 1000 | Z30: =$E30*1000 -> 1000 | AD30: =$E30*1000 -> 1000 | AH30: =F30+G30+H30+J30+K30+L30+N30+O30+P30+R30+S30+T30+V30+W30+X30+Z30+AA30+AB30+AD30+AE30+AF30 -> 7000 | AI30: =I30+M30+Q30+U30+Y30+AC30+AG30 -> 50 | AK30: 0 | AL30: =IF(N(F30)>=$E30*1000,"",IF(AND($E30>0,AK30>=$E30*1000),"G",IF(F$2<=TODAY(),"R",""))) | AM30: =AK30-IF(AL30="G",$E30*1000,0)+N(G30) -> 0 | AN30: =IF(N(J30)>=$E30*1000,"",IF(AND($E30>0,AM30>=$E30*1000),"G",IF(J$2<=TODAY(),"R",""))) | AO30: =AM30-IF(AN30="G",$E30*1000,0)+N(K30) -> 0 | AP30: =IF(N(N30)>=$E30*1000,"",IF(AND($E30>0,AO30>=$E30*1000),"G",IF(N$2<=TODAY(),"R",""))) | AQ30: =AO30-IF(AP30="G",$E30*1000,0)+N(O30) -> 0 | AR30: =IF(N(R30)>=$E30*1000,"",IF(AND($E30>0,AQ30>=$E30*1000),"G",IF(R$2<=TODAY(),"R",""))) | AS30: =AQ30-IF(AR30="G",$E30*1000,0)+N(S30) -> 0 | AT30: =IF(N(V30)>=$E30*1000,"",IF(AND($E30>0,AS30>=$E30*1000),"G",IF(V$2<=TODAY(),"R",""))) | AU30: =AS30-IF(AT30="G",$E30*1000,0)+N(W30) -> 0 | AV30: =IF(N(Z30)>=$E30*1000,"",IF(AND($E30>0,AU30>=$E30*1000),"G",IF(Z$2<=TODAY(),"R",""))) | AW30: =AU30-IF(AV30="G",$E30*1000,0)+N(AA30) -> 0 | AX30: =IF(N(AD30)>=$E30*1000,"",IF(AND($E30>0,AW30>=$E30*1000),"G",IF(AD$2<=TODAY(),"R",""))) | AY30: =AW30-IF(AX30="G",$E30*1000,0)+N(AE30) -> 0
B31: =ROW()-3 -> 28 | C31: Md. Sohel Islam | D31: ='Member Wise Deposit Summary'!D31 -> 00971527120848 | E31: 1 | F31: =$E31*1000 -> 1000 | J31: =$E31*1000 -> 1000 | N31: =$E31*1000 -> 1000 | R31: =$E31*1000 -> 1000 | V31: =$E31*1000 -> 1000 | Z31: =$E31*1000 -> 1000 | AD31: =$E31*1000 -> 1000 | AH31: =F31+G31+H31+J31+K31+L31+N31+O31+P31+R31+S31+T31+V31+W31+X31+Z31+AA31+AB31+AD31+AE31+AF31 -> 7000 | AI31: =I31+M31+Q31+U31+Y31+AC31+AG31 -> 0 | AK31: 0 | AL31: =IF(N(F31)>=$E31*1000,"",IF(AND($E31>0,AK31>=$E31*1000),"G",IF(F$2<=TODAY(),"R",""))) | AM31: =AK31-IF(AL31="G",$E31*1000,0)+N(G31) -> 0 | AN31: =IF(N(J31)>=$E31*1000,"",IF(AND($E31>0,AM31>=$E31*1000),"G",IF(J$2<=TODAY(),"R",""))) | AO31: =AM31-IF(AN31="G",$E31*1000,0)+N(K31) -> 0 | AP31: =IF(N(N31)>=$E31*1000,"",IF(AND($E31>0,AO31>=$E31*1000),"G",IF(N$2<=TODAY(),"R",""))) | AQ31: =AO31-IF(AP31="G",$E31*1000,0)+N(O31) -> 0 | AR31: =IF(N(R31)>=$E31*1000,"",IF(AND($E31>0,AQ31>=$E31*1000),"G",IF(R$2<=TODAY(),"R",""))) | AS31: =AQ31-IF(AR31="G",$E31*1000,0)+N(S31) -> 0 | AT31: =IF(N(V31)>=$E31*1000,"",IF(AND($E31>0,AS31>=$E31*1000),"G",IF(V$2<=TODAY(),"R",""))) | AU31: =AS31-IF(AT31="G",$E31*1000,0)+N(W31) -> 0 | AV31: =IF(N(Z31)>=$E31*1000,"",IF(AND($E31>0,AU31>=$E31*1000),"G",IF(Z$2<=TODAY(),"R",""))) | AW31: =AU31-IF(AV31="G",$E31*1000,0)+N(AA31) -> 0 | AX31: =IF(N(AD31)>=$E31*1000,"",IF(AND($E31>0,AW31>=$E31*1000),"G",IF(AD$2<=TODAY(),"R",""))) | AY31: =AW31-IF(AX31="G",$E31*1000,0)+N(AE31) -> 0
B32: =ROW()-3 -> 29 | C32: Idrish Alam | D32: ='Member Wise Deposit Summary'!D32 -> 1883033042 | E32: 1 | F32: =$E32*1000 -> 1000 | J32: =$E32*1000 -> 1000 | N32: =$E32*1000 -> 1000 | R32: =$E32*1000 -> 1000 | V32: =$E32*1000 -> 1000 | Z32: =$E32*1000 -> 1000 | AD32: =$E32*1000 -> 1000 | AH32: =F32+G32+H32+J32+K32+L32+N32+O32+P32+R32+S32+T32+V32+W32+X32+Z32+AA32+AB32+AD32+AE32+AF32 -> 7000 | AI32: =I32+M32+Q32+U32+Y32+AC32+AG32 -> 0 | AK32: 0 | AL32: =IF(N(F32)>=$E32*1000,"",IF(AND($E32>0,AK32>=$E32*1000),"G",IF(F$2<=TODAY(),"R",""))) | AM32: =AK32-IF(AL32="G",$E32*1000,0)+N(G32) -> 0 | AN32: =IF(N(J32)>=$E32*1000,"",IF(AND($E32>0,AM32>=$E32*1000),"G",IF(J$2<=TODAY(),"R",""))) | AO32: =AM32-IF(AN32="G",$E32*1000,0)+N(K32) -> 0 | AP32: =IF(N(N32)>=$E32*1000,"",IF(AND($E32>0,AO32>=$E32*1000),"G",IF(N$2<=TODAY(),"R",""))) | AQ32: =AO32-IF(AP32="G",$E32*1000,0)+N(O32) -> 0 | AR32: =IF(N(R32)>=$E32*1000,"",IF(AND($E32>0,AQ32>=$E32*1000),"G",IF(R$2<=TODAY(),"R",""))) | AS32: =AQ32-IF(AR32="G",$E32*1000,0)+N(S32) -> 0 | AT32: =IF(N(V32)>=$E32*1000,"",IF(AND($E32>0,AS32>=$E32*1000),"G",IF(V$2<=TODAY(),"R",""))) | AU32: =AS32-IF(AT32="G",$E32*1000,0)+N(W32) -> 0 | AV32: =IF(N(Z32)>=$E32*1000,"",IF(AND($E32>0,AU32>=$E32*1000),"G",IF(Z$2<=TODAY(),"R",""))) | AW32: =AU32-IF(AV32="G",$E32*1000,0)+N(AA32) -> 0 | AX32: =IF(N(AD32)>=$E32*1000,"",IF(AND($E32>0,AW32>=$E32*1000),"G",IF(AD$2<=TODAY(),"R",""))) | AY32: =AW32-IF(AX32="G",$E32*1000,0)+N(AE32) -> 0
B33: =ROW()-3 -> 30 | C33: Jahed | D33: ='Member Wise Deposit Summary'!D33 -> 966562024068 | E33: 2 | F33: =$E33*1000 -> 2000 | J33: =$E33*1000 -> 2000 | N33: =$E33*1000 -> 2000 | R33: =$E33*1000 -> 2000 | V33: =$E33*1000 -> 2000 | AD33: =$E33*1000 -> 2000 | AF33: 2000 | AG33: 100 | AH33: =F33+G33+H33+J33+K33+L33+N33+O33+P33+R33+S33+T33+V33+W33+X33+Z33+AA33+AB33+AD33+AE33+AF33 -> 14000 | AI33: =I33+M33+Q33+U33+Y33+AC33+AG33 -> 100 | AK33: 0 | AL33: =IF(N(F33)>=$E33*1000,"",IF(AND($E33>0,AK33>=$E33*1000),"G",IF(F$2<=TODAY(),"R",""))) | AM33: =AK33-IF(AL33="G",$E33*1000,0)+N(G33) -> 0 | AN33: =IF(N(J33)>=$E33*1000,"",IF(AND($E33>0,AM33>=$E33*1000),"G",IF(J$2<=TODAY(),"R",""))) | AO33: =AM33-IF(AN33="G",$E33*1000,0)+N(K33) -> 0 | AP33: =IF(N(N33)>=$E33*1000,"",IF(AND($E33>0,AO33>=$E33*1000),"G",IF(N$2<=TODAY(),"R",""))) | AQ33: =AO33-IF(AP33="G",$E33*1000,0)+N(O33) -> 0 | AR33: =IF(N(R33)>=$E33*1000,"",IF(AND($E33>0,AQ33>=$E33*1000),"G",IF(R$2<=TODAY(),"R",""))) | AS33: =AQ33-IF(AR33="G",$E33*1000,0)+N(S33) -> 0 | AT33: =IF(N(V33)>=$E33*1000,"",IF(AND($E33>0,AS33>=$E33*1000),"G",IF(V$2<=TODAY(),"R",""))) | AU33: =AS33-IF(AT33="G",$E33*1000,0)+N(W33) -> 0 | AV33: =IF(N(Z33)>=$E33*1000,"",IF(AND($E33>0,AU33>=$E33*1000),"G",IF(Z$2<=TODAY(),"R",""))) -> R | AW33: =AU33-IF(AV33="G",$E33*1000,0)+N(AA33) -> 0 | AX33: =IF(N(AD33)>=$E33*1000,"",IF(AND($E33>0,AW33>=$E33*1000),"G",IF(AD$2<=TODAY(),"R",""))) | AY33: =AW33-IF(AX33="G",$E33*1000,0)+N(AE33) -> 0
B34: =ROW()-3 -> 31 | C34: Sahidul Islam | D34: ='Member Wise Deposit Summary'!D34 -> 966549955548 | E34: 2 | F34: =$E34*1000 -> 2000 | J34: =$E34*1000 -> 2000 | N34: =$E34*1000 -> 2000 | R34: =$E34*1000 -> 2000 | V34: =$E34*1000 -> 2000 | Z34: =$E34*1000 -> 2000 | AD34: =$E34*1000 -> 2000 | AH34: =F34+G34+H34+J34+K34+L34+N34+O34+P34+R34+S34+T34+V34+W34+X34+Z34+AA34+AB34+AD34+AE34+AF34 -> 14000 | AI34: =I34+M34+Q34+U34+Y34+AC34+AG34 -> 0 | AK34: 0 | AL34: =IF(N(F34)>=$E34*1000,"",IF(AND($E34>0,AK34>=$E34*1000),"G",IF(F$2<=TODAY(),"R",""))) | AM34: =AK34-IF(AL34="G",$E34*1000,0)+N(G34) -> 0 | AN34: =IF(N(J34)>=$E34*1000,"",IF(AND($E34>0,AM34>=$E34*1000),"G",IF(J$2<=TODAY(),"R",""))) | AO34: =AM34-IF(AN34="G",$E34*1000,0)+N(K34) -> 0 | AP34: =IF(N(N34)>=$E34*1000,"",IF(AND($E34>0,AO34>=$E34*1000),"G",IF(N$2<=TODAY(),"R",""))) | AQ34: =AO34-IF(AP34="G",$E34*1000,0)+N(O34) -> 0 | AR34: =IF(N(R34)>=$E34*1000,"",IF(AND($E34>0,AQ34>=$E34*1000),"G",IF(R$2<=TODAY(),"R",""))) | AS34: =AQ34-IF(AR34="G",$E34*1000,0)+N(S34) -> 0 | AT34: =IF(N(V34)>=$E34*1000,"",IF(AND($E34>0,AS34>=$E34*1000),"G",IF(V$2<=TODAY(),"R",""))) | AU34: =AS34-IF(AT34="G",$E34*1000,0)+N(W34) -> 0 | AV34: =IF(N(Z34)>=$E34*1000,"",IF(AND($E34>0,AU34>=$E34*1000),"G",IF(Z$2<=TODAY(),"R",""))) | AW34: =AU34-IF(AV34="G",$E34*1000,0)+N(AA34) -> 0 | AX34: =IF(N(AD34)>=$E34*1000,"",IF(AND($E34>0,AW34>=$E34*1000),"G",IF(AD$2<=TODAY(),"R",""))) | AY34: =AW34-IF(AX34="G",$E34*1000,0)+N(AE34) -> 0
B35: =ROW()-3 -> 32 | C35: Md. Sohel Uddin | D35: ='Member Wise Deposit Summary'!D35 -> 1822020050 | E35: 2 | F35: =$E35*1000 -> 2000 | J35: =$E35*1000 -> 2000 | N35: =$E35*1000 -> 2000 | R35: =$E35*1000 -> 2000 | V35: =$E35*1000 -> 2000 | Z35: =$E35*1000 -> 2000 | AH35: =F35+G35+H35+J35+K35+L35+N35+O35+P35+R35+S35+T35+V35+W35+X35+Z35+AA35+AB35+AD35+AE35+AF35 -> 12000 | AI35: =I35+M35+Q35+U35+Y35+AC35+AG35 -> 0 | AK35: 0 | AL35: =IF(N(F35)>=$E35*1000,"",IF(AND($E35>0,AK35>=$E35*1000),"G",IF(F$2<=TODAY(),"R",""))) | AM35: =AK35-IF(AL35="G",$E35*1000,0)+N(G35) -> 0 | AN35: =IF(N(J35)>=$E35*1000,"",IF(AND($E35>0,AM35>=$E35*1000),"G",IF(J$2<=TODAY(),"R",""))) | AO35: =AM35-IF(AN35="G",$E35*1000,0)+N(K35) -> 0 | AP35: =IF(N(N35)>=$E35*1000,"",IF(AND($E35>0,AO35>=$E35*1000),"G",IF(N$2<=TODAY(),"R",""))) | AQ35: =AO35-IF(AP35="G",$E35*1000,0)+N(O35) -> 0 | AR35: =IF(N(R35)>=$E35*1000,"",IF(AND($E35>0,AQ35>=$E35*1000),"G",IF(R$2<=TODAY(),"R",""))) | AS35: =AQ35-IF(AR35="G",$E35*1000,0)+N(S35) -> 0 | AT35: =IF(N(V35)>=$E35*1000,"",IF(AND($E35>0,AS35>=$E35*1000),"G",IF(V$2<=TODAY(),"R",""))) | AU35: =AS35-IF(AT35="G",$E35*1000,0)+N(W35) -> 0 | AV35: =IF(N(Z35)>=$E35*1000,"",IF(AND($E35>0,AU35>=$E35*1000),"G",IF(Z$2<=TODAY(),"R",""))) | AW35: =AU35-IF(AV35="G",$E35*1000,0)+N(AA35) -> 0 | AX35: =IF(N(AD35)>=$E35*1000,"",IF(AND($E35>0,AW35>=$E35*1000),"G",IF(AD$2<=TODAY(),"R",""))) -> R | AY35: =AW35-IF(AX35="G",$E35*1000,0)+N(AE35) -> 0
B36: =ROW()-3 -> 33 | C36: Mohammad Faruk | D36: ='Member Wise Deposit Summary'!D36 -> 1831797810 | E36: 1 | F36: =$E36*1000 -> 1000 | J36: =$E36*1000 -> 1000 | N36: =$E36*1000 -> 1000 | V36: =$E36*1000 -> 1000 | X36: 1000 | Y36: 50 | Z36: =$E36*1000 -> 1000 | AH36: =F36+G36+H36+J36+K36+L36+N36+O36+P36+R36+S36+T36+V36+W36+X36+Z36+AA36+AB36+AD36+AE36+AF36 -> 6000 | AI36: =I36+M36+Q36+U36+Y36+AC36+AG36 -> 50 | AK36: 0 | AL36: =IF(N(F36)>=$E36*1000,"",IF(AND($E36>0,AK36>=$E36*1000),"G",IF(F$2<=TODAY(),"R",""))) | AM36: =AK36-IF(AL36="G",$E36*1000,0)+N(G36) -> 0 | AN36: =IF(N(J36)>=$E36*1000,"",IF(AND($E36>0,AM36>=$E36*1000),"G",IF(J$2<=TODAY(),"R",""))) | AO36: =AM36-IF(AN36="G",$E36*1000,0)+N(K36) -> 0 | AP36: =IF(N(N36)>=$E36*1000,"",IF(AND($E36>0,AO36>=$E36*1000),"G",IF(N$2<=TODAY(),"R",""))) | AQ36: =AO36-IF(AP36="G",$E36*1000,0)+N(O36) -> 0 | AR36: =IF(N(R36)>=$E36*1000,"",IF(AND($E36>0,AQ36>=$E36*1000),"G",IF(R$2<=TODAY(),"R",""))) -> R | AS36: =AQ36-IF(AR36="G",$E36*1000,0)+N(S36) -> 0 | AT36: =IF(N(V36)>=$E36*1000,"",IF(AND($E36>0,AS36>=$E36*1000),"G",IF(V$2<=TODAY(),"R",""))) | AU36: =AS36-IF(AT36="G",$E36*1000,0)+N(W36) -> 0 | AV36: =IF(N(Z36)>=$E36*1000,"",IF(AND($E36>0,AU36>=$E36*1000),"G",IF(Z$2<=TODAY(),"R",""))) | AW36: =AU36-IF(AV36="G",$E36*1000,0)+N(AA36) -> 0 | AX36: =IF(N(AD36)>=$E36*1000,"",IF(AND($E36>0,AW36>=$E36*1000),"G",IF(AD$2<=TODAY(),"R",""))) -> R | AY36: =AW36-IF(AX36="G",$E36*1000,0)+N(AE36) -> 0
B37: =ROW()-3 -> 34 | C37: Didarul Islam | D37: ='Member Wise Deposit Summary'!D37 -> 971562663270 | E37: 1 | F37: =$E37*1000 -> 1000 | J37: =$E37*1000 -> 1000 | N37: =$E37*1000 -> 1000 | R37: =$E37*1000 -> 1000 | V37: =$E37*1000 -> 1000 | Z37: =$E37*1000 -> 1000 | AD37: =$E37*1000 -> 1000 | AH37: =F37+G37+H37+J37+K37+L37+N37+O37+P37+R37+S37+T37+V37+W37+X37+Z37+AA37+AB37+AD37+AE37+AF37 -> 7000 | AI37: =I37+M37+Q37+U37+Y37+AC37+AG37 -> 0 | AK37: 0 | AL37: =IF(N(F37)>=$E37*1000,"",IF(AND($E37>0,AK37>=$E37*1000),"G",IF(F$2<=TODAY(),"R",""))) | AM37: =AK37-IF(AL37="G",$E37*1000,0)+N(G37) -> 0 | AN37: =IF(N(J37)>=$E37*1000,"",IF(AND($E37>0,AM37>=$E37*1000),"G",IF(J$2<=TODAY(),"R",""))) | AO37: =AM37-IF(AN37="G",$E37*1000,0)+N(K37) -> 0 | AP37: =IF(N(N37)>=$E37*1000,"",IF(AND($E37>0,AO37>=$E37*1000),"G",IF(N$2<=TODAY(),"R",""))) | AQ37: =AO37-IF(AP37="G",$E37*1000,0)+N(O37) -> 0 | AR37: =IF(N(R37)>=$E37*1000,"",IF(AND($E37>0,AQ37>=$E37*1000),"G",IF(R$2<=TODAY(),"R",""))) | AS37: =AQ37-IF(AR37="G",$E37*1000,0)+N(S37) -> 0 | AT37: =IF(N(V37)>=$E37*1000,"",IF(AND($E37>0,AS37>=$E37*1000),"G",IF(V$2<=TODAY(),"R",""))) | AU37: =AS37-IF(AT37="G",$E37*1000,0)+N(W37) -> 0 | AV37: =IF(N(Z37)>=$E37*1000,"",IF(AND($E37>0,AU37>=$E37*1000),"G",IF(Z$2<=TODAY(),"R",""))) | AW37: =AU37-IF(AV37="G",$E37*1000,0)+N(AA37) -> 0 | AX37: =IF(N(AD37)>=$E37*1000,"",IF(AND($E37>0,AW37>=$E37*1000),"G",IF(AD$2<=TODAY(),"R",""))) | AY37: =AW37-IF(AX37="G",$E37*1000,0)+N(AE37) -> 0
B38: =ROW()-3 -> 35 | C38: Mohammad Fahim | D38: ='Member Wise Deposit Summary'!D38 -> 1873808231 | E38: 2 | F38: =$E38*1000 -> 2000 | J38: =$E38*1000 -> 2000 | N38: =$E38*1000 -> 2000 | R38: =$E38*1000 -> 2000 | V38: =$E38*1000 -> 2000 | Z38: =$E38*1000 -> 2000 | AD38: =$E38*1000 -> 2000 | AH38: =F38+G38+H38+J38+K38+L38+N38+O38+P38+R38+S38+T38+V38+W38+X38+Z38+AA38+AB38+AD38+AE38+AF38 -> 14000 | AI38: =I38+M38+Q38+U38+Y38+AC38+AG38 -> 0 | AK38: 0 | AL38: =IF(N(F38)>=$E38*1000,"",IF(AND($E38>0,AK38>=$E38*1000),"G",IF(F$2<=TODAY(),"R",""))) | AM38: =AK38-IF(AL38="G",$E38*1000,0)+N(G38) -> 0 | AN38: =IF(N(J38)>=$E38*1000,"",IF(AND($E38>0,AM38>=$E38*1000),"G",IF(J$2<=TODAY(),"R",""))) | AO38: =AM38-IF(AN38="G",$E38*1000,0)+N(K38) -> 0 | AP38: =IF(N(N38)>=$E38*1000,"",IF(AND($E38>0,AO38>=$E38*1000),"G",IF(N$2<=TODAY(),"R",""))) | AQ38: =AO38-IF(AP38="G",$E38*1000,0)+N(O38) -> 0 | AR38: =IF(N(R38)>=$E38*1000,"",IF(AND($E38>0,AQ38>=$E38*1000),"G",IF(R$2<=TODAY(),"R",""))) | AS38: =AQ38-IF(AR38="G",$E38*1000,0)+N(S38) -> 0 | AT38: =IF(N(V38)>=$E38*1000,"",IF(AND($E38>0,AS38>=$E38*1000),"G",IF(V$2<=TODAY(),"R",""))) | AU38: =AS38-IF(AT38="G",$E38*1000,0)+N(W38) -> 0 | AV38: =IF(N(Z38)>=$E38*1000,"",IF(AND($E38>0,AU38>=$E38*1000),"G",IF(Z$2<=TODAY(),"R",""))) | AW38: =AU38-IF(AV38="G",$E38*1000,0)+N(AA38) -> 0 | AX38: =IF(N(AD38)>=$E38*1000,"",IF(AND($E38>0,AW38>=$E38*1000),"G",IF(AD$2<=TODAY(),"R",""))) | AY38: =AW38-IF(AX38="G",$E38*1000,0)+N(AE38) -> 0
B39: =ROW()-3 -> 36 | C39: Delower Hossain | D39: ='Member Wise Deposit Summary'!D39 -> 971561572487 | E39: 1 | F39: =$E39*1000 -> 1000 | J39: =$E39*1000 -> 1000 | N39: =$E39*1000 -> 1000 | R39: =$E39*1000 -> 1000 | V39: =$E39*1000 -> 1000 | Z39: =$E39*1000 -> 1000 | AD39: =$E39*1000 -> 1000 | AH39: =F39+G39+H39+J39+K39+L39+N39+O39+P39+R39+S39+T39+V39+W39+X39+Z39+AA39+AB39+AD39+AE39+AF39 -> 7000 | AI39: =I39+M39+Q39+U39+Y39+AC39+AG39 -> 0 | AK39: 0 | AL39: =IF(N(F39)>=$E39*1000,"",IF(AND($E39>0,AK39>=$E39*1000),"G",IF(F$2<=TODAY(),"R",""))) | AM39: =AK39-IF(AL39="G",$E39*1000,0)+N(G39) -> 0 | AN39: =IF(N(J39)>=$E39*1000,"",IF(AND($E39>0,AM39>=$E39*1000),"G",IF(J$2<=TODAY(),"R",""))) | AO39: =AM39-IF(AN39="G",$E39*1000,0)+N(K39) -> 0 | AP39: =IF(N(N39)>=$E39*1000,"",IF(AND($E39>0,AO39>=$E39*1000),"G",IF(N$2<=TODAY(),"R",""))) | AQ39: =AO39-IF(AP39="G",$E39*1000,0)+N(O39) -> 0 | AR39: =IF(N(R39)>=$E39*1000,"",IF(AND($E39>0,AQ39>=$E39*1000),"G",IF(R$2<=TODAY(),"R",""))) | AS39: =AQ39-IF(AR39="G",$E39*1000,0)+N(S39) -> 0 | AT39: =IF(N(V39)>=$E39*1000,"",IF(AND($E39>0,AS39>=$E39*1000),"G",IF(V$2<=TODAY(),"R",""))) | AU39: =AS39-IF(AT39="G",$E39*1000,0)+N(W39) -> 0 | AV39: =IF(N(Z39)>=$E39*1000,"",IF(AND($E39>0,AU39>=$E39*1000),"G",IF(Z$2<=TODAY(),"R",""))) | AW39: =AU39-IF(AV39="G",$E39*1000,0)+N(AA39) -> 0 | AX39: =IF(N(AD39)>=$E39*1000,"",IF(AND($E39>0,AW39>=$E39*1000),"G",IF(AD$2<=TODAY(),"R",""))) | AY39: =AW39-IF(AX39="G",$E39*1000,0)+N(AE39) -> 0
B40: =ROW()-3 -> 37 | C40: Abdul Malek | D40: ='Member Wise Deposit Summary'!D40 -> 1879352117 | E40: 2 | F40: =$E40*1000 -> 2000 | J40: =$E40*1000 -> 2000 | N40: =$E40*1000 -> 2000 | R40: =$E40*1000 -> 2000 | V40: =$E40*1000 -> 2000 | Z40: =$E40*1000 -> 2000 | AD40: =$E40*1000 -> 2000 | AH40: =F40+G40+H40+J40+K40+L40+N40+O40+P40+R40+S40+T40+V40+W40+X40+Z40+AA40+AB40+AD40+AE40+AF40 -> 14000 | AI40: =I40+M40+Q40+U40+Y40+AC40+AG40 -> 0 | AK40: 0 | AL40: =IF(N(F40)>=$E40*1000,"",IF(AND($E40>0,AK40>=$E40*1000),"G",IF(F$2<=TODAY(),"R",""))) | AM40: =AK40-IF(AL40="G",$E40*1000,0)+N(G40) -> 0 | AN40: =IF(N(J40)>=$E40*1000,"",IF(AND($E40>0,AM40>=$E40*1000),"G",IF(J$2<=TODAY(),"R",""))) | AO40: =AM40-IF(AN40="G",$E40*1000,0)+N(K40) -> 0 | AP40: =IF(N(N40)>=$E40*1000,"",IF(AND($E40>0,AO40>=$E40*1000),"G",IF(N$2<=TODAY(),"R",""))) | AQ40: =AO40-IF(AP40="G",$E40*1000,0)+N(O40) -> 0 | AR40: =IF(N(R40)>=$E40*1000,"",IF(AND($E40>0,AQ40>=$E40*1000),"G",IF(R$2<=TODAY(),"R",""))) | AS40: =AQ40-IF(AR40="G",$E40*1000,0)+N(S40) -> 0 | AT40: =IF(N(V40)>=$E40*1000,"",IF(AND($E40>0,AS40>=$E40*1000),"G",IF(V$2<=TODAY(),"R",""))) | AU40: =AS40-IF(AT40="G",$E40*1000,0)+N(W40) -> 0 | AV40: =IF(N(Z40)>=$E40*1000,"",IF(AND($E40>0,AU40>=$E40*1000),"G",IF(Z$2<=TODAY(),"R",""))) | AW40: =AU40-IF(AV40="G",$E40*1000,0)+N(AA40) -> 0 | AX40: =IF(N(AD40)>=$E40*1000,"",IF(AND($E40>0,AW40>=$E40*1000),"G",IF(AD$2<=TODAY(),"R",""))) | AY40: =AW40-IF(AX40="G",$E40*1000,0)+N(AE40) -> 0
B41: =ROW()-3 -> 38 | C41: Khalil Uddin | D41: ='Member Wise Deposit Summary'!D41 -> 00971569173725 | E41: 2 | F41: =$E41*1000 -> 2000 | J41: =$E41*1000 -> 2000 | N41: =$E41*1000 -> 2000 | R41: =$E41*1000 -> 2000 | V41: =$E41*1000 -> 2000 | Z41: =$E41*1000 -> 2000 | AD41: =$E41*1000 -> 2000 | AH41: =F41+G41+H41+J41+K41+L41+N41+O41+P41+R41+S41+T41+V41+W41+X41+Z41+AA41+AB41+AD41+AE41+AF41 -> 14000 | AI41: =I41+M41+Q41+U41+Y41+AC41+AG41 -> 0 | AK41: 0 | AL41: =IF(N(F41)>=$E41*1000,"",IF(AND($E41>0,AK41>=$E41*1000),"G",IF(F$2<=TODAY(),"R",""))) | AM41: =AK41-IF(AL41="G",$E41*1000,0)+N(G41) -> 0 | AN41: =IF(N(J41)>=$E41*1000,"",IF(AND($E41>0,AM41>=$E41*1000),"G",IF(J$2<=TODAY(),"R",""))) | AO41: =AM41-IF(AN41="G",$E41*1000,0)+N(K41) -> 0 | AP41: =IF(N(N41)>=$E41*1000,"",IF(AND($E41>0,AO41>=$E41*1000),"G",IF(N$2<=TODAY(),"R",""))) | AQ41: =AO41-IF(AP41="G",$E41*1000,0)+N(O41) -> 0 | AR41: =IF(N(R41)>=$E41*1000,"",IF(AND($E41>0,AQ41>=$E41*1000),"G",IF(R$2<=TODAY(),"R",""))) | AS41: =AQ41-IF(AR41="G",$E41*1000,0)+N(S41) -> 0 | AT41: =IF(N(V41)>=$E41*1000,"",IF(AND($E41>0,AS41>=$E41*1000),"G",IF(V$2<=TODAY(),"R",""))) | AU41: =AS41-IF(AT41="G",$E41*1000,0)+N(W41) -> 0 | AV41: =IF(N(Z41)>=$E41*1000,"",IF(AND($E41>0,AU41>=$E41*1000),"G",IF(Z$2<=TODAY(),"R",""))) | AW41: =AU41-IF(AV41="G",$E41*1000,0)+N(AA41) -> 0 | AX41: =IF(N(AD41)>=$E41*1000,"",IF(AND($E41>0,AW41>=$E41*1000),"G",IF(AD$2<=TODAY(),"R",""))) | AY41: =AW41-IF(AX41="G",$E41*1000,0)+N(AE41) -> 0
B42: =ROW()-3 -> 39 | C42: Mohammad Abul Hashem | D42: ='Member Wise Deposit Summary'!D42 -> 1873807617 | E42: 2 | F42: =$E42*1000 -> 2000 | J42: =$E42*1000 -> 2000 | N42: =$E42*1000 -> 2000 | R42: =$E42*1000 -> 2000 | V42: =$E42*1000 -> 2000 | AD42: =$E42*1000 -> 2000 | AF42: 2000 | AG42: 100 | AH42: =F42+G42+H42+J42+K42+L42+N42+O42+P42+R42+S42+T42+V42+W42+X42+Z42+AA42+AB42+AD42+AE42+AF42 -> 14000 | AI42: =I42+M42+Q42+U42+Y42+AC42+AG42 -> 100 | AK42: 0 | AL42: =IF(N(F42)>=$E42*1000,"",IF(AND($E42>0,AK42>=$E42*1000),"G",IF(F$2<=TODAY(),"R",""))) | AM42: =AK42-IF(AL42="G",$E42*1000,0)+N(G42) -> 0 | AN42: =IF(N(J42)>=$E42*1000,"",IF(AND($E42>0,AM42>=$E42*1000),"G",IF(J$2<=TODAY(),"R",""))) | AO42: =AM42-IF(AN42="G",$E42*1000,0)+N(K42) -> 0 | AP42: =IF(N(N42)>=$E42*1000,"",IF(AND($E42>0,AO42>=$E42*1000),"G",IF(N$2<=TODAY(),"R",""))) | AQ42: =AO42-IF(AP42="G",$E42*1000,0)+N(O42) -> 0 | AR42: =IF(N(R42)>=$E42*1000,"",IF(AND($E42>0,AQ42>=$E42*1000),"G",IF(R$2<=TODAY(),"R",""))) | AS42: =AQ42-IF(AR42="G",$E42*1000,0)+N(S42) -> 0 | AT42: =IF(N(V42)>=$E42*1000,"",IF(AND($E42>0,AS42>=$E42*1000),"G",IF(V$2<=TODAY(),"R",""))) | AU42: =AS42-IF(AT42="G",$E42*1000,0)+N(W42) -> 0 | AV42: =IF(N(Z42)>=$E42*1000,"",IF(AND($E42>0,AU42>=$E42*1000),"G",IF(Z$2<=TODAY(),"R",""))) -> R | AW42: =AU42-IF(AV42="G",$E42*1000,0)+N(AA42) -> 0 | AX42: =IF(N(AD42)>=$E42*1000,"",IF(AND($E42>0,AW42>=$E42*1000),"G",IF(AD$2<=TODAY(),"R",""))) | AY42: =AW42-IF(AX42="G",$E42*1000,0)+N(AE42) -> 0
B43: =ROW()-3 -> 40 | C43: Abdul Karim | D43: ='Member Wise Deposit Summary'!D43 -> 971569774500 | E43: 2 | F43: =$E43*1000 -> 2000 | J43: =$E43*1000 -> 2000 | N43: =$E43*1000 -> 2000 | R43: =$E43*1000 -> 2000 | V43: =$E43*1000 -> 2000 | Z43: =$E43*1000 -> 2000 | AD43: =$E43*1000 -> 2000 | AH43: =F43+G43+H43+J43+K43+L43+N43+O43+P43+R43+S43+T43+V43+W43+X43+Z43+AA43+AB43+AD43+AE43+AF43 -> 14000 | AI43: =I43+M43+Q43+U43+Y43+AC43+AG43 -> 0 | AK43: 0 | AL43: =IF(N(F43)>=$E43*1000,"",IF(AND($E43>0,AK43>=$E43*1000),"G",IF(F$2<=TODAY(),"R",""))) | AM43: =AK43-IF(AL43="G",$E43*1000,0)+N(G43) -> 0 | AN43: =IF(N(J43)>=$E43*1000,"",IF(AND($E43>0,AM43>=$E43*1000),"G",IF(J$2<=TODAY(),"R",""))) | AO43: =AM43-IF(AN43="G",$E43*1000,0)+N(K43) -> 0 | AP43: =IF(N(N43)>=$E43*1000,"",IF(AND($E43>0,AO43>=$E43*1000),"G",IF(N$2<=TODAY(),"R",""))) | AQ43: =AO43-IF(AP43="G",$E43*1000,0)+N(O43) -> 0 | AR43: =IF(N(R43)>=$E43*1000,"",IF(AND($E43>0,AQ43>=$E43*1000),"G",IF(R$2<=TODAY(),"R",""))) | AS43: =AQ43-IF(AR43="G",$E43*1000,0)+N(S43) -> 0 | AT43: =IF(N(V43)>=$E43*1000,"",IF(AND($E43>0,AS43>=$E43*1000),"G",IF(V$2<=TODAY(),"R",""))) | AU43: =AS43-IF(AT43="G",$E43*1000,0)+N(W43) -> 0 | AV43: =IF(N(Z43)>=$E43*1000,"",IF(AND($E43>0,AU43>=$E43*1000),"G",IF(Z$2<=TODAY(),"R",""))) | AW43: =AU43-IF(AV43="G",$E43*1000,0)+N(AA43) -> 0 | AX43: =IF(N(AD43)>=$E43*1000,"",IF(AND($E43>0,AW43>=$E43*1000),"G",IF(AD$2<=TODAY(),"R",""))) | AY43: =AW43-IF(AX43="G",$E43*1000,0)+N(AE43) -> 0
B44: =ROW()-3 -> 41 | C44: Mohammad Kaisar | D44: ='Member Wise Deposit Summary'!D44 -> 1830621990 | E44: 2 | F44: =$E44*1000 -> 2000 | J44: =$E44*1000 -> 2000 | N44: =$E44*1000 -> 2000 | R44: =$E44*1000 -> 2000 | V44: =$E44*1000 -> 2000 | Z44: =$E44*1000 -> 2000 | AD44: =$E44*1000 -> 2000 | AH44: =F44+G44+H44+J44+K44+L44+N44+O44+P44+R44+S44+T44+V44+W44+X44+Z44+AA44+AB44+AD44+AE44+AF44 -> 14000 | AI44: =I44+M44+Q44+U44+Y44+AC44+AG44 -> 0 | AK44: 0 | AL44: =IF(N(F44)>=$E44*1000,"",IF(AND($E44>0,AK44>=$E44*1000),"G",IF(F$2<=TODAY(),"R",""))) | AM44: =AK44-IF(AL44="G",$E44*1000,0)+N(G44) -> 0 | AN44: =IF(N(J44)>=$E44*1000,"",IF(AND($E44>0,AM44>=$E44*1000),"G",IF(J$2<=TODAY(),"R",""))) | AO44: =AM44-IF(AN44="G",$E44*1000,0)+N(K44) -> 0 | AP44: =IF(N(N44)>=$E44*1000,"",IF(AND($E44>0,AO44>=$E44*1000),"G",IF(N$2<=TODAY(),"R",""))) | AQ44: =AO44-IF(AP44="G",$E44*1000,0)+N(O44) -> 0 | AR44: =IF(N(R44)>=$E44*1000,"",IF(AND($E44>0,AQ44>=$E44*1000),"G",IF(R$2<=TODAY(),"R",""))) | AS44: =AQ44-IF(AR44="G",$E44*1000,0)+N(S44) -> 0 | AT44: =IF(N(V44)>=$E44*1000,"",IF(AND($E44>0,AS44>=$E44*1000),"G",IF(V$2<=TODAY(),"R",""))) | AU44: =AS44-IF(AT44="G",$E44*1000,0)+N(W44) -> 0 | AV44: =IF(N(Z44)>=$E44*1000,"",IF(AND($E44>0,AU44>=$E44*1000),"G",IF(Z$2<=TODAY(),"R",""))) | AW44: =AU44-IF(AV44="G",$E44*1000,0)+N(AA44) -> 0 | AX44: =IF(N(AD44)>=$E44*1000,"",IF(AND($E44>0,AW44>=$E44*1000),"G",IF(AD$2<=TODAY(),"R",""))) | AY44: =AW44-IF(AX44="G",$E44*1000,0)+N(AE44) -> 0
B45: =ROW()-3 -> 42 | C45: Korshed Alam | D45: ='Member Wise Deposit Summary'!D45 -> 0971501332588 | E45: 6 | F45: =$E45*1000 -> 6000 | J45: =$E45*1000 -> 6000 | N45: =$E45*1000 -> 6000 | R45: =$E45*1000 -> 6000 | V45: =$E45*1000 -> 6000 | Z45: =$E45*1000 -> 6000 | AD45: =$E45*1000 -> 6000 | AH45: =F45+G45+H45+J45+K45+L45+N45+O45+P45+R45+S45+T45+V45+W45+X45+Z45+AA45+AB45+AD45+AE45+AF45 -> 42000 | AI45: =I45+M45+Q45+U45+Y45+AC45+AG45 -> 0 | AK45: 0 | AL45: =IF(N(F45)>=$E45*1000,"",IF(AND($E45>0,AK45>=$E45*1000),"G",IF(F$2<=TODAY(),"R",""))) | AM45: =AK45-IF(AL45="G",$E45*1000,0)+N(G45) -> 0 | AN45: =IF(N(J45)>=$E45*1000,"",IF(AND($E45>0,AM45>=$E45*1000),"G",IF(J$2<=TODAY(),"R",""))) | AO45: =AM45-IF(AN45="G",$E45*1000,0)+N(K45) -> 0 | AP45: =IF(N(N45)>=$E45*1000,"",IF(AND($E45>0,AO45>=$E45*1000),"G",IF(N$2<=TODAY(),"R",""))) | AQ45: =AO45-IF(AP45="G",$E45*1000,0)+N(O45) -> 0 | AR45: =IF(N(R45)>=$E45*1000,"",IF(AND($E45>0,AQ45>=$E45*1000),"G",IF(R$2<=TODAY(),"R",""))) | AS45: =AQ45-IF(AR45="G",$E45*1000,0)+N(S45) -> 0 | AT45: =IF(N(V45)>=$E45*1000,"",IF(AND($E45>0,AS45>=$E45*1000),"G",IF(V$2<=TODAY(),"R",""))) | AU45: =AS45-IF(AT45="G",$E45*1000,0)+N(W45) -> 0 | AV45: =IF(N(Z45)>=$E45*1000,"",IF(AND($E45>0,AU45>=$E45*1000),"G",IF(Z$2<=TODAY(),"R",""))) | AW45: =AU45-IF(AV45="G",$E45*1000,0)+N(AA45) -> 0 | AX45: =IF(N(AD45)>=$E45*1000,"",IF(AND($E45>0,AW45>=$E45*1000),"G",IF(AD$2<=TODAY(),"R",""))) | AY45: =AW45-IF(AX45="G",$E45*1000,0)+N(AE45) -> 0
B46: =ROW()-3 -> 43 | C46: Emon Hasan | D46: ='Member Wise Deposit Summary'!D46 -> 971545640821 | E46: 2 | F46: =$E46*1000 -> 2000 | J46: =$E46*1000 -> 2000 | N46: =$E46*1000 -> 2000 | R46: =$E46*1000 -> 2000 | Z46: =$E46*1000 -> 2000 | AB46: 2000 | AC46: 100 | AH46: =F46+G46+H46+J46+K46+L46+N46+O46+P46+R46+S46+T46+V46+W46+X46+Z46+AA46+AB46+AD46+AE46+AF46 -> 12000 | AI46: =I46+M46+Q46+U46+Y46+AC46+AG46 -> 100 | AK46: 0 | AL46: =IF(N(F46)>=$E46*1000,"",IF(AND($E46>0,AK46>=$E46*1000),"G",IF(F$2<=TODAY(),"R",""))) | AM46: =AK46-IF(AL46="G",$E46*1000,0)+N(G46) -> 0 | AN46: =IF(N(J46)>=$E46*1000,"",IF(AND($E46>0,AM46>=$E46*1000),"G",IF(J$2<=TODAY(),"R",""))) | AO46: =AM46-IF(AN46="G",$E46*1000,0)+N(K46) -> 0 | AP46: =IF(N(N46)>=$E46*1000,"",IF(AND($E46>0,AO46>=$E46*1000),"G",IF(N$2<=TODAY(),"R",""))) | AQ46: =AO46-IF(AP46="G",$E46*1000,0)+N(O46) -> 0 | AR46: =IF(N(R46)>=$E46*1000,"",IF(AND($E46>0,AQ46>=$E46*1000),"G",IF(R$2<=TODAY(),"R",""))) | AS46: =AQ46-IF(AR46="G",$E46*1000,0)+N(S46) -> 0 | AT46: =IF(N(V46)>=$E46*1000,"",IF(AND($E46>0,AS46>=$E46*1000),"G",IF(V$2<=TODAY(),"R",""))) -> R | AU46: =AS46-IF(AT46="G",$E46*1000,0)+N(W46) -> 0 | AV46: =IF(N(Z46)>=$E46*1000,"",IF(AND($E46>0,AU46>=$E46*1000),"G",IF(Z$2<=TODAY(),"R",""))) | AW46: =AU46-IF(AV46="G",$E46*1000,0)+N(AA46) -> 0 | AX46: =IF(N(AD46)>=$E46*1000,"",IF(AND($E46>0,AW46>=$E46*1000),"G",IF(AD$2<=TODAY(),"R",""))) -> R | AY46: =AW46-IF(AX46="G",$E46*1000,0)+N(AE46) -> 0
B47: =ROW()-3 -> 44 | C47: Tawhidul Islam | D47: ='Member Wise Deposit Summary'!D47 -> 971562982931 | E47: 2 | F47: =$E47*1000 -> 2000 | J47: =$E47*1000 -> 2000 | N47: =$E47*1000 -> 2000 | R47: =$E47*1000 -> 2000 | Z47: =$E47*1000 -> 2000 | AB47: 2000 | AC47: 100 | AH47: =F47+G47+H47+J47+K47+L47+N47+O47+P47+R47+S47+T47+V47+W47+X47+Z47+AA47+AB47+AD47+AE47+AF47 -> 12000 | AI47: =I47+M47+Q47+U47+Y47+AC47+AG47 -> 100 | AK47: 0 | AL47: =IF(N(F47)>=$E47*1000,"",IF(AND($E47>0,AK47>=$E47*1000),"G",IF(F$2<=TODAY(),"R",""))) | AM47: =AK47-IF(AL47="G",$E47*1000,0)+N(G47) -> 0 | AN47: =IF(N(J47)>=$E47*1000,"",IF(AND($E47>0,AM47>=$E47*1000),"G",IF(J$2<=TODAY(),"R",""))) | AO47: =AM47-IF(AN47="G",$E47*1000,0)+N(K47) -> 0 | AP47: =IF(N(N47)>=$E47*1000,"",IF(AND($E47>0,AO47>=$E47*1000),"G",IF(N$2<=TODAY(),"R",""))) | AQ47: =AO47-IF(AP47="G",$E47*1000,0)+N(O47) -> 0 | AR47: =IF(N(R47)>=$E47*1000,"",IF(AND($E47>0,AQ47>=$E47*1000),"G",IF(R$2<=TODAY(),"R",""))) | AS47: =AQ47-IF(AR47="G",$E47*1000,0)+N(S47) -> 0 | AT47: =IF(N(V47)>=$E47*1000,"",IF(AND($E47>0,AS47>=$E47*1000),"G",IF(V$2<=TODAY(),"R",""))) -> R | AU47: =AS47-IF(AT47="G",$E47*1000,0)+N(W47) -> 0 | AV47: =IF(N(Z47)>=$E47*1000,"",IF(AND($E47>0,AU47>=$E47*1000),"G",IF(Z$2<=TODAY(),"R",""))) | AW47: =AU47-IF(AV47="G",$E47*1000,0)+N(AA47) -> 0 | AX47: =IF(N(AD47)>=$E47*1000,"",IF(AND($E47>0,AW47>=$E47*1000),"G",IF(AD$2<=TODAY(),"R",""))) -> R | AY47: =AW47-IF(AX47="G",$E47*1000,0)+N(AE47) -> 0
B48: =ROW()-3 -> 45 | C48: Sahidul Islam | D48: ='Member Wise Deposit Summary'!D48 -> 1840409753 | E48: 1 | F48: =$E48*1000 -> 1000 | J48: =$E48*1000 -> 1000 | N48: =$E48*1000 -> 1000 | R48: =$E48*1000 -> 1000 | Z48: =$E48*1000 -> 1000 | AB48: 1000 | AC48: 50 | AH48: =F48+G48+H48+J48+K48+L48+N48+O48+P48+R48+S48+T48+V48+W48+X48+Z48+AA48+AB48+AD48+AE48+AF48 -> 6000 | AI48: =I48+M48+Q48+U48+Y48+AC48+AG48 -> 50 | AK48: 0 | AL48: =IF(N(F48)>=$E48*1000,"",IF(AND($E48>0,AK48>=$E48*1000),"G",IF(F$2<=TODAY(),"R",""))) | AM48: =AK48-IF(AL48="G",$E48*1000,0)+N(G48) -> 0 | AN48: =IF(N(J48)>=$E48*1000,"",IF(AND($E48>0,AM48>=$E48*1000),"G",IF(J$2<=TODAY(),"R",""))) | AO48: =AM48-IF(AN48="G",$E48*1000,0)+N(K48) -> 0 | AP48: =IF(N(N48)>=$E48*1000,"",IF(AND($E48>0,AO48>=$E48*1000),"G",IF(N$2<=TODAY(),"R",""))) | AQ48: =AO48-IF(AP48="G",$E48*1000,0)+N(O48) -> 0 | AR48: =IF(N(R48)>=$E48*1000,"",IF(AND($E48>0,AQ48>=$E48*1000),"G",IF(R$2<=TODAY(),"R",""))) | AS48: =AQ48-IF(AR48="G",$E48*1000,0)+N(S48) -> 0 | AT48: =IF(N(V48)>=$E48*1000,"",IF(AND($E48>0,AS48>=$E48*1000),"G",IF(V$2<=TODAY(),"R",""))) -> R | AU48: =AS48-IF(AT48="G",$E48*1000,0)+N(W48) -> 0 | AV48: =IF(N(Z48)>=$E48*1000,"",IF(AND($E48>0,AU48>=$E48*1000),"G",IF(Z$2<=TODAY(),"R",""))) | AW48: =AU48-IF(AV48="G",$E48*1000,0)+N(AA48) -> 0 | AX48: =IF(N(AD48)>=$E48*1000,"",IF(AND($E48>0,AW48>=$E48*1000),"G",IF(AD$2<=TODAY(),"R",""))) -> R | AY48: =AW48-IF(AX48="G",$E48*1000,0)+N(AE48) -> 0
B49: =ROW()-3 -> 46 | C49: Amir Hossen | D49: ='Member Wise Deposit Summary'!D49 -> 1871081769 | E49: 1 | F49: =$E49*1000 -> 1000 | J49: =$E49*1000 -> 1000 | N49: =$E49*1000 -> 1000 | R49: =$E49*1000 -> 1000 | AF49: 1000 | AG49: 50 | AH49: =F49+G49+H49+J49+K49+L49+N49+O49+P49+R49+S49+T49+V49+W49+X49+Z49+AA49+AB49+AD49+AE49+AF49 -> 5000 | AI49: =I49+M49+Q49+U49+Y49+AC49+AG49 -> 50 | AK49: 0 | AL49: =IF(N(F49)>=$E49*1000,"",IF(AND($E49>0,AK49>=$E49*1000),"G",IF(F$2<=TODAY(),"R",""))) | AM49: =AK49-IF(AL49="G",$E49*1000,0)+N(G49) -> 0 | AN49: =IF(N(J49)>=$E49*1000,"",IF(AND($E49>0,AM49>=$E49*1000),"G",IF(J$2<=TODAY(),"R",""))) | AO49: =AM49-IF(AN49="G",$E49*1000,0)+N(K49) -> 0 | AP49: =IF(N(N49)>=$E49*1000,"",IF(AND($E49>0,AO49>=$E49*1000),"G",IF(N$2<=TODAY(),"R",""))) | AQ49: =AO49-IF(AP49="G",$E49*1000,0)+N(O49) -> 0 | AR49: =IF(N(R49)>=$E49*1000,"",IF(AND($E49>0,AQ49>=$E49*1000),"G",IF(R$2<=TODAY(),"R",""))) | AS49: =AQ49-IF(AR49="G",$E49*1000,0)+N(S49) -> 0 | AT49: =IF(N(V49)>=$E49*1000,"",IF(AND($E49>0,AS49>=$E49*1000),"G",IF(V$2<=TODAY(),"R",""))) -> R | AU49: =AS49-IF(AT49="G",$E49*1000,0)+N(W49) -> 0 | AV49: =IF(N(Z49)>=$E49*1000,"",IF(AND($E49>0,AU49>=$E49*1000),"G",IF(Z$2<=TODAY(),"R",""))) -> R | AW49: =AU49-IF(AV49="G",$E49*1000,0)+N(AA49) -> 0 | AX49: =IF(N(AD49)>=$E49*1000,"",IF(AND($E49>0,AW49>=$E49*1000),"G",IF(AD$2<=TODAY(),"R",""))) -> R | AY49: =AW49-IF(AX49="G",$E49*1000,0)+N(AE49) -> 0
B50: =ROW()-3 -> 47 | C50: Mohammad Abdullah Al Rafi | D50: ='Member Wise Deposit Summary'!D50 -> 1882916447 | E50: 1 | F50: =$E50*1000 -> 1000 | J50: =$E50*1000 -> 1000 | N50: =$E50*1000 -> 1000 | R50: =$E50*1000 -> 1000 | V50: =$E50*1000 -> 1000 | AD50: =$E50*1000 -> 1000 | AF50: 1000 | AG50: 50 | AH50: =F50+G50+H50+J50+K50+L50+N50+O50+P50+R50+S50+T50+V50+W50+X50+Z50+AA50+AB50+AD50+AE50+AF50 -> 7000 | AI50: =I50+M50+Q50+U50+Y50+AC50+AG50 -> 50 | AK50: 0 | AL50: =IF(N(F50)>=$E50*1000,"",IF(AND($E50>0,AK50>=$E50*1000),"G",IF(F$2<=TODAY(),"R",""))) | AM50: =AK50-IF(AL50="G",$E50*1000,0)+N(G50) -> 0 | AN50: =IF(N(J50)>=$E50*1000,"",IF(AND($E50>0,AM50>=$E50*1000),"G",IF(J$2<=TODAY(),"R",""))) | AO50: =AM50-IF(AN50="G",$E50*1000,0)+N(K50) -> 0 | AP50: =IF(N(N50)>=$E50*1000,"",IF(AND($E50>0,AO50>=$E50*1000),"G",IF(N$2<=TODAY(),"R",""))) | AQ50: =AO50-IF(AP50="G",$E50*1000,0)+N(O50) -> 0 | AR50: =IF(N(R50)>=$E50*1000,"",IF(AND($E50>0,AQ50>=$E50*1000),"G",IF(R$2<=TODAY(),"R",""))) | AS50: =AQ50-IF(AR50="G",$E50*1000,0)+N(S50) -> 0 | AT50: =IF(N(V50)>=$E50*1000,"",IF(AND($E50>0,AS50>=$E50*1000),"G",IF(V$2<=TODAY(),"R",""))) | AU50: =AS50-IF(AT50="G",$E50*1000,0)+N(W50) -> 0 | AV50: =IF(N(Z50)>=$E50*1000,"",IF(AND($E50>0,AU50>=$E50*1000),"G",IF(Z$2<=TODAY(),"R",""))) -> R | AW50: =AU50-IF(AV50="G",$E50*1000,0)+N(AA50) -> 0 | AX50: =IF(N(AD50)>=$E50*1000,"",IF(AND($E50>0,AW50>=$E50*1000),"G",IF(AD$2<=TODAY(),"R",""))) | AY50: =AW50-IF(AX50="G",$E50*1000,0)+N(AE50) -> 0
B51: =ROW()-3 -> 48 | C51: Nurul Huda Misbah | D51: ='Member Wise Deposit Summary'!D51 -> 1814836702 | E51: 2 | F51: =$E51*1000 -> 2000 | J51: =$E51*1000 -> 2000 | N51: =$E51*1000 -> 2000 | R51: =$E51*1000 -> 2000 | V51: =$E51*1000 -> 2000 | Z51: =$E51*1000 -> 2000 | AD51: =$E51*1000 -> 2000 | AH51: =F51+G51+H51+J51+K51+L51+N51+O51+P51+R51+S51+T51+V51+W51+X51+Z51+AA51+AB51+AD51+AE51+AF51 -> 14000 | AI51: =I51+M51+Q51+U51+Y51+AC51+AG51 -> 0 | AK51: 0 | AL51: =IF(N(F51)>=$E51*1000,"",IF(AND($E51>0,AK51>=$E51*1000),"G",IF(F$2<=TODAY(),"R",""))) | AM51: =AK51-IF(AL51="G",$E51*1000,0)+N(G51) -> 0 | AN51: =IF(N(J51)>=$E51*1000,"",IF(AND($E51>0,AM51>=$E51*1000),"G",IF(J$2<=TODAY(),"R",""))) | AO51: =AM51-IF(AN51="G",$E51*1000,0)+N(K51) -> 0 | AP51: =IF(N(N51)>=$E51*1000,"",IF(AND($E51>0,AO51>=$E51*1000),"G",IF(N$2<=TODAY(),"R",""))) | AQ51: =AO51-IF(AP51="G",$E51*1000,0)+N(O51) -> 0 | AR51: =IF(N(R51)>=$E51*1000,"",IF(AND($E51>0,AQ51>=$E51*1000),"G",IF(R$2<=TODAY(),"R",""))) | AS51: =AQ51-IF(AR51="G",$E51*1000,0)+N(S51) -> 0 | AT51: =IF(N(V51)>=$E51*1000,"",IF(AND($E51>0,AS51>=$E51*1000),"G",IF(V$2<=TODAY(),"R",""))) | AU51: =AS51-IF(AT51="G",$E51*1000,0)+N(W51) -> 0 | AV51: =IF(N(Z51)>=$E51*1000,"",IF(AND($E51>0,AU51>=$E51*1000),"G",IF(Z$2<=TODAY(),"R",""))) | AW51: =AU51-IF(AV51="G",$E51*1000,0)+N(AA51) -> 0 | AX51: =IF(N(AD51)>=$E51*1000,"",IF(AND($E51>0,AW51>=$E51*1000),"G",IF(AD$2<=TODAY(),"R",""))) | AY51: =AW51-IF(AX51="G",$E51*1000,0)+N(AE51) -> 0
B52: =ROW()-3 -> 49 | C52: Aminul Hoque | D52: ='Member Wise Deposit Summary'!D52 -> 0097433390829 | E52: 1 | F52: =$E52*1000 -> 1000 | J52: =$E52*1000 -> 1000 | N52: =$E52*1000 -> 1000 | R52: =$E52*1000 -> 1000 | V52: =$E52*1000 -> 1000 | Z52: =$E52*1000 -> 1000 | AD52: =$E52*1000 -> 1000 | AH52: =F52+G52+H52+J52+K52+L52+N52+O52+P52+R52+S52+T52+V52+W52+X52+Z52+AA52+AB52+AD52+AE52+AF52 -> 7000 | AI52: =I52+M52+Q52+U52+Y52+AC52+AG52 -> 0 | AK52: 0 | AL52: =IF(N(F52)>=$E52*1000,"",IF(AND($E52>0,AK52>=$E52*1000),"G",IF(F$2<=TODAY(),"R",""))) | AM52: =AK52-IF(AL52="G",$E52*1000,0)+N(G52) -> 0 | AN52: =IF(N(J52)>=$E52*1000,"",IF(AND($E52>0,AM52>=$E52*1000),"G",IF(J$2<=TODAY(),"R",""))) | AO52: =AM52-IF(AN52="G",$E52*1000,0)+N(K52) -> 0 | AP52: =IF(N(N52)>=$E52*1000,"",IF(AND($E52>0,AO52>=$E52*1000),"G",IF(N$2<=TODAY(),"R",""))) | AQ52: =AO52-IF(AP52="G",$E52*1000,0)+N(O52) -> 0 | AR52: =IF(N(R52)>=$E52*1000,"",IF(AND($E52>0,AQ52>=$E52*1000),"G",IF(R$2<=TODAY(),"R",""))) | AS52: =AQ52-IF(AR52="G",$E52*1000,0)+N(S52) -> 0 | AT52: =IF(N(V52)>=$E52*1000,"",IF(AND($E52>0,AS52>=$E52*1000),"G",IF(V$2<=TODAY(),"R",""))) | AU52: =AS52-IF(AT52="G",$E52*1000,0)+N(W52) -> 0 | AV52: =IF(N(Z52)>=$E52*1000,"",IF(AND($E52>0,AU52>=$E52*1000),"G",IF(Z$2<=TODAY(),"R",""))) | AW52: =AU52-IF(AV52="G",$E52*1000,0)+N(AA52) -> 0 | AX52: =IF(N(AD52)>=$E52*1000,"",IF(AND($E52>0,AW52>=$E52*1000),"G",IF(AD$2<=TODAY(),"R",""))) | AY52: =AW52-IF(AX52="G",$E52*1000,0)+N(AE52) -> 0
B53: =ROW()-3 -> 50 | C53: Shekh Ahmed Roki | D53: ='Member Wise Deposit Summary'!D53 -> 1829921642 | E53: 1 | F53: =$E53*1000 -> 1000 | J53: =$E53*1000 -> 1000 | N53: =$E53*1000 -> 1000 | R53: =$E53*1000 -> 1000 | V53: =$E53*1000 -> 1000 | Z53: =$E53*1000 -> 1000 | AD53: =$E53*1000 -> 1000 | AH53: =F53+G53+H53+J53+K53+L53+N53+O53+P53+R53+S53+T53+V53+W53+X53+Z53+AA53+AB53+AD53+AE53+AF53 -> 7000 | AI53: =I53+M53+Q53+U53+Y53+AC53+AG53 -> 0 | AK53: 0 | AL53: =IF(N(F53)>=$E53*1000,"",IF(AND($E53>0,AK53>=$E53*1000),"G",IF(F$2<=TODAY(),"R",""))) | AM53: =AK53-IF(AL53="G",$E53*1000,0)+N(G53) -> 0 | AN53: =IF(N(J53)>=$E53*1000,"",IF(AND($E53>0,AM53>=$E53*1000),"G",IF(J$2<=TODAY(),"R",""))) | AO53: =AM53-IF(AN53="G",$E53*1000,0)+N(K53) -> 0 | AP53: =IF(N(N53)>=$E53*1000,"",IF(AND($E53>0,AO53>=$E53*1000),"G",IF(N$2<=TODAY(),"R",""))) | AQ53: =AO53-IF(AP53="G",$E53*1000,0)+N(O53) -> 0 | AR53: =IF(N(R53)>=$E53*1000,"",IF(AND($E53>0,AQ53>=$E53*1000),"G",IF(R$2<=TODAY(),"R",""))) | AS53: =AQ53-IF(AR53="G",$E53*1000,0)+N(S53) -> 0 | AT53: =IF(N(V53)>=$E53*1000,"",IF(AND($E53>0,AS53>=$E53*1000),"G",IF(V$2<=TODAY(),"R",""))) | AU53: =AS53-IF(AT53="G",$E53*1000,0)+N(W53) -> 0 | AV53: =IF(N(Z53)>=$E53*1000,"",IF(AND($E53>0,AU53>=$E53*1000),"G",IF(Z$2<=TODAY(),"R",""))) | AW53: =AU53-IF(AV53="G",$E53*1000,0)+N(AA53) -> 0 | AX53: =IF(N(AD53)>=$E53*1000,"",IF(AND($E53>0,AW53>=$E53*1000),"G",IF(AD$2<=TODAY(),"R",""))) | AY53: =AW53-IF(AX53="G",$E53*1000,0)+N(AE53) -> 0
B54: =ROW()-3 -> 51 | C54: Md. Sahjahan | D54: ='Member Wise Deposit Summary'!D54 -> 1889786926 | E54: 3 | F54: =$E54*1000 -> 3000 | J54: =$E54*1000 -> 3000 | N54: =$E54*1000 -> 3000 | R54: =$E54*1000 -> 3000 | V54: =$E54*1000 -> 3000 | Z54: =$E54*1000 -> 3000 | AD54: =$E54*1000 -> 3000 | AH54: =F54+G54+H54+J54+K54+L54+N54+O54+P54+R54+S54+T54+V54+W54+X54+Z54+AA54+AB54+AD54+AE54+AF54 -> 21000 | AI54: =I54+M54+Q54+U54+Y54+AC54+AG54 -> 0 | AK54: 0 | AL54: =IF(N(F54)>=$E54*1000,"",IF(AND($E54>0,AK54>=$E54*1000),"G",IF(F$2<=TODAY(),"R",""))) | AM54: =AK54-IF(AL54="G",$E54*1000,0)+N(G54) -> 0 | AN54: =IF(N(J54)>=$E54*1000,"",IF(AND($E54>0,AM54>=$E54*1000),"G",IF(J$2<=TODAY(),"R",""))) | AO54: =AM54-IF(AN54="G",$E54*1000,0)+N(K54) -> 0 | AP54: =IF(N(N54)>=$E54*1000,"",IF(AND($E54>0,AO54>=$E54*1000),"G",IF(N$2<=TODAY(),"R",""))) | AQ54: =AO54-IF(AP54="G",$E54*1000,0)+N(O54) -> 0 | AR54: =IF(N(R54)>=$E54*1000,"",IF(AND($E54>0,AQ54>=$E54*1000),"G",IF(R$2<=TODAY(),"R",""))) | AS54: =AQ54-IF(AR54="G",$E54*1000,0)+N(S54) -> 0 | AT54: =IF(N(V54)>=$E54*1000,"",IF(AND($E54>0,AS54>=$E54*1000),"G",IF(V$2<=TODAY(),"R",""))) | AU54: =AS54-IF(AT54="G",$E54*1000,0)+N(W54) -> 0 | AV54: =IF(N(Z54)>=$E54*1000,"",IF(AND($E54>0,AU54>=$E54*1000),"G",IF(Z$2<=TODAY(),"R",""))) | AW54: =AU54-IF(AV54="G",$E54*1000,0)+N(AA54) -> 0 | AX54: =IF(N(AD54)>=$E54*1000,"",IF(AND($E54>0,AW54>=$E54*1000),"G",IF(AD$2<=TODAY(),"R",""))) | AY54: =AW54-IF(AX54="G",$E54*1000,0)+N(AE54) -> 0
B55: =ROW()-3 -> 52 | C55: Babul Hossen | D55: ='Member Wise Deposit Summary'!D55 -> 1833903155 | E55: 1 | F55: =$E55*1000 -> 1000 | J55: =$E55*1000 -> 1000 | N55: =$E55*1000 -> 1000 | R55: =$E55*1000 -> 1000 | V55: =$E55*1000 -> 1000 | Z55: =$E55*1000 -> 1000 | AD55: =$E55*1000 -> 1000 | AH55: =F55+G55+H55+J55+K55+L55+N55+O55+P55+R55+S55+T55+V55+W55+X55+Z55+AA55+AB55+AD55+AE55+AF55 -> 7000 | AI55: =I55+M55+Q55+U55+Y55+AC55+AG55 -> 0 | AK55: 0 | AL55: =IF(N(F55)>=$E55*1000,"",IF(AND($E55>0,AK55>=$E55*1000),"G",IF(F$2<=TODAY(),"R",""))) | AM55: =AK55-IF(AL55="G",$E55*1000,0)+N(G55) -> 0 | AN55: =IF(N(J55)>=$E55*1000,"",IF(AND($E55>0,AM55>=$E55*1000),"G",IF(J$2<=TODAY(),"R",""))) | AO55: =AM55-IF(AN55="G",$E55*1000,0)+N(K55) -> 0 | AP55: =IF(N(N55)>=$E55*1000,"",IF(AND($E55>0,AO55>=$E55*1000),"G",IF(N$2<=TODAY(),"R",""))) | AQ55: =AO55-IF(AP55="G",$E55*1000,0)+N(O55) -> 0 | AR55: =IF(N(R55)>=$E55*1000,"",IF(AND($E55>0,AQ55>=$E55*1000),"G",IF(R$2<=TODAY(),"R",""))) | AS55: =AQ55-IF(AR55="G",$E55*1000,0)+N(S55) -> 0 | AT55: =IF(N(V55)>=$E55*1000,"",IF(AND($E55>0,AS55>=$E55*1000),"G",IF(V$2<=TODAY(),"R",""))) | AU55: =AS55-IF(AT55="G",$E55*1000,0)+N(W55) -> 0 | AV55: =IF(N(Z55)>=$E55*1000,"",IF(AND($E55>0,AU55>=$E55*1000),"G",IF(Z$2<=TODAY(),"R",""))) | AW55: =AU55-IF(AV55="G",$E55*1000,0)+N(AA55) -> 0 | AX55: =IF(N(AD55)>=$E55*1000,"",IF(AND($E55>0,AW55>=$E55*1000),"G",IF(AD$2<=TODAY(),"R",""))) | AY55: =AW55-IF(AX55="G",$E55*1000,0)+N(AE55) -> 0
B56: =ROW()-3 -> 53 | C56: Khair Ahmed | D56: ='Member Wise Deposit Summary'!D56 -> 1897045177 | E56: 1 | F56: =$E56*1000 -> 1000 | J56: =$E56*1000 -> 1000 | N56: =$E56*1000 -> 1000 | R56: =$E56*1000 -> 1000 | V56: =$E56*1000 -> 1000 | Z56: =$E56*1000 -> 1000 | AD56: =$E56*1000 -> 1000 | AH56: =F56+G56+H56+J56+K56+L56+N56+O56+P56+R56+S56+T56+V56+W56+X56+Z56+AA56+AB56+AD56+AE56+AF56 -> 7000 | AI56: =I56+M56+Q56+U56+Y56+AC56+AG56 -> 0 | AK56: 0 | AL56: =IF(N(F56)>=$E56*1000,"",IF(AND($E56>0,AK56>=$E56*1000),"G",IF(F$2<=TODAY(),"R",""))) | AM56: =AK56-IF(AL56="G",$E56*1000,0)+N(G56) -> 0 | AN56: =IF(N(J56)>=$E56*1000,"",IF(AND($E56>0,AM56>=$E56*1000),"G",IF(J$2<=TODAY(),"R",""))) | AO56: =AM56-IF(AN56="G",$E56*1000,0)+N(K56) -> 0 | AP56: =IF(N(N56)>=$E56*1000,"",IF(AND($E56>0,AO56>=$E56*1000),"G",IF(N$2<=TODAY(),"R",""))) | AQ56: =AO56-IF(AP56="G",$E56*1000,0)+N(O56) -> 0 | AR56: =IF(N(R56)>=$E56*1000,"",IF(AND($E56>0,AQ56>=$E56*1000),"G",IF(R$2<=TODAY(),"R",""))) | AS56: =AQ56-IF(AR56="G",$E56*1000,0)+N(S56) -> 0 | AT56: =IF(N(V56)>=$E56*1000,"",IF(AND($E56>0,AS56>=$E56*1000),"G",IF(V$2<=TODAY(),"R",""))) | AU56: =AS56-IF(AT56="G",$E56*1000,0)+N(W56) -> 0 | AV56: =IF(N(Z56)>=$E56*1000,"",IF(AND($E56>0,AU56>=$E56*1000),"G",IF(Z$2<=TODAY(),"R",""))) | AW56: =AU56-IF(AV56="G",$E56*1000,0)+N(AA56) -> 0 | AX56: =IF(N(AD56)>=$E56*1000,"",IF(AND($E56>0,AW56>=$E56*1000),"G",IF(AD$2<=TODAY(),"R",""))) | AY56: =AW56-IF(AX56="G",$E56*1000,0)+N(AE56) -> 0
B57: =ROW()-3 -> 54 | C57: Md. Lutfar Rahman | D57: ='Member Wise Deposit Summary'!D57 -> 00966564847790 | E57: 1 | F57: =$E57*1000 -> 1000 | J57: =$E57*1000 -> 1000 | N57: =$E57*1000 -> 1000 | R57: =$E57*1000 -> 1000 | V57: =$E57*1000 -> 1000 | Z57: =$E57*1000 -> 1000 | AD57: =$E57*1000 -> 1000 | AH57: =F57+G57+H57+J57+K57+L57+N57+O57+P57+R57+S57+T57+V57+W57+X57+Z57+AA57+AB57+AD57+AE57+AF57 -> 7000 | AI57: =I57+M57+Q57+U57+Y57+AC57+AG57 -> 0 | AK57: 0 | AL57: =IF(N(F57)>=$E57*1000,"",IF(AND($E57>0,AK57>=$E57*1000),"G",IF(F$2<=TODAY(),"R",""))) | AM57: =AK57-IF(AL57="G",$E57*1000,0)+N(G57) -> 0 | AN57: =IF(N(J57)>=$E57*1000,"",IF(AND($E57>0,AM57>=$E57*1000),"G",IF(J$2<=TODAY(),"R",""))) | AO57: =AM57-IF(AN57="G",$E57*1000,0)+N(K57) -> 0 | AP57: =IF(N(N57)>=$E57*1000,"",IF(AND($E57>0,AO57>=$E57*1000),"G",IF(N$2<=TODAY(),"R",""))) | AQ57: =AO57-IF(AP57="G",$E57*1000,0)+N(O57) -> 0 | AR57: =IF(N(R57)>=$E57*1000,"",IF(AND($E57>0,AQ57>=$E57*1000),"G",IF(R$2<=TODAY(),"R",""))) | AS57: =AQ57-IF(AR57="G",$E57*1000,0)+N(S57) -> 0 | AT57: =IF(N(V57)>=$E57*1000,"",IF(AND($E57>0,AS57>=$E57*1000),"G",IF(V$2<=TODAY(),"R",""))) | AU57: =AS57-IF(AT57="G",$E57*1000,0)+N(W57) -> 0 | AV57: =IF(N(Z57)>=$E57*1000,"",IF(AND($E57>0,AU57>=$E57*1000),"G",IF(Z$2<=TODAY(),"R",""))) | AW57: =AU57-IF(AV57="G",$E57*1000,0)+N(AA57) -> 0 | AX57: =IF(N(AD57)>=$E57*1000,"",IF(AND($E57>0,AW57>=$E57*1000),"G",IF(AD$2<=TODAY(),"R",""))) | AY57: =AW57-IF(AX57="G",$E57*1000,0)+N(AE57) -> 0
B58: =ROW()-3 -> 55 | C58: Abu Bakker | D58: ='Member Wise Deposit Summary'!D58 -> 00971559969326 | E58: 2 | F58: =$E58*1000 -> 2000 | J58: =$E58*1000 -> 2000 | N58: =$E58*1000 -> 2000 | Q58: 50 | R58: =$E58*1000 -> 2000 | AH58: =F58+G58+H58+J58+K58+L58+N58+O58+P58+R58+S58+T58+V58+W58+X58+Z58+AA58+AB58+AD58+AE58+AF58 -> 8000 | AI58: =I58+M58+Q58+U58+Y58+AC58+AG58 -> 50 | AK58: 0 | AL58: =IF(N(F58)>=$E58*1000,"",IF(AND($E58>0,AK58>=$E58*1000),"G",IF(F$2<=TODAY(),"R",""))) | AM58: =AK58-IF(AL58="G",$E58*1000,0)+N(G58) -> 0 | AN58: =IF(N(J58)>=$E58*1000,"",IF(AND($E58>0,AM58>=$E58*1000),"G",IF(J$2<=TODAY(),"R",""))) | AO58: =AM58-IF(AN58="G",$E58*1000,0)+N(K58) -> 0 | AP58: =IF(N(N58)>=$E58*1000,"",IF(AND($E58>0,AO58>=$E58*1000),"G",IF(N$2<=TODAY(),"R",""))) | AQ58: =AO58-IF(AP58="G",$E58*1000,0)+N(O58) -> 0 | AR58: =IF(N(R58)>=$E58*1000,"",IF(AND($E58>0,AQ58>=$E58*1000),"G",IF(R$2<=TODAY(),"R",""))) | AS58: =AQ58-IF(AR58="G",$E58*1000,0)+N(S58) -> 0 | AT58: =IF(N(V58)>=$E58*1000,"",IF(AND($E58>0,AS58>=$E58*1000),"G",IF(V$2<=TODAY(),"R",""))) -> R | AU58: =AS58-IF(AT58="G",$E58*1000,0)+N(W58) -> 0 | AV58: =IF(N(Z58)>=$E58*1000,"",IF(AND($E58>0,AU58>=$E58*1000),"G",IF(Z$2<=TODAY(),"R",""))) -> R | AW58: =AU58-IF(AV58="G",$E58*1000,0)+N(AA58) -> 0 | AX58: =IF(N(AD58)>=$E58*1000,"",IF(AND($E58>0,AW58>=$E58*1000),"G",IF(AD$2<=TODAY(),"R",""))) -> R | AY58: =AW58-IF(AX58="G",$E58*1000,0)+N(AE58) -> 0
B59: =ROW()-3 -> 56 | C59: Abdullah Al Mumid | D59: ='Member Wise Deposit Summary'!D59 -> 01585430658 | E59: 1 | F59: =$E59*1000 -> 1000 | J59: =$E59*1000 -> 1000 | N59: =$E59*1000 -> 1000 | R59: =$E59*1000 -> 1000 | V59: =$E59*1000 -> 1000 | Y59: 50 | Z59: =$E59*1000 -> 1000 | AD59: =$E59*1000 -> 1000 | AH59: =F59+G59+H59+J59+K59+L59+N59+O59+P59+R59+S59+T59+V59+W59+X59+Z59+AA59+AB59+AD59+AE59+AF59 -> 7000 | AI59: =I59+M59+Q59+U59+Y59+AC59+AG59 -> 50 | AK59: 0 | AL59: =IF(N(F59)>=$E59*1000,"",IF(AND($E59>0,AK59>=$E59*1000),"G",IF(F$2<=TODAY(),"R",""))) | AM59: =AK59-IF(AL59="G",$E59*1000,0)+N(G59) -> 0 | AN59: =IF(N(J59)>=$E59*1000,"",IF(AND($E59>0,AM59>=$E59*1000),"G",IF(J$2<=TODAY(),"R",""))) | AO59: =AM59-IF(AN59="G",$E59*1000,0)+N(K59) -> 0 | AP59: =IF(N(N59)>=$E59*1000,"",IF(AND($E59>0,AO59>=$E59*1000),"G",IF(N$2<=TODAY(),"R",""))) | AQ59: =AO59-IF(AP59="G",$E59*1000,0)+N(O59) -> 0 | AR59: =IF(N(R59)>=$E59*1000,"",IF(AND($E59>0,AQ59>=$E59*1000),"G",IF(R$2<=TODAY(),"R",""))) | AS59: =AQ59-IF(AR59="G",$E59*1000,0)+N(S59) -> 0 | AT59: =IF(N(V59)>=$E59*1000,"",IF(AND($E59>0,AS59>=$E59*1000),"G",IF(V$2<=TODAY(),"R",""))) | AU59: =AS59-IF(AT59="G",$E59*1000,0)+N(W59) -> 0 | AV59: =IF(N(Z59)>=$E59*1000,"",IF(AND($E59>0,AU59>=$E59*1000),"G",IF(Z$2<=TODAY(),"R",""))) | AW59: =AU59-IF(AV59="G",$E59*1000,0)+N(AA59) -> 0 | AX59: =IF(N(AD59)>=$E59*1000,"",IF(AND($E59>0,AW59>=$E59*1000),"G",IF(AD$2<=TODAY(),"R",""))) | AY59: =AW59-IF(AX59="G",$E59*1000,0)+N(AE59) -> 0
B60: =ROW()-3 -> 57 | C60: Sujan Kanti Karmaker | D60: ='Member Wise Deposit Summary'!D60 -> 01814785317 | E60: 1 | F60: =$E60*1000 -> 1000 | J60: =$E60*1000 -> 1000 | N60: =$E60*1000 -> 1000 | R60: =$E60*1000 -> 1000 | V60: =$E60*1000 -> 1000 | Z60: =$E60*1000 -> 1000 | AD60: =$E60*1000 -> 1000 | AH60: =F60+G60+H60+J60+K60+L60+N60+O60+P60+R60+S60+T60+V60+W60+X60+Z60+AA60+AB60+AD60+AE60+AF60 -> 7000 | AI60: =I60+M60+Q60+U60+Y60+AC60+AG60 -> 0 | AK60: 0 | AL60: =IF(N(F60)>=$E60*1000,"",IF(AND($E60>0,AK60>=$E60*1000),"G",IF(F$2<=TODAY(),"R",""))) | AM60: =AK60-IF(AL60="G",$E60*1000,0)+N(G60) -> 0 | AN60: =IF(N(J60)>=$E60*1000,"",IF(AND($E60>0,AM60>=$E60*1000),"G",IF(J$2<=TODAY(),"R",""))) | AO60: =AM60-IF(AN60="G",$E60*1000,0)+N(K60) -> 0 | AP60: =IF(N(N60)>=$E60*1000,"",IF(AND($E60>0,AO60>=$E60*1000),"G",IF(N$2<=TODAY(),"R",""))) | AQ60: =AO60-IF(AP60="G",$E60*1000,0)+N(O60) -> 0 | AR60: =IF(N(R60)>=$E60*1000,"",IF(AND($E60>0,AQ60>=$E60*1000),"G",IF(R$2<=TODAY(),"R",""))) | AS60: =AQ60-IF(AR60="G",$E60*1000,0)+N(S60) -> 0 | AT60: =IF(N(V60)>=$E60*1000,"",IF(AND($E60>0,AS60>=$E60*1000),"G",IF(V$2<=TODAY(),"R",""))) | AU60: =AS60-IF(AT60="G",$E60*1000,0)+N(W60) -> 0 | AV60: =IF(N(Z60)>=$E60*1000,"",IF(AND($E60>0,AU60>=$E60*1000),"G",IF(Z$2<=TODAY(),"R",""))) | AW60: =AU60-IF(AV60="G",$E60*1000,0)+N(AA60) -> 0 | AX60: =IF(N(AD60)>=$E60*1000,"",IF(AND($E60>0,AW60>=$E60*1000),"G",IF(AD$2<=TODAY(),"R",""))) | AY60: =AW60-IF(AX60="G",$E60*1000,0)+N(AE60) -> 0
B61: =ROW()-3 -> 58 | C61: Prokash Kanti Nath | D61: ='Member Wise Deposit Summary'!D61 -> 01728125764 | E61: 1 | F61: =$E61*1000 -> 1000 | J61: =$E61*1000 -> 1000 | N61: =$E61*1000 -> 1000 | R61: =$E61*1000 -> 1000 | V61: =$E61*1000 -> 1000 | Z61: =$E61*1000 -> 1000 | AD61: =$E61*1000 -> 1000 | AH61: =F61+G61+H61+J61+K61+L61+N61+O61+P61+R61+S61+T61+V61+W61+X61+Z61+AA61+AB61+AD61+AE61+AF61 -> 7000 | AI61: =I61+M61+Q61+U61+Y61+AC61+AG61 -> 0 | AK61: 0 | AL61: =IF(N(F61)>=$E61*1000,"",IF(AND($E61>0,AK61>=$E61*1000),"G",IF(F$2<=TODAY(),"R",""))) | AM61: =AK61-IF(AL61="G",$E61*1000,0)+N(G61) -> 0 | AN61: =IF(N(J61)>=$E61*1000,"",IF(AND($E61>0,AM61>=$E61*1000),"G",IF(J$2<=TODAY(),"R",""))) | AO61: =AM61-IF(AN61="G",$E61*1000,0)+N(K61) -> 0 | AP61: =IF(N(N61)>=$E61*1000,"",IF(AND($E61>0,AO61>=$E61*1000),"G",IF(N$2<=TODAY(),"R",""))) | AQ61: =AO61-IF(AP61="G",$E61*1000,0)+N(O61) -> 0 | AR61: =IF(N(R61)>=$E61*1000,"",IF(AND($E61>0,AQ61>=$E61*1000),"G",IF(R$2<=TODAY(),"R",""))) | AS61: =AQ61-IF(AR61="G",$E61*1000,0)+N(S61) -> 0 | AT61: =IF(N(V61)>=$E61*1000,"",IF(AND($E61>0,AS61>=$E61*1000),"G",IF(V$2<=TODAY(),"R",""))) | AU61: =AS61-IF(AT61="G",$E61*1000,0)+N(W61) -> 0 | AV61: =IF(N(Z61)>=$E61*1000,"",IF(AND($E61>0,AU61>=$E61*1000),"G",IF(Z$2<=TODAY(),"R",""))) | AW61: =AU61-IF(AV61="G",$E61*1000,0)+N(AA61) -> 0 | AX61: =IF(N(AD61)>=$E61*1000,"",IF(AND($E61>0,AW61>=$E61*1000),"G",IF(AD$2<=TODAY(),"R",""))) | AY61: =AW61-IF(AX61="G",$E61*1000,0)+N(AE61) -> 0
B62: =ROW()-3 -> 59 | C62: Abdul Sabur | D62: ='Member Wise Deposit Summary'!D62 -> 1817246488 | E62: 1 | F62: =$E62*1000 -> 1000 | J62: =$E62*1000 -> 1000 | N62: =$E62*1000 -> 1000 | R62: =$E62*1000 -> 1000 | V62: =$E62*1000 -> 1000 | Z62: =$E62*1000 -> 1000 | AD62: =$E62*1000 -> 1000 | AH62: =F62+G62+H62+J62+K62+L62+N62+O62+P62+R62+S62+T62+V62+W62+X62+Z62+AA62+AB62+AD62+AE62+AF62 -> 7000 | AI62: =I62+M62+Q62+U62+Y62+AC62+AG62 -> 0 | AK62: 0 | AL62: =IF(N(F62)>=$E62*1000,"",IF(AND($E62>0,AK62>=$E62*1000),"G",IF(F$2<=TODAY(),"R",""))) | AM62: =AK62-IF(AL62="G",$E62*1000,0)+N(G62) -> 0 | AN62: =IF(N(J62)>=$E62*1000,"",IF(AND($E62>0,AM62>=$E62*1000),"G",IF(J$2<=TODAY(),"R",""))) | AO62: =AM62-IF(AN62="G",$E62*1000,0)+N(K62) -> 0 | AP62: =IF(N(N62)>=$E62*1000,"",IF(AND($E62>0,AO62>=$E62*1000),"G",IF(N$2<=TODAY(),"R",""))) | AQ62: =AO62-IF(AP62="G",$E62*1000,0)+N(O62) -> 0 | AR62: =IF(N(R62)>=$E62*1000,"",IF(AND($E62>0,AQ62>=$E62*1000),"G",IF(R$2<=TODAY(),"R",""))) | AS62: =AQ62-IF(AR62="G",$E62*1000,0)+N(S62) -> 0 | AT62: =IF(N(V62)>=$E62*1000,"",IF(AND($E62>0,AS62>=$E62*1000),"G",IF(V$2<=TODAY(),"R",""))) | AU62: =AS62-IF(AT62="G",$E62*1000,0)+N(W62) -> 0 | AV62: =IF(N(Z62)>=$E62*1000,"",IF(AND($E62>0,AU62>=$E62*1000),"G",IF(Z$2<=TODAY(),"R",""))) | AW62: =AU62-IF(AV62="G",$E62*1000,0)+N(AA62) -> 0 | AX62: =IF(N(AD62)>=$E62*1000,"",IF(AND($E62>0,AW62>=$E62*1000),"G",IF(AD$2<=TODAY(),"R",""))) | AY62: =AW62-IF(AX62="G",$E62*1000,0)+N(AE62) -> 0
B63: =ROW()-3 -> 60 | C63: Ridowanul Hoque | D63: ='Member Wise Deposit Summary'!D63 -> 1866911987 | E63: 2 | F63: =$E63*1000 -> 2000 | J63: =$E63*1000 -> 2000 | N63: =$E63*1000 -> 2000 | R63: =$E63*1000 -> 2000 | U63: 100 | V63: =$E63*1000 -> 2000 | Z63: =$E63*1000 -> 2000 | AD63: =$E63*1000 -> 2000 | AH63: =F63+G63+H63+J63+K63+L63+N63+O63+P63+R63+S63+T63+V63+W63+X63+Z63+AA63+AB63+AD63+AE63+AF63 -> 14000 | AI63: =I63+M63+Q63+U63+Y63+AC63+AG63 -> 100 | AK63: 0 | AL63: =IF(N(F63)>=$E63*1000,"",IF(AND($E63>0,AK63>=$E63*1000),"G",IF(F$2<=TODAY(),"R",""))) | AM63: =AK63-IF(AL63="G",$E63*1000,0)+N(G63) -> 0 | AN63: =IF(N(J63)>=$E63*1000,"",IF(AND($E63>0,AM63>=$E63*1000),"G",IF(J$2<=TODAY(),"R",""))) | AO63: =AM63-IF(AN63="G",$E63*1000,0)+N(K63) -> 0 | AP63: =IF(N(N63)>=$E63*1000,"",IF(AND($E63>0,AO63>=$E63*1000),"G",IF(N$2<=TODAY(),"R",""))) | AQ63: =AO63-IF(AP63="G",$E63*1000,0)+N(O63) -> 0 | AR63: =IF(N(R63)>=$E63*1000,"",IF(AND($E63>0,AQ63>=$E63*1000),"G",IF(R$2<=TODAY(),"R",""))) | AS63: =AQ63-IF(AR63="G",$E63*1000,0)+N(S63) -> 0 | AT63: =IF(N(V63)>=$E63*1000,"",IF(AND($E63>0,AS63>=$E63*1000),"G",IF(V$2<=TODAY(),"R",""))) | AU63: =AS63-IF(AT63="G",$E63*1000,0)+N(W63) -> 0 | AV63: =IF(N(Z63)>=$E63*1000,"",IF(AND($E63>0,AU63>=$E63*1000),"G",IF(Z$2<=TODAY(),"R",""))) | AW63: =AU63-IF(AV63="G",$E63*1000,0)+N(AA63) -> 0 | AX63: =IF(N(AD63)>=$E63*1000,"",IF(AND($E63>0,AW63>=$E63*1000),"G",IF(AD$2<=TODAY(),"R",""))) | AY63: =AW63-IF(AX63="G",$E63*1000,0)+N(AE63) -> 0
B64: =ROW()-3 -> 61 | C64: Mohammad Toyab | D64: ='Member Wise Deposit Summary'!D64 -> 1817504865 | E64: 1 | F64: =$E64*1000 -> 1000 | J64: =$E64*1000 -> 1000 | N64: =$E64*1000 -> 1000 | R64: =$E64*1000 -> 1000 | V64: =$E64*1000 -> 1000 | Z64: =$E64*1000 -> 1000 | AD64: =$E64*1000 -> 1000 | AH64: =F64+G64+H64+J64+K64+L64+N64+O64+P64+R64+S64+T64+V64+W64+X64+Z64+AA64+AB64+AD64+AE64+AF64 -> 7000 | AI64: =I64+M64+Q64+U64+Y64+AC64+AG64 -> 0 | AK64: 0 | AL64: =IF(N(F64)>=$E64*1000,"",IF(AND($E64>0,AK64>=$E64*1000),"G",IF(F$2<=TODAY(),"R",""))) | AM64: =AK64-IF(AL64="G",$E64*1000,0)+N(G64) -> 0 | AN64: =IF(N(J64)>=$E64*1000,"",IF(AND($E64>0,AM64>=$E64*1000),"G",IF(J$2<=TODAY(),"R",""))) | AO64: =AM64-IF(AN64="G",$E64*1000,0)+N(K64) -> 0 | AP64: =IF(N(N64)>=$E64*1000,"",IF(AND($E64>0,AO64>=$E64*1000),"G",IF(N$2<=TODAY(),"R",""))) | AQ64: =AO64-IF(AP64="G",$E64*1000,0)+N(O64) -> 0 | AR64: =IF(N(R64)>=$E64*1000,"",IF(AND($E64>0,AQ64>=$E64*1000),"G",IF(R$2<=TODAY(),"R",""))) | AS64: =AQ64-IF(AR64="G",$E64*1000,0)+N(S64) -> 0 | AT64: =IF(N(V64)>=$E64*1000,"",IF(AND($E64>0,AS64>=$E64*1000),"G",IF(V$2<=TODAY(),"R",""))) | AU64: =AS64-IF(AT64="G",$E64*1000,0)+N(W64) -> 0 | AV64: =IF(N(Z64)>=$E64*1000,"",IF(AND($E64>0,AU64>=$E64*1000),"G",IF(Z$2<=TODAY(),"R",""))) | AW64: =AU64-IF(AV64="G",$E64*1000,0)+N(AA64) -> 0 | AX64: =IF(N(AD64)>=$E64*1000,"",IF(AND($E64>0,AW64>=$E64*1000),"G",IF(AD$2<=TODAY(),"R",""))) | AY64: =AW64-IF(AX64="G",$E64*1000,0)+N(AE64) -> 0
B65: =ROW()-3 -> 62 | C65: Nurul Amin | D65: ='Member Wise Deposit Summary'!D65 -> 1885316318 | E65: 1 | F65: =$E65*1000 -> 1000 | J65: =$E65*1000 -> 1000 | R65: =$E65*1000 -> 1000 | T65: 1000 | U65: 50 | Z65: =$E65*1000 -> 1000 | AB65: 1000 | AC65: 50 | AD65: =$E65*1000 -> 1000 | AH65: =F65+G65+H65+J65+K65+L65+N65+O65+P65+R65+S65+T65+V65+W65+X65+Z65+AA65+AB65+AD65+AE65+AF65 -> 7000 | AI65: =I65+M65+Q65+U65+Y65+AC65+AG65 -> 100 | AK65: 0 | AL65: =IF(N(F65)>=$E65*1000,"",IF(AND($E65>0,AK65>=$E65*1000),"G",IF(F$2<=TODAY(),"R",""))) | AM65: =AK65-IF(AL65="G",$E65*1000,0)+N(G65) -> 0 | AN65: =IF(N(J65)>=$E65*1000,"",IF(AND($E65>0,AM65>=$E65*1000),"G",IF(J$2<=TODAY(),"R",""))) | AO65: =AM65-IF(AN65="G",$E65*1000,0)+N(K65) -> 0 | AP65: =IF(N(N65)>=$E65*1000,"",IF(AND($E65>0,AO65>=$E65*1000),"G",IF(N$2<=TODAY(),"R",""))) -> R | AQ65: =AO65-IF(AP65="G",$E65*1000,0)+N(O65) -> 0 | AR65: =IF(N(R65)>=$E65*1000,"",IF(AND($E65>0,AQ65>=$E65*1000),"G",IF(R$2<=TODAY(),"R",""))) | AS65: =AQ65-IF(AR65="G",$E65*1000,0)+N(S65) -> 0 | AT65: =IF(N(V65)>=$E65*1000,"",IF(AND($E65>0,AS65>=$E65*1000),"G",IF(V$2<=TODAY(),"R",""))) -> R | AU65: =AS65-IF(AT65="G",$E65*1000,0)+N(W65) -> 0 | AV65: =IF(N(Z65)>=$E65*1000,"",IF(AND($E65>0,AU65>=$E65*1000),"G",IF(Z$2<=TODAY(),"R",""))) | AW65: =AU65-IF(AV65="G",$E65*1000,0)+N(AA65) -> 0 | AX65: =IF(N(AD65)>=$E65*1000,"",IF(AND($E65>0,AW65>=$E65*1000),"G",IF(AD$2<=TODAY(),"R",""))) | AY65: =AW65-IF(AX65="G",$E65*1000,0)+N(AE65) -> 0
B66: =ROW()-3 -> 63 | C66: Joy Sankar Karmaker | D66: ='Member Wise Deposit Summary'!D66 -> 1827204517 | E66: 1 | F66: =$E66*1000 -> 1000 | J66: =$E66*1000 -> 1000 | N66: =$E66*1000 -> 1000 | V66: =$E66*1000 -> 1000 | X66: 1000 | Y66: 50 | Z66: =$E66*1000 -> 1000 | AD66: =$E66*1000 -> 1000 | AH66: =F66+G66+H66+J66+K66+L66+N66+O66+P66+R66+S66+T66+V66+W66+X66+Z66+AA66+AB66+AD66+AE66+AF66 -> 7000 | AI66: =I66+M66+Q66+U66+Y66+AC66+AG66 -> 50 | AK66: 0 | AL66: =IF(N(F66)>=$E66*1000,"",IF(AND($E66>0,AK66>=$E66*1000),"G",IF(F$2<=TODAY(),"R",""))) | AM66: =AK66-IF(AL66="G",$E66*1000,0)+N(G66) -> 0 | AN66: =IF(N(J66)>=$E66*1000,"",IF(AND($E66>0,AM66>=$E66*1000),"G",IF(J$2<=TODAY(),"R",""))) | AO66: =AM66-IF(AN66="G",$E66*1000,0)+N(K66) -> 0 | AP66: =IF(N(N66)>=$E66*1000,"",IF(AND($E66>0,AO66>=$E66*1000),"G",IF(N$2<=TODAY(),"R",""))) | AQ66: =AO66-IF(AP66="G",$E66*1000,0)+N(O66) -> 0 | AR66: =IF(N(R66)>=$E66*1000,"",IF(AND($E66>0,AQ66>=$E66*1000),"G",IF(R$2<=TODAY(),"R",""))) -> R | AS66: =AQ66-IF(AR66="G",$E66*1000,0)+N(S66) -> 0 | AT66: =IF(N(V66)>=$E66*1000,"",IF(AND($E66>0,AS66>=$E66*1000),"G",IF(V$2<=TODAY(),"R",""))) | AU66: =AS66-IF(AT66="G",$E66*1000,0)+N(W66) -> 0 | AV66: =IF(N(Z66)>=$E66*1000,"",IF(AND($E66>0,AU66>=$E66*1000),"G",IF(Z$2<=TODAY(),"R",""))) | AW66: =AU66-IF(AV66="G",$E66*1000,0)+N(AA66) -> 0 | AX66: =IF(N(AD66)>=$E66*1000,"",IF(AND($E66>0,AW66>=$E66*1000),"G",IF(AD$2<=TODAY(),"R",""))) | AY66: =AW66-IF(AX66="G",$E66*1000,0)+N(AE66) -> 0
B67: =ROW()-3 -> 64 | C67: Mohammad Sahjahan | D67: ='Member Wise Deposit Summary'!D67 -> 00971557893251 | E67: 1 | F67: =$E67*1000 -> 1000 | J67: =$E67*1000 -> 1000 | N67: =$E67*1000 -> 1000 | R67: =$E67*1000 -> 1000 | V67: =$E67*1000 -> 1000 | Z67: =$E67*1000 -> 1000 | AD67: =$E67*1000 -> 1000 | AH67: =F67+G67+H67+J67+K67+L67+N67+O67+P67+R67+S67+T67+V67+W67+X67+Z67+AA67+AB67+AD67+AE67+AF67 -> 7000 | AI67: =I67+M67+Q67+U67+Y67+AC67+AG67 -> 0 | AK67: 0 | AL67: =IF(N(F67)>=$E67*1000,"",IF(AND($E67>0,AK67>=$E67*1000),"G",IF(F$2<=TODAY(),"R",""))) | AM67: =AK67-IF(AL67="G",$E67*1000,0)+N(G67) -> 0 | AN67: =IF(N(J67)>=$E67*1000,"",IF(AND($E67>0,AM67>=$E67*1000),"G",IF(J$2<=TODAY(),"R",""))) | AO67: =AM67-IF(AN67="G",$E67*1000,0)+N(K67) -> 0 | AP67: =IF(N(N67)>=$E67*1000,"",IF(AND($E67>0,AO67>=$E67*1000),"G",IF(N$2<=TODAY(),"R",""))) | AQ67: =AO67-IF(AP67="G",$E67*1000,0)+N(O67) -> 0 | AR67: =IF(N(R67)>=$E67*1000,"",IF(AND($E67>0,AQ67>=$E67*1000),"G",IF(R$2<=TODAY(),"R",""))) | AS67: =AQ67-IF(AR67="G",$E67*1000,0)+N(S67) -> 0 | AT67: =IF(N(V67)>=$E67*1000,"",IF(AND($E67>0,AS67>=$E67*1000),"G",IF(V$2<=TODAY(),"R",""))) | AU67: =AS67-IF(AT67="G",$E67*1000,0)+N(W67) -> 0 | AV67: =IF(N(Z67)>=$E67*1000,"",IF(AND($E67>0,AU67>=$E67*1000),"G",IF(Z$2<=TODAY(),"R",""))) | AW67: =AU67-IF(AV67="G",$E67*1000,0)+N(AA67) -> 0 | AX67: =IF(N(AD67)>=$E67*1000,"",IF(AND($E67>0,AW67>=$E67*1000),"G",IF(AD$2<=TODAY(),"R",""))) | AY67: =AW67-IF(AX67="G",$E67*1000,0)+N(AE67) -> 0
B68: =ROW()-3 -> 65 | C68: Akter Hossen | D68: ='Member Wise Deposit Summary'!D68 -> 1861821214 | E68: 1 | F68: =$E68*1000 -> 1000 | J68: =$E68*1000 -> 1000 | N68: =$E68*1000 -> 1000 | R68: =$E68*1000 -> 1000 | V68: =$E68*1000 -> 1000 | Z68: =$E68*1000 -> 1000 | AD68: =$E68*1000 -> 1000 | AH68: =F68+G68+H68+J68+K68+L68+N68+O68+P68+R68+S68+T68+V68+W68+X68+Z68+AA68+AB68+AD68+AE68+AF68 -> 7000 | AI68: =I68+M68+Q68+U68+Y68+AC68+AG68 -> 0 | AK68: 0 | AL68: =IF(N(F68)>=$E68*1000,"",IF(AND($E68>0,AK68>=$E68*1000),"G",IF(F$2<=TODAY(),"R",""))) | AM68: =AK68-IF(AL68="G",$E68*1000,0)+N(G68) -> 0 | AN68: =IF(N(J68)>=$E68*1000,"",IF(AND($E68>0,AM68>=$E68*1000),"G",IF(J$2<=TODAY(),"R",""))) | AO68: =AM68-IF(AN68="G",$E68*1000,0)+N(K68) -> 0 | AP68: =IF(N(N68)>=$E68*1000,"",IF(AND($E68>0,AO68>=$E68*1000),"G",IF(N$2<=TODAY(),"R",""))) | AQ68: =AO68-IF(AP68="G",$E68*1000,0)+N(O68) -> 0 | AR68: =IF(N(R68)>=$E68*1000,"",IF(AND($E68>0,AQ68>=$E68*1000),"G",IF(R$2<=TODAY(),"R",""))) | AS68: =AQ68-IF(AR68="G",$E68*1000,0)+N(S68) -> 0 | AT68: =IF(N(V68)>=$E68*1000,"",IF(AND($E68>0,AS68>=$E68*1000),"G",IF(V$2<=TODAY(),"R",""))) | AU68: =AS68-IF(AT68="G",$E68*1000,0)+N(W68) -> 0 | AV68: =IF(N(Z68)>=$E68*1000,"",IF(AND($E68>0,AU68>=$E68*1000),"G",IF(Z$2<=TODAY(),"R",""))) | AW68: =AU68-IF(AV68="G",$E68*1000,0)+N(AA68) -> 0 | AX68: =IF(N(AD68)>=$E68*1000,"",IF(AND($E68>0,AW68>=$E68*1000),"G",IF(AD$2<=TODAY(),"R",""))) | AY68: =AW68-IF(AX68="G",$E68*1000,0)+N(AE68) -> 0
B69: =ROW()-3 -> 66 | C69: Ehsanul Kabir | D69: ='Member Wise Deposit Summary'!D69 -> 00971557512381 | E69: 1 | F69: =$E69*1000 -> 1000 | J69: =$E69*1000 -> 1000 | N69: =$E69*1000 -> 1000 | R69: =$E69*1000 -> 1000 | V69: =$E69*1000 -> 1000 | Z69: =$E69*1000 -> 1000 | AD69: =$E69*1000 -> 1000 | AH69: =F69+G69+H69+J69+K69+L69+N69+O69+P69+R69+S69+T69+V69+W69+X69+Z69+AA69+AB69+AD69+AE69+AF69 -> 7000 | AI69: =I69+M69+Q69+U69+Y69+AC69+AG69 -> 0 | AK69: 0 | AL69: =IF(N(F69)>=$E69*1000,"",IF(AND($E69>0,AK69>=$E69*1000),"G",IF(F$2<=TODAY(),"R",""))) | AM69: =AK69-IF(AL69="G",$E69*1000,0)+N(G69) -> 0 | AN69: =IF(N(J69)>=$E69*1000,"",IF(AND($E69>0,AM69>=$E69*1000),"G",IF(J$2<=TODAY(),"R",""))) | AO69: =AM69-IF(AN69="G",$E69*1000,0)+N(K69) -> 0 | AP69: =IF(N(N69)>=$E69*1000,"",IF(AND($E69>0,AO69>=$E69*1000),"G",IF(N$2<=TODAY(),"R",""))) | AQ69: =AO69-IF(AP69="G",$E69*1000,0)+N(O69) -> 0 | AR69: =IF(N(R69)>=$E69*1000,"",IF(AND($E69>0,AQ69>=$E69*1000),"G",IF(R$2<=TODAY(),"R",""))) | AS69: =AQ69-IF(AR69="G",$E69*1000,0)+N(S69) -> 0 | AT69: =IF(N(V69)>=$E69*1000,"",IF(AND($E69>0,AS69>=$E69*1000),"G",IF(V$2<=TODAY(),"R",""))) | AU69: =AS69-IF(AT69="G",$E69*1000,0)+N(W69) -> 0 | AV69: =IF(N(Z69)>=$E69*1000,"",IF(AND($E69>0,AU69>=$E69*1000),"G",IF(Z$2<=TODAY(),"R",""))) | AW69: =AU69-IF(AV69="G",$E69*1000,0)+N(AA69) -> 0 | AX69: =IF(N(AD69)>=$E69*1000,"",IF(AND($E69>0,AW69>=$E69*1000),"G",IF(AD$2<=TODAY(),"R",""))) | AY69: =AW69-IF(AX69="G",$E69*1000,0)+N(AE69) -> 0
B70: =ROW()-3 -> 67 | C70: Mohammad Sayed Uddin Forhad | D70: ='Member Wise Deposit Summary'!D70 -> 971585735180 | E70: 1 | F70: =$E70*1000 -> 1000 | J70: =$E70*1000 -> 1000 | N70: =$E70*1000 -> 1000 | R70: =$E70*1000 -> 1000 | V70: =$E70*1000 -> 1000 | Z70: =$E70*1000 -> 1000 | AD70: =$E70*1000 -> 1000 | AH70: =F70+G70+H70+J70+K70+L70+N70+O70+P70+R70+S70+T70+V70+W70+X70+Z70+AA70+AB70+AD70+AE70+AF70 -> 7000 | AI70: =I70+M70+Q70+U70+Y70+AC70+AG70 -> 0 | AK70: 0 | AL70: =IF(N(F70)>=$E70*1000,"",IF(AND($E70>0,AK70>=$E70*1000),"G",IF(F$2<=TODAY(),"R",""))) | AM70: =AK70-IF(AL70="G",$E70*1000,0)+N(G70) -> 0 | AN70: =IF(N(J70)>=$E70*1000,"",IF(AND($E70>0,AM70>=$E70*1000),"G",IF(J$2<=TODAY(),"R",""))) | AO70: =AM70-IF(AN70="G",$E70*1000,0)+N(K70) -> 0 | AP70: =IF(N(N70)>=$E70*1000,"",IF(AND($E70>0,AO70>=$E70*1000),"G",IF(N$2<=TODAY(),"R",""))) | AQ70: =AO70-IF(AP70="G",$E70*1000,0)+N(O70) -> 0 | AR70: =IF(N(R70)>=$E70*1000,"",IF(AND($E70>0,AQ70>=$E70*1000),"G",IF(R$2<=TODAY(),"R",""))) | AS70: =AQ70-IF(AR70="G",$E70*1000,0)+N(S70) -> 0 | AT70: =IF(N(V70)>=$E70*1000,"",IF(AND($E70>0,AS70>=$E70*1000),"G",IF(V$2<=TODAY(),"R",""))) | AU70: =AS70-IF(AT70="G",$E70*1000,0)+N(W70) -> 0 | AV70: =IF(N(Z70)>=$E70*1000,"",IF(AND($E70>0,AU70>=$E70*1000),"G",IF(Z$2<=TODAY(),"R",""))) | AW70: =AU70-IF(AV70="G",$E70*1000,0)+N(AA70) -> 0 | AX70: =IF(N(AD70)>=$E70*1000,"",IF(AND($E70>0,AW70>=$E70*1000),"G",IF(AD$2<=TODAY(),"R",""))) | AY70: =AW70-IF(AX70="G",$E70*1000,0)+N(AE70) -> 0
B71: =ROW()-3 -> 68 | C71: Mohammad Ziabul Hoque | D71: ='Member Wise Deposit Summary'!D71 -> 971502927559 | E71: 1 | F71: =$E71*1000 -> 1000 | J71: =$E71*1000 -> 1000 | N71: =$E71*1000 -> 1000 | R71: =$E71*1000 -> 1000 | V71: =$E71*1000 -> 1000 | Z71: =$E71*1000 -> 1000 | AD71: =$E71*1000 -> 1000 | AH71: =F71+G71+H71+J71+K71+L71+N71+O71+P71+R71+S71+T71+V71+W71+X71+Z71+AA71+AB71+AD71+AE71+AF71 -> 7000 | AI71: =I71+M71+Q71+U71+Y71+AC71+AG71 -> 0 | AK71: 0 | AL71: =IF(N(F71)>=$E71*1000,"",IF(AND($E71>0,AK71>=$E71*1000),"G",IF(F$2<=TODAY(),"R",""))) | AM71: =AK71-IF(AL71="G",$E71*1000,0)+N(G71) -> 0 | AN71: =IF(N(J71)>=$E71*1000,"",IF(AND($E71>0,AM71>=$E71*1000),"G",IF(J$2<=TODAY(),"R",""))) | AO71: =AM71-IF(AN71="G",$E71*1000,0)+N(K71) -> 0 | AP71: =IF(N(N71)>=$E71*1000,"",IF(AND($E71>0,AO71>=$E71*1000),"G",IF(N$2<=TODAY(),"R",""))) | AQ71: =AO71-IF(AP71="G",$E71*1000,0)+N(O71) -> 0 | AR71: =IF(N(R71)>=$E71*1000,"",IF(AND($E71>0,AQ71>=$E71*1000),"G",IF(R$2<=TODAY(),"R",""))) | AS71: =AQ71-IF(AR71="G",$E71*1000,0)+N(S71) -> 0 | AT71: =IF(N(V71)>=$E71*1000,"",IF(AND($E71>0,AS71>=$E71*1000),"G",IF(V$2<=TODAY(),"R",""))) | AU71: =AS71-IF(AT71="G",$E71*1000,0)+N(W71) -> 0 | AV71: =IF(N(Z71)>=$E71*1000,"",IF(AND($E71>0,AU71>=$E71*1000),"G",IF(Z$2<=TODAY(),"R",""))) | AW71: =AU71-IF(AV71="G",$E71*1000,0)+N(AA71) -> 0 | AX71: =IF(N(AD71)>=$E71*1000,"",IF(AND($E71>0,AW71>=$E71*1000),"G",IF(AD$2<=TODAY(),"R",""))) | AY71: =AW71-IF(AX71="G",$E71*1000,0)+N(AE71) -> 0
B72: =ROW()-3 -> 69 | C72: Mohammad Yousof | D72: ='Member Wise Deposit Summary'!D72 -> 971561607784 | E72: 2 | F72: =$E72*1000 -> 2000 | J72: =$E72*1000 -> 2000 | N72: =$E72*1000 -> 2000 | R72: =$E72*1000 -> 2000 | V72: =$E72*1000 -> 2000 | Z72: =$E72*1000 -> 2000 | AD72: =$E72*1000 -> 2000 | AH72: =F72+G72+H72+J72+K72+L72+N72+O72+P72+R72+S72+T72+V72+W72+X72+Z72+AA72+AB72+AD72+AE72+AF72 -> 14000 | AI72: =I72+M72+Q72+U72+Y72+AC72+AG72 -> 0 | AK72: 0 | AL72: =IF(N(F72)>=$E72*1000,"",IF(AND($E72>0,AK72>=$E72*1000),"G",IF(F$2<=TODAY(),"R",""))) | AM72: =AK72-IF(AL72="G",$E72*1000,0)+N(G72) -> 0 | AN72: =IF(N(J72)>=$E72*1000,"",IF(AND($E72>0,AM72>=$E72*1000),"G",IF(J$2<=TODAY(),"R",""))) | AO72: =AM72-IF(AN72="G",$E72*1000,0)+N(K72) -> 0 | AP72: =IF(N(N72)>=$E72*1000,"",IF(AND($E72>0,AO72>=$E72*1000),"G",IF(N$2<=TODAY(),"R",""))) | AQ72: =AO72-IF(AP72="G",$E72*1000,0)+N(O72) -> 0 | AR72: =IF(N(R72)>=$E72*1000,"",IF(AND($E72>0,AQ72>=$E72*1000),"G",IF(R$2<=TODAY(),"R",""))) | AS72: =AQ72-IF(AR72="G",$E72*1000,0)+N(S72) -> 0 | AT72: =IF(N(V72)>=$E72*1000,"",IF(AND($E72>0,AS72>=$E72*1000),"G",IF(V$2<=TODAY(),"R",""))) | AU72: =AS72-IF(AT72="G",$E72*1000,0)+N(W72) -> 0 | AV72: =IF(N(Z72)>=$E72*1000,"",IF(AND($E72>0,AU72>=$E72*1000),"G",IF(Z$2<=TODAY(),"R",""))) | AW72: =AU72-IF(AV72="G",$E72*1000,0)+N(AA72) -> 0 | AX72: =IF(N(AD72)>=$E72*1000,"",IF(AND($E72>0,AW72>=$E72*1000),"G",IF(AD$2<=TODAY(),"R",""))) | AY72: =AW72-IF(AX72="G",$E72*1000,0)+N(AE72) -> 0
B73: =ROW()-3 -> 70 | C73: Mohammad Osman Goni | D73: ='Member Wise Deposit Summary'!D73 -> 1814123764 | E73: 1 | F73: =$E73*1000 -> 1000 | J73: =$E73*1000 -> 1000 | N73: =$E73*1000 -> 1000 | V73: =$E73*1000 -> 1000 | X73: 1000 | Y73: 50 | Z73: =$E73*1000 -> 1000 | AD73: =$E73*1000 -> 1000 | AH73: =F73+G73+H73+J73+K73+L73+N73+O73+P73+R73+S73+T73+V73+W73+X73+Z73+AA73+AB73+AD73+AE73+AF73 -> 7000 | AI73: =I73+M73+Q73+U73+Y73+AC73+AG73 -> 50 | AK73: 0 | AL73: =IF(N(F73)>=$E73*1000,"",IF(AND($E73>0,AK73>=$E73*1000),"G",IF(F$2<=TODAY(),"R",""))) | AM73: =AK73-IF(AL73="G",$E73*1000,0)+N(G73) -> 0 | AN73: =IF(N(J73)>=$E73*1000,"",IF(AND($E73>0,AM73>=$E73*1000),"G",IF(J$2<=TODAY(),"R",""))) | AO73: =AM73-IF(AN73="G",$E73*1000,0)+N(K73) -> 0 | AP73: =IF(N(N73)>=$E73*1000,"",IF(AND($E73>0,AO73>=$E73*1000),"G",IF(N$2<=TODAY(),"R",""))) | AQ73: =AO73-IF(AP73="G",$E73*1000,0)+N(O73) -> 0 | AR73: =IF(N(R73)>=$E73*1000,"",IF(AND($E73>0,AQ73>=$E73*1000),"G",IF(R$2<=TODAY(),"R",""))) -> R | AS73: =AQ73-IF(AR73="G",$E73*1000,0)+N(S73) -> 0 | AT73: =IF(N(V73)>=$E73*1000,"",IF(AND($E73>0,AS73>=$E73*1000),"G",IF(V$2<=TODAY(),"R",""))) | AU73: =AS73-IF(AT73="G",$E73*1000,0)+N(W73) -> 0 | AV73: =IF(N(Z73)>=$E73*1000,"",IF(AND($E73>0,AU73>=$E73*1000),"G",IF(Z$2<=TODAY(),"R",""))) | AW73: =AU73-IF(AV73="G",$E73*1000,0)+N(AA73) -> 0 | AX73: =IF(N(AD73)>=$E73*1000,"",IF(AND($E73>0,AW73>=$E73*1000),"G",IF(AD$2<=TODAY(),"R",""))) | AY73: =AW73-IF(AX73="G",$E73*1000,0)+N(AE73) -> 0
B74: =ROW()-3 -> 71 | C74: Iqbal Hossen | D74: ='Member Wise Deposit Summary'!D74 -> 00971503805124 | E74: 1 | F74: =$E74*1000 -> 1000 | J74: =$E74*1000 -> 1000 | N74: =$E74*1000 -> 1000 | R74: =$E74*1000 -> 1000 | V74: =$E74*1000 -> 1000 | Z74: =$E74*1000 -> 1000 | AD74: =$E74*1000 -> 1000 | AH74: =F74+G74+H74+J74+K74+L74+N74+O74+P74+R74+S74+T74+V74+W74+X74+Z74+AA74+AB74+AD74+AE74+AF74 -> 7000 | AI74: =I74+M74+Q74+U74+Y74+AC74+AG74 -> 0 | AK74: 0 | AL74: =IF(N(F74)>=$E74*1000,"",IF(AND($E74>0,AK74>=$E74*1000),"G",IF(F$2<=TODAY(),"R",""))) | AM74: =AK74-IF(AL74="G",$E74*1000,0)+N(G74) -> 0 | AN74: =IF(N(J74)>=$E74*1000,"",IF(AND($E74>0,AM74>=$E74*1000),"G",IF(J$2<=TODAY(),"R",""))) | AO74: =AM74-IF(AN74="G",$E74*1000,0)+N(K74) -> 0 | AP74: =IF(N(N74)>=$E74*1000,"",IF(AND($E74>0,AO74>=$E74*1000),"G",IF(N$2<=TODAY(),"R",""))) | AQ74: =AO74-IF(AP74="G",$E74*1000,0)+N(O74) -> 0 | AR74: =IF(N(R74)>=$E74*1000,"",IF(AND($E74>0,AQ74>=$E74*1000),"G",IF(R$2<=TODAY(),"R",""))) | AS74: =AQ74-IF(AR74="G",$E74*1000,0)+N(S74) -> 0 | AT74: =IF(N(V74)>=$E74*1000,"",IF(AND($E74>0,AS74>=$E74*1000),"G",IF(V$2<=TODAY(),"R",""))) | AU74: =AS74-IF(AT74="G",$E74*1000,0)+N(W74) -> 0 | AV74: =IF(N(Z74)>=$E74*1000,"",IF(AND($E74>0,AU74>=$E74*1000),"G",IF(Z$2<=TODAY(),"R",""))) | AW74: =AU74-IF(AV74="G",$E74*1000,0)+N(AA74) -> 0 | AX74: =IF(N(AD74)>=$E74*1000,"",IF(AND($E74>0,AW74>=$E74*1000),"G",IF(AD$2<=TODAY(),"R",""))) | AY74: =AW74-IF(AX74="G",$E74*1000,0)+N(AE74) -> 0
B75: =ROW()-3 -> 72 | C75: Debasish Karmaker | D75: ='Member Wise Deposit Summary'!D75 -> 1863367162 | E75: 1 | F75: =$E75*1000 -> 1000 | J75: =$E75*1000 -> 1000 | N75: =$E75*1000 -> 1000 | R75: =$E75*1000 -> 1000 | V75: =$E75*1000 -> 1000 | Z75: =$E75*1000 -> 1000 | AD75: =$E75*1000 -> 1000 | AH75: =F75+G75+H75+J75+K75+L75+N75+O75+P75+R75+S75+T75+V75+W75+X75+Z75+AA75+AB75+AD75+AE75+AF75 -> 7000 | AI75: =I75+M75+Q75+U75+Y75+AC75+AG75 -> 0 | AK75: 0 | AL75: =IF(N(F75)>=$E75*1000,"",IF(AND($E75>0,AK75>=$E75*1000),"G",IF(F$2<=TODAY(),"R",""))) | AM75: =AK75-IF(AL75="G",$E75*1000,0)+N(G75) -> 0 | AN75: =IF(N(J75)>=$E75*1000,"",IF(AND($E75>0,AM75>=$E75*1000),"G",IF(J$2<=TODAY(),"R",""))) | AO75: =AM75-IF(AN75="G",$E75*1000,0)+N(K75) -> 0 | AP75: =IF(N(N75)>=$E75*1000,"",IF(AND($E75>0,AO75>=$E75*1000),"G",IF(N$2<=TODAY(),"R",""))) | AQ75: =AO75-IF(AP75="G",$E75*1000,0)+N(O75) -> 0 | AR75: =IF(N(R75)>=$E75*1000,"",IF(AND($E75>0,AQ75>=$E75*1000),"G",IF(R$2<=TODAY(),"R",""))) | AS75: =AQ75-IF(AR75="G",$E75*1000,0)+N(S75) -> 0 | AT75: =IF(N(V75)>=$E75*1000,"",IF(AND($E75>0,AS75>=$E75*1000),"G",IF(V$2<=TODAY(),"R",""))) | AU75: =AS75-IF(AT75="G",$E75*1000,0)+N(W75) -> 0 | AV75: =IF(N(Z75)>=$E75*1000,"",IF(AND($E75>0,AU75>=$E75*1000),"G",IF(Z$2<=TODAY(),"R",""))) | AW75: =AU75-IF(AV75="G",$E75*1000,0)+N(AA75) -> 0 | AX75: =IF(N(AD75)>=$E75*1000,"",IF(AND($E75>0,AW75>=$E75*1000),"G",IF(AD$2<=TODAY(),"R",""))) | AY75: =AW75-IF(AX75="G",$E75*1000,0)+N(AE75) -> 0
B76: =ROW()-3 -> 73 | C76: Salim Uddin | D76: ='Member Wise Deposit Summary'!D76 -> 00971545732130 | E76: 1 | F76: =$E76*1000 -> 1000 | J76: =$E76*1000 -> 1000 | N76: =$E76*1000 -> 1000 | R76: =$E76*1000 -> 1000 | V76: =$E76*1000 -> 1000 | Z76: =$E76*1000 -> 1000 | AD76: =$E76*1000 -> 1000 | AH76: =F76+G76+H76+J76+K76+L76+N76+O76+P76+R76+S76+T76+V76+W76+X76+Z76+AA76+AB76+AD76+AE76+AF76 -> 7000 | AI76: =I76+M76+Q76+U76+Y76+AC76+AG76 -> 0 | AK76: 0 | AL76: =IF(N(F76)>=$E76*1000,"",IF(AND($E76>0,AK76>=$E76*1000),"G",IF(F$2<=TODAY(),"R",""))) | AM76: =AK76-IF(AL76="G",$E76*1000,0)+N(G76) -> 0 | AN76: =IF(N(J76)>=$E76*1000,"",IF(AND($E76>0,AM76>=$E76*1000),"G",IF(J$2<=TODAY(),"R",""))) | AO76: =AM76-IF(AN76="G",$E76*1000,0)+N(K76) -> 0 | AP76: =IF(N(N76)>=$E76*1000,"",IF(AND($E76>0,AO76>=$E76*1000),"G",IF(N$2<=TODAY(),"R",""))) | AQ76: =AO76-IF(AP76="G",$E76*1000,0)+N(O76) -> 0 | AR76: =IF(N(R76)>=$E76*1000,"",IF(AND($E76>0,AQ76>=$E76*1000),"G",IF(R$2<=TODAY(),"R",""))) | AS76: =AQ76-IF(AR76="G",$E76*1000,0)+N(S76) -> 0 | AT76: =IF(N(V76)>=$E76*1000,"",IF(AND($E76>0,AS76>=$E76*1000),"G",IF(V$2<=TODAY(),"R",""))) | AU76: =AS76-IF(AT76="G",$E76*1000,0)+N(W76) -> 0 | AV76: =IF(N(Z76)>=$E76*1000,"",IF(AND($E76>0,AU76>=$E76*1000),"G",IF(Z$2<=TODAY(),"R",""))) | AW76: =AU76-IF(AV76="G",$E76*1000,0)+N(AA76) -> 0 | AX76: =IF(N(AD76)>=$E76*1000,"",IF(AND($E76>0,AW76>=$E76*1000),"G",IF(AD$2<=TODAY(),"R",""))) | AY76: =AW76-IF(AX76="G",$E76*1000,0)+N(AE76) -> 0
B77: =ROW()-3 -> 74 | C77: Mujibur Rahman | D77: ='Member Wise Deposit Summary'!D77 -> 00966504512844 | E77: 1 | F77: =$E77*1000 -> 1000 | J77: =$E77*1000 -> 1000 | K77: 4000 | AD77: =$E77*1000 -> 1000 | AE77: 5000 | AH77: =F77+G77+H77+J77+K77+L77+N77+O77+P77+R77+S77+T77+V77+W77+X77+Z77+AA77+AB77+AD77+AE77+AF77 -> 12000 | AI77: =I77+M77+Q77+U77+Y77+AC77+AG77 -> 0 | AK77: 0 | AL77: =IF(N(F77)>=$E77*1000,"",IF(AND($E77>0,AK77>=$E77*1000),"G",IF(F$2<=TODAY(),"R",""))) | AM77: =AK77-IF(AL77="G",$E77*1000,0)+N(G77) -> 0 | AN77: =IF(N(J77)>=$E77*1000,"",IF(AND($E77>0,AM77>=$E77*1000),"G",IF(J$2<=TODAY(),"R",""))) | AO77: =AM77-IF(AN77="G",$E77*1000,0)+N(K77) -> 4000 | AP77: =IF(N(N77)>=$E77*1000,"",IF(AND($E77>0,AO77>=$E77*1000),"G",IF(N$2<=TODAY(),"R",""))) -> G | AQ77: =AO77-IF(AP77="G",$E77*1000,0)+N(O77) -> 3000 | AR77: =IF(N(R77)>=$E77*1000,"",IF(AND($E77>0,AQ77>=$E77*1000),"G",IF(R$2<=TODAY(),"R",""))) -> G | AS77: =AQ77-IF(AR77="G",$E77*1000,0)+N(S77) -> 2000 | AT77: =IF(N(V77)>=$E77*1000,"",IF(AND($E77>0,AS77>=$E77*1000),"G",IF(V$2<=TODAY(),"R",""))) -> G | AU77: =AS77-IF(AT77="G",$E77*1000,0)+N(W77) -> 1000 | AV77: =IF(N(Z77)>=$E77*1000,"",IF(AND($E77>0,AU77>=$E77*1000),"G",IF(Z$2<=TODAY(),"R",""))) -> G | AW77: =AU77-IF(AV77="G",$E77*1000,0)+N(AA77) -> 0 | AX77: =IF(N(AD77)>=$E77*1000,"",IF(AND($E77>0,AW77>=$E77*1000),"G",IF(AD$2<=TODAY(),"R",""))) | AY77: =AW77-IF(AX77="G",$E77*1000,0)+N(AE77) -> 5000
B78: =ROW()-3 -> 75 | C78: Md. Borhan Uddin | D78: ='Member Wise Deposit Summary'!D78 -> 1608600387 | E78: 1 | F78: =$E78*1000 -> 1000 | J78: =$E78*1000 -> 1000 | N78: =$E78*1000 -> 1000 | R78: =$E78*1000 -> 1000 | S78: 1000 | Z78: =$E78*1000 -> 1000 | AD78: =$E78*1000 -> 1000 | AE78: 2000 | AH78: =F78+G78+H78+J78+K78+L78+N78+O78+P78+R78+S78+T78+V78+W78+X78+Z78+AA78+AB78+AD78+AE78+AF78 -> 9000 | AI78: =I78+M78+Q78+U78+Y78+AC78+AG78 -> 0 | AK78: 0 | AL78: =IF(N(F78)>=$E78*1000,"",IF(AND($E78>0,AK78>=$E78*1000),"G",IF(F$2<=TODAY(),"R",""))) | AM78: =AK78-IF(AL78="G",$E78*1000,0)+N(G78) -> 0 | AN78: =IF(N(J78)>=$E78*1000,"",IF(AND($E78>0,AM78>=$E78*1000),"G",IF(J$2<=TODAY(),"R",""))) | AO78: =AM78-IF(AN78="G",$E78*1000,0)+N(K78) -> 0 | AP78: =IF(N(N78)>=$E78*1000,"",IF(AND($E78>0,AO78>=$E78*1000),"G",IF(N$2<=TODAY(),"R",""))) | AQ78: =AO78-IF(AP78="G",$E78*1000,0)+N(O78) -> 0 | AR78: =IF(N(R78)>=$E78*1000,"",IF(AND($E78>0,AQ78>=$E78*1000),"G",IF(R$2<=TODAY(),"R",""))) | AS78: =AQ78-IF(AR78="G",$E78*1000,0)+N(S78) -> 1000 | AT78: =IF(N(V78)>=$E78*1000,"",IF(AND($E78>0,AS78>=$E78*1000),"G",IF(V$2<=TODAY(),"R",""))) -> G | AU78: =AS78-IF(AT78="G",$E78*1000,0)+N(W78) -> 0 | AV78: =IF(N(Z78)>=$E78*1000,"",IF(AND($E78>0,AU78>=$E78*1000),"G",IF(Z$2<=TODAY(),"R",""))) | AW78: =AU78-IF(AV78="G",$E78*1000,0)+N(AA78) -> 0 | AX78: =IF(N(AD78)>=$E78*1000,"",IF(AND($E78>0,AW78>=$E78*1000),"G",IF(AD$2<=TODAY(),"R",""))) | AY78: =AW78-IF(AX78="G",$E78*1000,0)+N(AE78) -> 2000
B79: =ROW()-3 -> 76 | C79: Mokter Ahmed | D79: ='Member Wise Deposit Summary'!D79 -> 00966554277305 | E79: 1 | F79: =$E79*1000 -> 1000 | J79: =$E79*1000 -> 1000 | N79: =$E79*1000 -> 1000 | R79: =$E79*1000 -> 1000 | S79: 2000 | AD79: =$E79*1000 -> 1000 | AE79: 2000 | AH79: =F79+G79+H79+J79+K79+L79+N79+O79+P79+R79+S79+T79+V79+W79+X79+Z79+AA79+AB79+AD79+AE79+AF79 -> 9000 | AI79: =I79+M79+Q79+U79+Y79+AC79+AG79 -> 0 | AK79: 0 | AL79: =IF(N(F79)>=$E79*1000,"",IF(AND($E79>0,AK79>=$E79*1000),"G",IF(F$2<=TODAY(),"R",""))) | AM79: =AK79-IF(AL79="G",$E79*1000,0)+N(G79) -> 0 | AN79: =IF(N(J79)>=$E79*1000,"",IF(AND($E79>0,AM79>=$E79*1000),"G",IF(J$2<=TODAY(),"R",""))) | AO79: =AM79-IF(AN79="G",$E79*1000,0)+N(K79) -> 0 | AP79: =IF(N(N79)>=$E79*1000,"",IF(AND($E79>0,AO79>=$E79*1000),"G",IF(N$2<=TODAY(),"R",""))) | AQ79: =AO79-IF(AP79="G",$E79*1000,0)+N(O79) -> 0 | AR79: =IF(N(R79)>=$E79*1000,"",IF(AND($E79>0,AQ79>=$E79*1000),"G",IF(R$2<=TODAY(),"R",""))) | AS79: =AQ79-IF(AR79="G",$E79*1000,0)+N(S79) -> 2000 | AT79: =IF(N(V79)>=$E79*1000,"",IF(AND($E79>0,AS79>=$E79*1000),"G",IF(V$2<=TODAY(),"R",""))) -> G | AU79: =AS79-IF(AT79="G",$E79*1000,0)+N(W79) -> 1000 | AV79: =IF(N(Z79)>=$E79*1000,"",IF(AND($E79>0,AU79>=$E79*1000),"G",IF(Z$2<=TODAY(),"R",""))) -> G | AW79: =AU79-IF(AV79="G",$E79*1000,0)+N(AA79) -> 0 | AX79: =IF(N(AD79)>=$E79*1000,"",IF(AND($E79>0,AW79>=$E79*1000),"G",IF(AD$2<=TODAY(),"R",""))) | AY79: =AW79-IF(AX79="G",$E79*1000,0)+N(AE79) -> 2000
B80: =ROW()-3 -> 77 | C80: Nepal Kanti Karmaker | D80: ='Member Wise Deposit Summary'!D80 -> 1812676040 | E80: 1 | AH80: =F80+G80+H80+J80+K80+L80+N80+O80+P80+R80+S80+T80+V80+W80+X80+Z80+AA80+AB80+AD80+AE80+AF80 -> 0 | AI80: =I80+M80+Q80+U80+Y80+AC80+AG80 -> 0 | AK80: 0 | AL80: =IF(N(F80)>=$E80*1000,"",IF(AND($E80>0,AK80>=$E80*1000),"G",IF(F$2<=TODAY(),"R",""))) -> R | AM80: =AK80-IF(AL80="G",$E80*1000,0)+N(G80) -> 0 | AN80: =IF(N(J80)>=$E80*1000,"",IF(AND($E80>0,AM80>=$E80*1000),"G",IF(J$2<=TODAY(),"R",""))) -> R | AO80: =AM80-IF(AN80="G",$E80*1000,0)+N(K80) -> 0 | AP80: =IF(N(N80)>=$E80*1000,"",IF(AND($E80>0,AO80>=$E80*1000),"G",IF(N$2<=TODAY(),"R",""))) -> R | AQ80: =AO80-IF(AP80="G",$E80*1000,0)+N(O80) -> 0 | AR80: =IF(N(R80)>=$E80*1000,"",IF(AND($E80>0,AQ80>=$E80*1000),"G",IF(R$2<=TODAY(),"R",""))) -> R | AS80: =AQ80-IF(AR80="G",$E80*1000,0)+N(S80) -> 0 | AT80: =IF(N(V80)>=$E80*1000,"",IF(AND($E80>0,AS80>=$E80*1000),"G",IF(V$2<=TODAY(),"R",""))) -> R | AU80: =AS80-IF(AT80="G",$E80*1000,0)+N(W80) -> 0 | AV80: =IF(N(Z80)>=$E80*1000,"",IF(AND($E80>0,AU80>=$E80*1000),"G",IF(Z$2<=TODAY(),"R",""))) -> R | AW80: =AU80-IF(AV80="G",$E80*1000,0)+N(AA80) -> 0 | AX80: =IF(N(AD80)>=$E80*1000,"",IF(AND($E80>0,AW80>=$E80*1000),"G",IF(AD$2<=TODAY(),"R",""))) -> R | AY80: =AW80-IF(AX80="G",$E80*1000,0)+N(AE80) -> 0
B81: Total | F81: =_xlfn.AGGREGATE(9,6,F4:F80) -> 124000 | G81: =_xlfn.AGGREGATE(9,6,G4:G80) -> 0 | H81: =_xlfn.AGGREGATE(9,6,H4:H80) -> 0 | I81: =_xlfn.AGGREGATE(9,6,I4:I80) -> 0 | J81: =_xlfn.AGGREGATE(9,6,J4:J80) -> 124000 | K81: =_xlfn.AGGREGATE(9,6,K4:K80) -> 4000 | L81: =_xlfn.AGGREGATE(9,6,L4:L80) -> 0 | M81: =_xlfn.AGGREGATE(9,6,M4:M80) -> 0 | ... AI81: =_xlfn.AGGREGATE(9,6,AI4:AI80) -> 1400

Sheet Monthly Collection-2024)
A1: =HYPERLINK("#DASHBOARD!A1","⬅ Dashboard") -> ⬅ Dashboard | BE1: AUTO HELPER (do not edit): Status R=Due, G=Advance-covered; Advance balance carried month to month. Use the [+] above to expand.
B2: Member ID. | C2: Name | D2: Mobile Number | E2: Number of Shares | F2: 45292 | J2: =EDATE($F2,1) -> 45323 | N2: =EDATE($F2,2) -> 45352 | R2: =EDATE($F2,3) -> 45383 | V2: =EDATE($F2,4) -> 45413 | Z2: =EDATE($F2,5) -> 45444 | AD2: =EDATE($F2,6) -> 45474 | AH2: =EDATE($F2,7) -> 45505 | AL2: =EDATE($F2,8) -> 45536 | AP2: =EDATE($F2,9) -> 45566 | AT2: =EDATE($F2,10) -> 45597 | AX2: =EDATE($F2,11) -> 45627 | BB2: Total Deposit | BC2: Total Fine | BF2: =F$2 -> 45292 | BH2: =J$2 -> 45323 | BJ2: =N$2 -> 45352 | BL2: =R$2 -> 45383 | BN2: =V$2 -> 45413 | BP2: =Z$2 -> 45444 | BR2: =AD$2 -> 45474 | BT2: =AH$2 -> 45505 | BV2: =AL$2 -> 45536 | BX2: =AP$2 -> 45566 | BZ2: =AT$2 -> 45597 | CB2: =AX$2 -> 45627
F3: Regular Deposit | G3: Advance | H3: Due Collection | I3: Fine | J3: Regular Deposit | K3: Advance | L3: Due Collection | M3: Fine | N3: Regular Deposit | O3: Advance | P3: Due Collection | Q3: Fine | R3: Regular Deposit | S3: Advance | T3: Due Collection | U3: Fine | V3: Regular Deposit | W3: Advance | X3: Due Collection | Y3: Fine | Z3: Regular Deposit | AA3: Advance | AB3: Due Collection | AC3: Fine | AD3: Regular Deposit | AE3: Advance | AF3: Due Collection | AG3: Fine | AH3: Regular Deposit | AI3: Advance | AJ3: Due Collection | AK3: Fine | AL3: Regular Deposit | AM3: Advance | AN3: Due Collection | AO3: Fine | AP3: Regular Deposit | AQ3: Advance | AR3: Due Collection | AS3: Fine | AT3: Regular Deposit | AU3: Advance | AV3: Due Collection | AW3: Fine | AX3: Regular Deposit | AY3: Advance | AZ3: Due Collection | BA3: Fine | BE3: Carry-in adv | BF3: Status | BG3: Adv balance | BH3: Status | BI3: Adv balance | BJ3: Status | BK3: Adv balance | BL3: Status | BM3: Adv balance | BN3: Status | BO3: Adv balance | BP3: Status | BQ3: Adv balance | BR3: Status | BS3: Adv balance | BT3: Status | BU3: Adv balance | BV3: Status | BW3: Adv balance | BX3: Status | BY3: Adv balance | BZ3: Status | CA3: Adv balance | CB3: Status | CC3: Adv balance
B4: =ROW()-3 -> 1 | C4: Monjurul Islam | D4: ='Member Wise Deposit Summary'!D4 -> 1814824030 | E4: 3 | F4: =$E4*1000 -> 3000 | J4: =$E4*1000 -> 3000 | N4: =$E4*1000 -> 3000 | R4: =$E4*1000 -> 3000 | Z4: 3000 | AB4: 3000 | AC4: 150 | AD4: =$E4*1000 -> 3000 | AH4: =$E4*1000 -> 3000 | AL4: =$E4*1000 -> 3000 | AP4: =$E4*1000 -> 3000 | AT4: =$E4*1000 -> 3000 | AX4: =$E4*1000 -> 3000 | BB4: =F4+G4+H4+J4+K4+L4+N4+O4+P4+R4+S4+T4+V4+W4+X4+Z4+AA4+AB4+AD4+AE4+AF4+AH4+AI4+AJ4+AL4+AM4+AN4+AP4+AQ4+AR4+AT4+AU4+AV4+AX4+AY4+AZ4 -> 36000 | BC4: =I4+M4+Q4+U4+Y4+AC4+AG4+AK4+AO4+AS4+AW4+BA4 -> 150 | BE4: ='Monthly Collection-2023'!AY4 -> 0 | BF4: =IF(N(F4)>=$E4*1000,"",IF(AND($E4>0,BE4>=$E4*1000),"G",IF(F$2<=TODAY(),"R",""))) | BG4: =BE4-IF(BF4="G",$E4*1000,0)+N(G4) -> 0 | BH4: =IF(N(J4)>=$E4*1000,"",IF(AND($E4>0,BG4>=$E4*1000),"G",IF(J$2<=TODAY(),"R",""))) | BI4: =BG4-IF(BH4="G",$E4*1000,0)+N(K4) -> 0 | BJ4: =IF(N(N4)>=$E4*1000,"",IF(AND($E4>0,BI4>=$E4*1000),"G",IF(N$2<=TODAY(),"R",""))) | BK4: =BI4-IF(BJ4="G",$E4*1000,0)+N(O4) -> 0 | BL4: =IF(N(R4)>=$E4*1000,"",IF(AND($E4>0,BK4>=$E4*1000),"G",IF(R$2<=TODAY(),"R",""))) | BM4: =BK4-IF(BL4="G",$E4*1000,0)+N(S4) -> 0 | BN4: =IF(N(V4)>=$E4*1000,"",IF(AND($E4>0,BM4>=$E4*1000),"G",IF(V$2<=TODAY(),"R",""))) -> R | BO4: =BM4-IF(BN4="G",$E4*1000,0)+N(W4) -> 0 | BP4: =IF(N(Z4)>=$E4*1000,"",IF(AND($E4>0,BO4>=$E4*1000),"G",IF(Z$2<=TODAY(),"R",""))) | BQ4: =BO4-IF(BP4="G",$E4*1000,0)+N(AA4) -> 0 | BR4: =IF(N(AD4)>=$E4*1000,"",IF(AND($E4>0,BQ4>=$E4*1000),"G",IF(AD$2<=TODAY(),"R",""))) | BS4: =BQ4-IF(BR4="G",$E4*1000,0)+N(AE4) -> 0 | BT4: =IF(N(AH4)>=$E4*1000,"",IF(AND($E4>0,BS4>=$E4*1000),"G",IF(AH$2<=TODAY(),"R",""))) | BU4: =BS4-IF(BT4="G",$E4*1000,0)+N(AI4) -> 0 | BV4: =IF(N(AL4)>=$E4*1000,"",IF(AND($E4>0,BU4>=$E4*1000),"G",IF(AL$2<=TODAY(),"R",""))) | BW4: =BU4-IF(BV4="G",$E4*1000,0)+N(AM4) -> 0 | BX4: =IF(N(AP4)>=$E4*1000,"",IF(AND($E4>0,BW4>=$E4*1000),"G",IF(AP$2<=TODAY(),"R",""))) | BY4: =BW4-IF(BX4="G",$E4*1000,0)+N(AQ4) -> 0 | BZ4: =IF(N(AT4)>=$E4*1000,"",IF(AND($E4>0,BY4>=$E4*1000),"G",IF(AT$2<=TODAY(),"R",""))) | CA4: =BY4-IF(BZ4="G",$E4*1000,0)+N(AU4) -> 0 | CB4: =IF(N(AX4)>=$E4*1000,"",IF(AND($E4>0,CA4>=$E4*1000),"G",IF(AX$2<=TODAY(),"R",""))) | CC4: =CA4-IF(CB4="G",$E4*1000,0)+N(AY4) -> 0
